Workbook

Sheet コスト見積もり
A1: AWS＋ROSA コスト見積もり（東京リージョン ap-northeast-1）
A2: 構成の根拠: doc/basic-design/06-infra-network-design.md（D-U6-01〜14）ほか設計書。ROSAサービス料は AWS 公式料金ページから取得（2026-08時点）。AWSインフラの単価は公式ページが動的読み込みのため取得できず、青字の入力欄としている
A3: ★青字セル＝入力欄（未取得）。AWS Pricing Calculator または各サービスの公式料金ページから値を入れると、以降の集計は自動計算される。数量は設計値（上限台数・構成）に基づくが、規模別の按分は推定
A5: ■ 前提（入力）
A6: 項目 | B6: 値 | C6: 単位 | D6: 備考
A7: 対象リージョン | B7: 東京 ap-northeast-1 | C7: — | D7: 前提P-15。予備地域は平時ゼロのため本表に含めない
A8: 月間稼働時間 | B8: 730 | C8: 時間 | D8: 24時間×365日÷12
A9: 為替レート | B9: 150 | C9: 円/USD | D9: 円換算用の入力値。実勢に合わせて変更
A10: 想定利用者数 シナリオ1 | B10: 1000000 | C10: 人 | D10: 小規模。最小構成想定
A11: 想定利用者数 シナリオ2 | B11: 5000000 | C11: 人 | D11: 更新メモ「100〜500万ユーザー」の上限
A12: 想定利用者数 シナリオ3 | B12: 10000000 | C12: 人 | D12: 前提P-02の凍結値（設計上の上限）
A14: ■ ROSA サービス料（AWS公式料金ページから取得）
A15: 区分 | B15: 項目 | C15: 単価 | D15: 単位 | E15: 出典 | F15: 状態
A16: ROSA | B16: 制御部分の料金（hosted control planes） | C16: 0.25 | D16: クラスタ・時 | E16: https://aws.amazon.com/rosa/pricing/ | F16: 取得済
A17: ROSA | B17: ワーカーノードのサービス料（従量） | C17: 0.171 | D17: 4vCPU・時 | E17: https://aws.amazon.com/rosa/pricing/ | F17: 取得済
A18: ROSA | B18: 同・年額換算（従量） | C18: 1500 | D18: 4vCPU・年 | E18: https://aws.amazon.com/rosa/pricing/ | F18: 取得済
A19: ROSA | B19: 同・1年契約 | C19: 1000 | D19: 4vCPU・年 | E19: https://aws.amazon.com/rosa/pricing/ | F19: 取得済
A20: ROSA | B20: 同・3年契約 | C20: 667 | D20: 4vCPU・年 | E20: https://aws.amazon.com/rosa/pricing/ | F20: 取得済
A21: ※ ROSAのサービス料は全対応リージョンで同一。契約による割引は従量比で1年33%・3年55%。製品サポートは基盤に内包され追加費用は発生しない（前提P-01）
A23: ■ AWSインフラ費 明細（数量＝月間の課金単位数。単価は青字の入力欄）
A24: 区分 | B24: リソース／サービス | C24: 用途（設計上の根拠） | D24: 数量の考え方 | E24: 数量 100万人 | F24: 数量 500万人 | G24: 数量 1000万人 | H24: 単位 | I24: 単価(USD) | J24: 月額 100万人 | K24: 月額 500万人 | L24: 月額 1000万人 | M24: 単価の出典URL | N24: 備考
A25: 計算 | B25: ROSA 計算ノード（認証製品専用・仲介側） | C25: 認証処理の実行。D-U6-04で2系統に分離、上限9台 | D25: 台数×730時間。100万=3台／500万=6台／1000万=9台（上限） | E25: 2190 | F25: 4380 | G25: 6570 | H25: インスタンス時間 | I25: 0.1819 | J25: =E25*$I25 -> 398.361 | K25: =F25*$I25 -> 796.722 | L25: =G25*$I25 -> 1195.083 | M25: https://aws.amazon.com/jp/ec2/pricing/on-demand/ | N25: c7g.xlarge（D-U6-04）
A26: 計算 | B26: ROSA 計算ノード（認証製品専用・自社受け皿側） | C26: パスワード検証が支配的。D-U6-04で上限18台 | D26: 台数×730時間。100万=3台／500万=9台／1000万=18台（上限） | E26: 2190 | F26: 6570 | G26: 13140 | H26: インスタンス時間 | I26: 0.1819 | J26: =E26*$I26 -> 398.361 | K26: =F26*$I26 -> 1195.083 | L26: =G26*$I26 -> 2390.166 | M26: https://aws.amazon.com/jp/ec2/pricing/on-demand/ | N26: c7g.xlarge（D-U6-04）
A27: 計算 | B27: ROSA 計算ノード（管理系）×2クラスタ | C27: 入口・監視・イメージ配布・受け口。規模と監視量で準静的 | D27: 3台×2クラスタ×730時間で固定 | E27: 4380 | F27: 4380 | G27: 4380 | H27: インスタンス時間 | I27: 0.091 | J27: =E27*$I27 -> 398.58 | K27: =F27*$I27 -> 398.58 | L27: =G27*$I27 -> 398.58 | M27: https://aws.amazon.com/jp/ec2/pricing/on-demand/ | N27: c7g.large（default/infra Pool）
A28: 計算 | B28: ROSA サービス料（制御部分） | C28: D-U6-03で2クラスタ構成 | D28: 0.25ドル×2クラスタ×730時間 | E28: 1460 | F28: 1460 | G28: 1460 | H28: クラスタ時間 | I28: 0.25 | J28: =E28*$I28 -> 365 | K28: =F28*$I28 -> 365 | L28: =G28*$I28 -> 365 | M28: https://aws.amazon.com/jp/rosa/pricing/ | N28: 取得済（変更なし）
A29: 計算 | B29: ROSA サービス料（ワーカーノード） | C29: 4vCPUあたりの従量。ノードのvCPU総数に比例 | D29: ノード合計vCPU÷4×730時間。1台4vCPU想定 | E29: 1642 | F29: 3103 | G29: 5658 | H29: 4vCPU時間 | I29: 0.171 | J29: =E29*$I29 -> 280.782 | K29: =F29*$I29 -> 530.613 | L29: =G29*$I29 -> 967.518 | M29: https://aws.amazon.com/jp/rosa/pricing/ | N29: 取得済（変更なし）
A30: 計算 | B30: EBS（ノード用ブロックストレージ） | C30: 各ノードのOS・作業領域 | D30: 認証製品用ノード120GB＋管理系ノード100GB（D-U6-16）。100万=KC6台+管理6台／500万=KC15台+管理6台／1000万=KC27台+管理6台 | E30: 1320 | F30: 2400 | G30: 3840 | H30: GB・月 | I30: 0.096 | J30: =E30*$I30 -> 126.72 | K30: =F30*$I30 -> 230.4 | L30: =G30*$I30 -> 368.64 | M30: https://aws.amazon.com/jp/ebs/pricing/ | N30: D-U6-16でgp3・KC Pool 120GB（ログバッファ30GB明示）・infra Pool 100GBに確定。旧値は一律100GB前提
A31: DB | B31: Aurora インスタンス（認証用・書込1＋読取2） | C31: D-U6-07。db.r7g.xlarge想定の3拠点構成 | D31: 3台×730時間 | E31: 2190 | F31: 2190 | G31: 2190 | H31: インスタンス時間 | I31: 0.665 | J31: =E31*$I31 -> 1456.35 | K31: =F31*$I31 -> 1456.35 | L31: =G31*$I31 -> 1456.35 | M31: https://aws.amazon.com/jp/rds/aurora/pricing/ | N31: db.r7g.xlarge 標準ストレージ構成
A32: DB | B32: Aurora インスタンス（権限系・書込1＋読取2） | C32: D-U6-07。認証用と別系統・別鍵で分離 | D32: 3台×730時間 | E32: 2190 | F32: 2190 | G32: 2190 | H32: インスタンス時間 | I32: 0.665 | J32: =E32*$I32 -> 1456.35 | K32: =F32*$I32 -> 1456.35 | L32: =G32*$I32 -> 1456.35 | M32: https://aws.amazon.com/jp/rds/aurora/pricing/ | N32: db.r7g.xlarge 標準ストレージ構成
A33: DB | B33: Aurora ストレージ | C33: 利用者・セッション・権限・ID対応表・射影 | D33: 利用者数に比例。1人あたり約2KB＋索引 | E33: 200 | F33: 1000 | G33: 2000 | H33: GB・月 | I33: 0.12 | J33: =E33*$I33 -> 24 | K33: =F33*$I33 -> 120 | L33: =G33*$I33 -> 240 | M33: https://aws.amazon.com/jp/rds/aurora/pricing/ | N33: 1人あたり約2KB＋索引
A34: DB | B34: Aurora I/O | C34: 認証時の読み書き。100req/sあたり書込1,400 IOPSが公式算定式 | D34: ログイン回数に比例（月間認証回数×IO係数） | E34: 50000000 | F34: 250000000 | G34: 500000000 | H34: I/O 件 | I34: 2.4e-07 | J34: =E34*$I34 -> 12 | K34: =F34*$I34 -> 60 | L34: =G34*$I34 -> 120 | M34: https://aws.amazon.com/jp/rds/aurora/pricing/ | N34: ※単位を「100万リクエスト」から「I/O 件」へ是正。件数×単価で計算する
A35: DB | B35: Aurora バックアップストレージ | C35: 時点復元1〜35日＋定期取得の控え | D35: データ量と同程度＋世代分 | E35: 400 | F35: 2000 | G35: 4000 | H35: GB・月 | I35: 0.023 | J35: =E35*$I35 -> 9.2 | K35: =F35*$I35 -> 46 | L35: =G35*$I35 -> 92 | M35: https://aws.amazon.com/jp/rds/aurora/pricing/
A36: DB | B36: Aurora グローバル複製（予備地域へのデータ保全） | C36: D-U8-14のL1。計算資源は平時ゼロだがデータ層は維持 | D36: 複製データ量。転送＋предスト保管 | E36: 200 | F36: 1000 | G36: 2000 | H36: GB・月 | I36: 0.12 | J36: =E36*$I36 -> 24 | K36: =F36*$I36 -> 120 | L36: =G36*$I36 -> 240 | M36: https://aws.amazon.com/jp/rds/aurora/pricing/ | N36: ※DR案②③でのみ発生。案①では0
A37: NW | B37: 内部接続点（内部NLB）×2 | C37: D-U6-05。管理APIへの到達。インターネット非露出 | D37: 2台×730時間＋処理容量単位 | E37: 1460 | F37: 1460 | G37: 1460 | H37: NLB時間 | I37: 0.0243 | J37: =E37*$I37 -> 35.478 | K37: =F37*$I37 -> 35.478 | L37: =G37*$I37 -> 35.478 | M37: https://aws.amazon.com/jp/elasticloadbalancing/pricing/ | N37: 別途 LCU 0.006/時
A38: NW | B38: 負荷分散装置（ALB） | C38: D-U6-11の生命線。管理画面の固定拒否ルールを評価 | D38: 1台×730時間＋処理容量単位 | E38: 730 | F38: 730 | G38: 730 | H38: ALB時間 | I38: 0.0243 | J38: =E38*$I38 -> 17.739 | K38: =F38*$I38 -> 17.739 | L38: =G38*$I38 -> 17.739 | M38: https://aws.amazon.com/jp/elasticloadbalancing/pricing/ | N38: 別途 LCU
A39: NW | B39: 配信網（CloudFront） | C39: D-U6-04の入口3系統。画面配信とAPI入口 | D39: データ転送量とリクエスト数 | E39: 500 | F39: 2500 | G39: 5000 | H39: GB | I39: 0.114 | J39: =E39*$I39 -> 57 | K39: =F39*$I39 -> 285 | L39: =G39*$I39 -> 570 | M39: https://aws.amazon.com/jp/cloudfront/pricing/ | N39: 日本向け転送。別途リクエスト 0.0000012/件
A40: NW | B40: 不正アクセス遮断（WAF） | C40: D-U7-17。ただし入口側は他組織管理 | D40: ルール数＋リクエスト数。自管理分のみ | E40: 10 | F40: 50 | G40: 100 | H40: 100万リクエスト | I40: 0.6 | J40: =E40*$I40 -> 6 | K40: =F40*$I40 -> 30 | L40: =G40*$I40 -> 60 | M40: https://aws.amazon.com/jp/waf/pricing/ | N40: 0.0000006/件×100万。別途 Rule 1.0/月
A41: NW | B41: 私設接続（PrivateLink） | C41: D-U6-06。2つの受け皿の間を単方向で接続 | D41: エンドポイント×730時間＋転送量 | E41: 1460 | F41: 1460 | G41: 1460 | H41: エンドポイント時間 | I41: 0.014 | J41: =E41*$I41 -> 20.44 | K41: =F41*$I41 -> 20.44 | L41: =G41*$I41 -> 20.44 | M41: https://aws.amazon.com/jp/privatelink/pricing/
A42: NW | B42: 接続点群（VPCエンドポイント） | C42: D-U6-07の外部通信を持たない構成。各サービスへの私設経路 | D42: 20種×3拠点×730時間 | E42: 7300 | F42: 7300 | G42: 7300 | H42: エンドポイント時間 | I42: 0.014 | J42: =E42*$I42 -> 102.2 | K42: =F42*$I42 -> 102.2 | L42: =G42*$I42 -> 102.2 | M42: https://aws.amazon.com/jp/privatelink/pricing/
A43: NW | B43: 名前解決（Route 53 私設ゾーン） | C43: DU-U6-13。内外で解決結果を分ける構成 | D43: ゾーン数＋問い合わせ数 | E43: 10000000 | F43: 50000000 | G43: 100000000 | H43: クエリ | I43: 4e-07 | J43: =E43*$I43 -> 4 | K43: =F43*$I43 -> 20 | L43: =G43*$I43 -> 40 | M43: https://aws.amazon.com/jp/route53/pricing/ | N43: ※単位を「100万クエリ」から「クエリ」へ是正。別途ゾーン 0.50/月
A44: NW | B44: データ転送（拠点間） | C44: 3拠点分散のため拠点をまたぐ通信が発生 | D44: クラスタ内・DB複製の拠点間転送量 | E44: 100 | F44: 500 | G44: 1000 | H44: GB | I44: 0.09 | J44: =E44*$I44 -> 9 | K44: =F44*$I44 -> 45 | L44: =G44*$I44 -> 90 | M44: https://aws.amazon.com/jp/ec2/pricing/on-demand/ | N44: 東京→大阪
A45: NW | B45: データ転送（インターネット向け） | C45: 利用者への画面・通行証の応答 | D45: 配信網経由分を除いた直接転送 | E45: 50 | F45: 250 | G45: 500 | H45: GB | I45: 0.114 | J45: =E45*$I45 -> 5.7 | K45: =F45*$I45 -> 28.5 | L45: =G45*$I45 -> 57 | M45: https://aws.amazon.com/jp/ec2/pricing/on-demand/ | N45: CloudFront経由のため直接転送は限定的
A46: APP | B46: 関数実行（管理API） | C46: D-U6-06。認証製品と別の障害ドメインに分離 | D46: 呼び出し回数×実行時間×メモリ | E46: 10000000 | F46: 30000000 | G46: 50000000 | H46: リクエスト | I46: 2e-07 | J46: =E46*$I46 -> 2 | K46: =F46*$I46 -> 6 | L46: =G46*$I46 -> 10 | M46: https://aws.amazon.com/jp/lambda/pricing/ | N46: ※単位を「100万リクエスト」から「リクエスト」へ是正。別途 GB秒 0.0000166667
A47: APP | B47: 関数実行（糊付け：影ユーザ制御・伝播・通知配信） | C47: DU-U3-05、DU-U10-03。非同期の連結処理 | D47: イベント数に比例 | E47: 5000000 | F47: 15000000 | G47: 25000000 | H47: リクエスト | I47: 2e-07 | J47: =E47*$I47 -> 1 | K47: =F47*$I47 -> 3 | L47: =G47*$I47 -> 5 | M47: https://aws.amazon.com/jp/lambda/pricing/ | N47: ※単位を「100万リクエスト」から「リクエスト」へ是正。別途 GB秒
A48: APP | B48: API入口（API Gateway） | C48: D-U6-06。通行証の一次検証と流量制限 | D48: リクエスト数 | E48: 10000000 | F48: 30000000 | G48: 50000000 | H48: リクエスト | I48: 1.29e-06 | J48: =E48*$I48 -> 12.9 | K48: =F48*$I48 -> 38.7 | L48: =G48*$I48 -> 64.5 | M48: https://aws.amazon.com/jp/api-gateway/pricing/ | N48: ※単位を「100万リクエスト」から「リクエスト」へ是正。HTTP API
A49: APP | B49: イベントバス（EventBridge） | C49: D-U6-02のアカウント跨ぎ8経路。削除伝播と初回通知 | D49: 発行イベント数 | E49: 5000000 | F49: 15000000 | G49: 25000000 | H49: イベント | I49: 1e-07 | J49: =E49*$I49 -> 0.5 | K49: =F49*$I49 -> 1.5 | L49: =G49*$I49 -> 2.5 | M49: https://aws.amazon.com/jp/eventbridge/pricing/ | N49: ※単位を「100万イベント」から「イベント」へ是正。8Kチャンク
A50: APP | B50: キー・バリューストア（DynamoDB） | C50: D-U7-04の不正検知の履歴、顧客開示用の監査ログ射影 | D50: 書込・読込・保管量 | E50: 5000000 | F50: 25000000 | G50: 50000000 | H50: 書込単位 | I50: 8.9e-07 | J50: =E50*$I50 -> 4.45 | K50: =F50*$I50 -> 22.25 | L50: =G50*$I50 -> 44.5 | M50: https://aws.amazon.com/jp/dynamodb/pricing/ | N50: ※単位を「100万リクエスト」から「書込単位」へ是正。オンデマンド
A51: セキュリティ | B51: 暗号鍵（KMS CMK） | C51: D-U7-01。3階層6アカウント写像で初期10種 | D51: 10鍵×月額＋API呼び出し数 | E51: 10 | F51: 10 | G51: 10 | H51: 鍵・月 | I51: 1 | J51: =E51*$I51 -> 10 | K51: =F51*$I51 -> 10 | L51: =G51*$I51 -> 10 | M51: https://aws.amazon.com/jp/kms/pricing/ | N51: 別途 API 0.000003/件
A52: セキュリティ | B52: 秘密情報の保管（Secrets Manager） | C52: D-U7-01。90日自動入れ替え対象 | D52: 顧客別の接続用秘密情報＋内部用 | E52: 30 | F52: 30 | G52: 30 | H52: シークレット・月 | I52: 0.4 | J52: =E52*$I52 -> 12 | K52: =F52*$I52 -> 12 | L52: =G52*$I52 -> 12 | M52: https://aws.amazon.com/jp/secrets-manager/pricing/
A53: セキュリティ | B53: 自社認証局（Private CA） | C53: DU-U6-11。内部接続点の通信暗号化 | D53: 認証局×月額＋証明書発行数 | E53: 1 | F53: 1 | G53: 1 | H53: CA・月 | I53: 400 | J53: =E53*$I53 -> 400 | K53: =F53*$I53 -> 400 | L53: =G53*$I53 -> 400 | M53: https://aws.amazon.com/jp/private-ca/pricing/ | N53: 汎用モード400 USD/月。D-U6-15で短期証明書モード（50 USD/月）を第一候補に決定。切替可否は有効期間の検証待ち。差は年420万円
A54: セキュリティ | B54: 変更不能な控え（AWS Backup Vault Lock） | C54: D-U8-14のL3。ランサム対策の最終防衛線 | D54: 保管量＋別地域複製 | E54: 400 | F54: 2000 | G54: 4000 | H54: GB・月 | I54: 0.09 | J54: =E54*$I54 -> 36 | K54: =F54*$I54 -> 180 | L54: =G54*$I54 -> 360 | M54: https://aws.amazon.com/jp/backup/pricing/
A55: 運用 | B55: ログ（即時参照90日） | C55: D-U9-05の3層構造のうちHot層 | D55: 取込量＋保管量 | E55: 100 | F55: 500 | G55: 1000 | H55: GB | I55: 0.76 | J55: =E55*$I55 -> 76 | K55: =F55*$I55 -> 380 | L55: =G55*$I55 -> 760 | M55: https://aws.amazon.com/jp/cloudwatch/pricing/ | N55: 取り込み。別途保管 0.033/GB-月
A56: 運用 | B56: ログ検索基盤（1年） | C56: D-U9-05のCold検索層 | D56: インスタンス＋ストレージ | E56: 1460 | F56: 2190 | G56: 2920 | H56: インスタンス時間 | I56: 0.164 | J56: =E56*$I56 -> 239.44 | K56: =F56*$I56 -> 359.16 | L56: =G56*$I56 -> 478.88 | M56: https://aws.amazon.com/jp/opensearch-service/pricing/ | N56: m6g.large.search 想定
A57: 運用 | B57: 長期保管（S3＋Glacier Deep Archive） | C57: D-U7-13。改ざん不能モードで7年 | D57: 累積保管量（7年分の逓増） | E57: 5000 | F57: 25000 | G57: 50000 | H57: GB・月 | I57: 0.002 | J57: =E57*$I57 -> 10 | K57: =F57*$I57 -> 50 | L57: =G57*$I57 -> 100 | M57: https://aws.amazon.com/jp/s3/glacier/pricing/ | N57: Deep Archive
A58: 運用 | B58: メール送信（SES） | C58: DU-U6-12。通知・招待メール | D58: 送信数 | E58: 100000 | F58: 500000 | G58: 1000000 | H58: 通 | I58: 0.0001 | J58: =E58*$I58 -> 10 | K58: =F58*$I58 -> 50 | L58: =G58*$I58 -> 100 | M58: https://aws.amazon.com/jp/ses/pricing/ | N58: ※単位を「1000通」から「通」へ是正
A59: 運用 | B59: 外形監視（Canary） | C59: D-U9-16。認証実装漏れの検知 | D59: 実行回数×2クラスタ | E59: 131400 | F59: 131400 | G59: 131400 | H59: 実行回数 | I59: 0.0019 | J59: =E59*$I59 -> 249.66 | K59: =F59*$I59 -> 249.66 | L59: =G59*$I59 -> 249.66 | M59: https://aws.amazon.com/jp/cloudwatch/pricing/ | N59: 3系統
A60: 合計（AWSインフラ＋ROSAサービス料） | J60: =SUM(J25:J59) -> 6271.211 | K60: =SUM(K25:K59) -> 9121.725 | L60: =SUM(L25:L59) -> 12879.584 | N60: =IF(COUNTBLANK($I$25:$I$59)>0,"⚠ 単価未入力 "&COUNTBLANK($I$25:$I$59)&"件（青字セル）","✓ 全単価が入力済み") -> ✓ 全単価が入力済み
A62: ■ 区分別 月額小計
A63: 区分 | B63: 項目数 | C63: 月額 100万人 | D63: 月額 500万人 | E63: 月額 1000万人
A64: 計算 | B64: =COUNTIF($A$25:$A$59,$A64) -> 6 | C64: =SUMIF($A$25:$A$59,$A64,$J$25:$J$59) -> 1967.804 | D64: =SUMIF($A$25:$A$59,$A64,$K$25:$K$59) -> 3516.398 | E64: =SUMIF($A$25:$A$59,$A64,$L$25:$L$59) -> 5684.987
A65: DB | B65: =COUNTIF($A$25:$A$59,$A65) -> 6 | C65: =SUMIF($A$25:$A$59,$A65,$J$25:$J$59) -> 2981.9 | D65: =SUMIF($A$25:$A$59,$A65,$K$25:$K$59) -> 3258.7 | E65: =SUMIF($A$25:$A$59,$A65,$L$25:$L$59) -> 3604.7
A66: NW | B66: =COUNTIF($A$25:$A$59,$A66) -> 9 | C66: =SUMIF($A$25:$A$59,$A66,$J$25:$J$59) -> 257.557 | D66: =SUMIF($A$25:$A$59,$A66,$K$25:$K$59) -> 584.357 | E66: =SUMIF($A$25:$A$59,$A66,$L$25:$L$59) -> 992.857
A67: APP | B67: =COUNTIF($A$25:$A$59,$A67) -> 5 | C67: =SUMIF($A$25:$A$59,$A67,$J$25:$J$59) -> 20.85 | D67: =SUMIF($A$25:$A$59,$A67,$K$25:$K$59) -> 71.45 | E67: =SUMIF($A$25:$A$59,$A67,$L$25:$L$59) -> 126.5
A68: セキュリティ | B68: =COUNTIF($A$25:$A$59,$A68) -> 4 | C68: =SUMIF($A$25:$A$59,$A68,$J$25:$J$59) -> 458 | D68: =SUMIF($A$25:$A$59,$A68,$K$25:$K$59) -> 602 | E68: =SUMIF($A$25:$A$59,$A68,$L$25:$L$59) -> 782
A69: 運用 | B69: =COUNTIF($A$25:$A$59,$A69) -> 5 | C69: =SUMIF($A$25:$A$59,$A69,$J$25:$J$59) -> 585.1 | D69: =SUMIF($A$25:$A$59,$A69,$K$25:$K$59) -> 1088.82 | E69: =SUMIF($A$25:$A$59,$A69,$L$25:$L$59) -> 1688.54
A70: 合計 | B70: =SUM(B64:B69) -> 35 | C70: =SUM(C64:C69) -> 6271.211 | D70: =SUM(D64:D69) -> 9121.725 | E70: =SUM(E64:E69) -> 12879.584 | F70: =IF(B70=COUNTA($B$25:$B$59),"✓ 明細行数と一致","⚠ 不一致") -> ✓ 明細行数と一致
A72: ■ 総括（月額・年額・3年総額）
A73: 項目 | B73: 100万人 | C73: 500万人 | D73: 1000万人 | E73: 備考
A74: 月額（USD） | B74: =J60 -> 6271.211 | C74: =K60 -> 9121.725 | D74: =L60 -> 12879.584 | E74: 明細の合計
A75: 月額（円） | B75: =B74*$B$9 -> 940681.65 | C75: =C74*$B$9 -> 1368258.7 | D75: =D74*$B$9 -> 1931937.6 | E75: 為替レートは前提の入力値
A76: 年額（USD） | B76: =B74*12 -> 75254.532 | C76: =C74*12 -> 109460.7 | D76: =D74*12 -> 154555.01 | E76: 月額×12
A77: 3年総額（USD） | B77: =B76*3 -> 225763.6 | C77: =C76*3 -> 328382.1 | D77: =D76*3 -> 463665.02 | E77: 年額×3。ROSAの3年契約割引は未反映
A78: 3年総額（円） | B78: =B77*$B$9 -> 33864539 | C78: =C77*$B$9 -> 49257315 | D78: =D77*$B$9 -> 69549754
A79: 利用者1人あたり月額（円） | B79: =IFERROR(B75/$B$10,0) -> 0.94068165 | C79: =IFERROR(C75/$B$11,0) -> 0.27365175 | D79: =IFERROR(D75/$B$12,0) -> 0.19319376 | E79: 月額円÷利用者数
A80: 参考: 設計書の概算（月額USD） | B80: 2032 | C80: 2032 | D80: 2032 | E80: D-U6-05。東京2クラスタの基盤部分のみ・±30%。本表はデータベース等を含むため範囲が広い
A82: ■ 2026-08-17 単価取得後の是正メモ
A83: ① Aurora I/O（34行）: 単位表記が「100万リクエスト」だったが数量は件数のため「I/O 件」へ是正。単価0.00000024 USD/件を件数に直接掛ける。100万件単位で掛けると100万倍ずれる
A84: ② 同様の単位是正: Route 53（43行）／関数実行2件（46・47行）／API入口（48行）／イベントバス（49行）／DynamoDB（50行）／メール送信（58行）も「100万〜」「1000通」表記を実数単位へ是正済み
A85: ="③ 総括の開き: 設計書の概算 2,032 USD に対し、今回の積み上げは "&TEXT(SUM(J25:J59),"#,##0")&" USD（100万人）で約3倍。主因は Aurora インスタンス2系統×3台（"&TEXT(J31+J32,"#,##0")&" USD）。どちらが正か要精査" -> ③ 総括の開き: 設計書の概算 2,032 USD に対し、今回の積み上げは 6,271 USD（100万人）で約3倍。主因は Aurora インスタンス2系統×3台（2,913 USD）。どちらが正か要精査
A86: ④ 未反映の割引: ROSAの1年契約（33%）／3年契約（55%）は未適用。適用すれば計算区分が下がる
A87: ⑤ Private CA（53行）: 400 USD/月は汎用モードの単価。短期証明書モードなら 50 USD/月で、年420万円の差になる
A88: ⑥ 予備地域（大阪）の費用は本シートに含まない。別シート「DR案別コスト」を参照（案①0.9万円／案②1.7万円／案③38万円・月額100万人規模）

Sheet 設計決定一覧
A1: 設計決定一覧（基本設計 02〜10 の正式決定）
A2: 出典: github.com/suepie/aws-atuh-poc doc/basic-design/ commit 9511a58 ／ Gitからの派生ビュー（読み取り専用）。2026-08-12 網羅性再監査で16件追加
A4: 決定名（何を決めたか） | B4: 設計単元 | C4: 決定内容 | D4: 内部ID（Git内の採番） | E4: 出典
A5: Realm構成 | B5: U2 Keycloak論理 | C5: Broker KC=単一Realm『broker』+Organizations、IdP-KC=単一Realm『idp』+Organizations。masterはKeycloak自体の管理専用で業務ユーザ・Clientを置かない。Realm名はissuer URLに埋まり変更不可のため普遍的短名 | D5: U2 §2.1.1 | E5: basic-design/02-keycloak-logical-design.md
A6: Organizationsの使い方 | B6: U2 Keycloak論理 | C6: Brokerは全顧客（IdPあり・なし問わず）を1顧客=1Orgで登録。顧客IdPは必ず当該顧客Orgに紐付け（グローバルIdP禁止）。IdP-KCはIdPなし顧客のみ登録。Org attributeは表示名とhrd_modeのみ、課金・契約メタは持たない | D6: U2 §2.1.2 | E6: basic-design/02-keycloak-logical-design.md
A7: Org命名規則・alias規則 | B7: U2 Keycloak論理 | C7: Org alias=小文字英数字2〜20文字・先頭英字・ハイフン禁止・作成後変更不可。tenant_idクレーム値とログインIDのtenantプレフィックスと完全一致。master/admin/broker/idp/api/scim/test等は予約語で使用禁止 | D7: U2 §2.1.3 | E7: basic-design/02-keycloak-logical-design.md
A8: IdP alias規則 | B8: U2 Keycloak論理 | C8: 顧客IdP alias=<orgAlias>-<proto><NN>（例 acme-oidc01）。IdP製品名はdisplayNameのみに記載しaliasには含めない（製品乗換時にalias変更＝顧客側再設定を避ける） | D8: U2 §2.1.4 | E8: basic-design/02-keycloak-logical-design.md
A9: 2-tier間フェデの位置付け | B9: U2 Keycloak論理 | C9: Brokerから見たIdP-KCは「OIDC IdPの1つ」として登録。IdP-KC側ではBrokerをOIDC confidential clientとして登録 | D9: U2 §2.2.1 | E9: basic-design/02-keycloak-logical-design.md
A10: Broker側IdP登録（IdP-KC向け） | B10: U2 Keycloak論理 | C10: IdPなし顧客共通の単一OIDC IdPエントリ『idpkc-oidc01』を作り、IdPなし顧客の全Orgに紐付け。loginHint=true / hideOnLoginPage=true / trustEmail=false / syncMode=IMPORT / storeToken=false | D10: U2 §2.2.2 | E10: basic-design/02-keycloak-logical-design.md
A11: IdP-KC側Client登録（Broker向け） | B11: U2 Keycloak論理 | C11: client_id=broker-rp。Confidential・Standard Flowのみ（Implicit/Direct Access/Service Account無効）。redirect URIは完全一致1本のみ（ワイルドカード禁止）。Phase 1=client_secret_post、Phase 2でprivate_key_jwtへ昇格。Web Origins/CORSなし | D11: U2 §2.2.3 | E11: basic-design/02-keycloak-logical-design.md
A12: 2-tier間のクレーム受け渡し | B12: U2 Keycloak論理 | C12: IdP-KC側に専用Client Scope『broker-federation』を作りMapperを集約（tenant_id / preferred_username / amr / email の4種）。JIT突合キーはtenant_id+persistent sub、emailは補助。Phase 1ではIdP-KCのrolesをBrokerへ伝播しない | D12: U2 §2.2.4 | E12: basic-design/02-keycloak-logical-design.md
A13: ログアウト連鎖 | B13: U2 Keycloak論理 | C13: idpkc-oidc01にbackchannelSupported=trueを設定し、Brokerのログアウト時にIdP-KCセッションも常時破棄（自社基盤のため越境問題なし）。storeToken=false下でのid_token_hint取り回しは実機確認が必要 | D13: U2 §2.2.5 #1 | E13: basic-design/02-keycloak-logical-design.md
A14: IdP-KC側Realmセッション TTL | B14: U2 Keycloak論理 | C14: Realm『idp』のSSO Session Idle/MaxをBroker Realmと同値（Idle 1h / Max 24h）に固定。IaCで両Realm共通変数化し独立変更を構造的に防ぐ | D14: U2 §2.2.5 #2 | E14: basic-design/02-keycloak-logical-design.md
A15: ステップアップ（AAL3）の転送 | B15: U2 Keycloak論理 | C15: 認証元がidpkc-oidc01の場合、IdP-KCへacr_values="3"+prompt=loginを付けて再リダイレクト。IdP-KC側にもACR-to-LoAマッピング（1/2/3）を定義し、amrで返してmfa_indicator Mapper（FORCE）がBroker側acr判定に反映 | D15: U2 §2.2.5 #3 | E15: basic-design/02-keycloak-logical-design.md
... A189: 忘れられる権利と7年間の改ざん不能監査の境界を明文化 | B189: U10 連携・移行 | C189: 利用者からの消去要求と、改ざん不能で7年保管する監査証跡は正面から衝突するため、「消去する対象」と「不変の監査側で墓標化・仮名化して残す対象」の境界を文書で定める（都度判断は不可）。既定は、個人データ本体は停止処理のうえ次段階の物理削除へ／監査ログ内の主体識別子は仮名化して保持（法令上の保持根拠がある）。認可判定ログ内の識別子の仮名化も同じ扱いで整合させる。境界の最終確定は顧客確認 B-RTBF-1 | D189: D-U10-13b | E189: basic-design/10-integration-migration-design.md §10.5

Sheet ADR一覧
A1: ADR（アーキテクチャ決定記録）一覧 — 全67本
A2: 出典: doc/adr/00-index.md ＋ 各ADRファイル（commit 9511a58 時点）。Gitからの派生ビュー（読み取り専用）
A3: ★ADR-061は2026-08-18にGit側の索引（00-index.md）へ登録済み（APIプラットフォーム側のスコープ）。本表では実ファイルから収録している
A5: ADR番号 | B5: 表題 | C5: ステータス | D5: 日付 | E5: 備考・更新履歴 | G5: ステータス別
A6: ADR-001 | B6: PoC第1パターンとしてCognitoハイブリッド構成を採用 | C6: Accepted | D6: 2026-03-17 | G6: ステータス | H6: 件数
A7: ADR-002 | B7: 認可方式としてLambda Authorizerを採用 | C7: Accepted | D7: 2026-03-17 | G7: Proposed | H7: =COUNTIF($C$6:$C$72,$G7) -> 48
A8: ADR-003 | B8: 認証ライブラリとしてoidc-client-tsを採用 | C8: Accepted | D8: 2026-03-17 | G8: Accepted | H8: =COUNTIF($C$6:$C$72,$G8) -> 12
A9: ADR-004 | B9: 1アカウント2 User Poolでマルチアカウント構成を擬似再現 | C9: Accepted | D9: 2026-03-17 | G9: Accepted (Phase 1) | H9: =COUNTIF($C$6:$C$72,$G9) -> 1
A10: ADR-005 | B10: 共通認証基盤にUser Poolを使用（Identity Poolではない） | C10: Accepted | D10: 2026-03-17 | G10: Accepted（条件付き） | H10: =COUNTIF($C$6:$C$72,$G10) -> 1
A11: ADR-006 | B11: Cognito vs Keycloak コスト損益分岐点の分析 | C11: Proposed | D11: 2026-03-17 | G11: Scope Reduced | H11: =COUNTIF($C$6:$C$72,$G11) -> 2
A12: ADR-007 | B12: 大阪リージョンでAuth0 OIDC IdP接続不可の記録 | C12: Accepted | D12: 2026-03-18 | G12: Out of Scope | H12: =COUNTIF($C$6:$C$72,$G12) -> 1
A13: ADR-008 | B13: PoCでKeycloak start-devモードを使用 | C13: Accepted | D13: 2026-03-25 | G13: 合計 | H13: =SUM(H7:H12) -> 65 | I13: =IF(H13=COUNTA($A$6:$A$72),"✓ 明細行数と一致","⚠ 不一致") -> ⚠ 不一致
A14: ADR-009 | B14: MFA責任はパスワード管理側に帰属させる | C14: Accepted | D14: 2026-03-28
A15: ADR-010 | B15: Keycloak環境をPrivate Subnet + VPC Endpoint構成へ移行 | C15: Accepted | D15: 2026-04-21
A16: ADR-011 | B16: 認証基盤前段ネットワーク設計の統合判断 | C16: Proposed | D16: 2026-04-21 | E16: HTTPS／カスタムドメイン／WAF／CloudFront
A17: ADR-012 | B17: VPC Lambda Authorizer + Internal ALBによる鍵情報のプライベート化 | C17: Accepted | D17: 2026-04-23
A18: ADR-013 | B18: CloudFront + WAFによるIP制限の置き換え戦略 | C18: Proposed | D18: 2026-04-24
A19: ADR-014 | B19: 共有認証基盤が対応する認証パターンの範囲 | C19: Proposed | D19: 2026-04-24
A20: ADR-015 | B20: PoCではRHBK検証を実施せず本番設計フェーズへ先送り | C20: Proposed | D20: 2026-04-24
A21: ADR-016 | B21: Cognito機能ティアの機能マトリクスと選定基準 | C21: Proposed | D21: 2026-05-13 | E21: Lite / Essentials / Plus
A22: ADR-017 | B22: マルチテナントL2（単一領域＋複数IdP）の採用根拠 | C22: Proposed | D22: 2026-06-11 / 2026-07-23 | E22: 2026-07-23更新: 1000+ IdP条件付き成立・必須対策7点・PoC P-1〜P-7を追記
A23: ADR-018 | B23: 利用者識別子3階層戦略（メール非保有＋顧客独自ID対応） | C23: Proposed | D23: 2026-06-12
A24: ADR-019 | B24: 既存システムからの移行戦略（並走＋キャッシュ移行） | C24: Proposed | D24: 2026-06-12
A25: ADR-020 | B25: 所属判定のヒントキー戦略＋フェデ/ローカル混在の識別子先行 | C25: Proposed | D25: 2026-06-12
A26: ADR-021 | B26: ログイン後の着地UX（サービス選択画面＋権限不足画面） | C26: Proposed | D26: 2026-06-12
A27: ADR-022 | B27: エッジでの権限不足画面の制御パターン | C27: Proposed | D27: 2026-06-12
A28: ADR-023 | B28: 業務システム（ServiceNow）連携設計 | C28: Proposed | D28: 2026-06-15 | E28: SSO＋プロビジョニング方向の選択
A29: ADR-024 | B29: ログイン画面アーキテクチャとブランディング4パターン | C29: Proposed | D29: 2026-06-15
A30: ADR-025 | B30: 利用者自動同期の位置づけと受信スタンス | C30: Proposed | D30: 2026-06-15 | E30: 2026-07-08 §H追記: 顧客IdPがLDAPの場合の扱い、論点6件、ヒアリングB-LDAP-1〜7を起票
A31: ADR-026 | B31: 強度の不整合の具体例とステップアップ設計 | C31: Proposed | D31: 2026-06-15
A32: ADR-027 | B32: 同一顧客内の利用者重複の扱い（7シナリオ＋連携戦略） | C32: Proposed | D32: 2026-06-15
A33: ADR-028 | B33: IdPなし顧客のローカル利用者管理 — 4選択肢の比較 | C33: Superseded | D33: 2026-06-15 | E33: 2026-08-18: 前提P-07の転換により置き換え（Superseded）。削除せず記録として保持
A34: ADR-029 | B34: ローカル利用者の定義 — 利用者カテゴリと範囲シナリオ | C34: Superseded | D34: 2026-06-15 | E34: 2026-08-18: ADR-033の2層分離（2-tier）で置き換え（Superseded）。削除せず記録として保持
A35: ADR-030 | B35: 最小の通行証項目設計と接続元アプリの表現 | C35: Proposed | D35: 2026-06-15
A36: ADR-031 | B36: 追加確認の実施情報の統合方針 | C36: Proposed | D36: 2026-06-15
A37: ADR-032 | B37: 1000万規模におけるプラットフォーム選定とコスト比較 | C37: Proposed | D37: 2026-06-12
A38: ADR-033 | B38: 2層アーキテクチャ（仲介＋自社受け皿） | C38: Proposed | D38: 2026-06-15 / 2026-07-23 | E38: 2026-07-23更新: 別アカウント配置＋2クラスタ凍結＋シャーディング拡張パス
A39: ADR-034 | B39: 状況に応じた認証（リスクベース）の設計 | C39: Proposed | D39: 2026-06-18
A40: ADR-035 | B40: 不正検知と対応（ITDR）の設計 | C40: Proposed | D40: 2026-06-18
A41: ADR-036 | B41: 顧客監査対応 | C41: Scope Reduced | D41: 2026-06-18 | E41: 2026-06-24縮小: 監査ログ保管＋都度メール対応のみ。情報開示ポータルはスコープ外
A42: ADR-037 | B42: 責任分界モデルと軽量な権限管理の設計 | C42: Proposed | D42: 2026-06-18
A43: ADR-038 | B43: 利用者管理画面（顧客テナント管理者向け） | C43: Proposed | D43: 2026-06-18
A44: ADR-039 | B44: ネットワーク監査アカウント設計 | C44: Proposed | D44: 2026-06-23 / 2026-07-23 | E44: v3 2026-07-23: 当該アカウントが他組織管理と判明し要求仕様化。外部通信の許可申請リスクを追記
A45: ADR-040 | B45: 特権管理（一時昇格） | C45: Out of Scope | D45: 2026-06-23 | E45: 2026-06-24: 本基盤対象外、運用体制側で別途検討。管理画面パス保護方針はADR-039/013へ
A46: ADR-041 | B46: 実行環境の権限設計 | C46: Proposed | D46: 2026-06-23 / 2026-07-23 | E46: 2026-07-23更新: 基盤転換に伴い方式を変更
A47: ADR-042 | B47: 自動化された攻撃の検知と対策の設計 | C47: Proposed | D47: 2026-06-23
A48: ADR-043 | B48: アクセシビリティ設計（WCAG 2.2 AA＋JIS準拠） | C48: Proposed | D48: 2026-06-23 | E48: 要件側に対応項目が存在しない点は本ブックの「設計→要件」で指摘済み
A49: ADR-044 | B49: 机上演習・インシデント訓練の設計 | C49: Proposed | D49: 2026-06-23
A50: ADR-045 | B50: 鍵管理戦略の集約 | C50: Proposed | D50: 2026-06-23
A51: ADR-046 | B51: 供給網セキュリティ | C51: Proposed | D51: 2026-06-23
A52: ADR-047 | B52: 耐量子暗号への移行計画 | C52: Proposed | D52: 2026-06-23
A53: ADR-048 | B53: データ可搬性＋データ主体の権利対応 | C53: Proposed | D53: 2026-06-23
A54: ADR-049 | B54: 委託先リスク管理 | C54: Proposed | D54: 2026-06-23
A55: ADR-050 | B55: モバイルアプリ認証設計 | C55: Proposed | D55: 2026-06-23
A56: ADR-051 | B56: 複数地域での災害復旧・切替の詳細設計 | C56: Proposed | D56: 2026-06-23 / 2026-07-23 | E56: 2026-07-23更新: 予備地域の対応確認。ただし2026-07-30の手動復旧転換により再改訂が必要（DU-U8-12）
A57: ADR-052 | B57: 認証APIへの流量制限 | C57: Scope Reduced | D57: 2026-06-23 | E57: 2026-06-24縮小: 認証APIのみ。その他はAPIプラットフォーム側／※2026-08-18 二重定義に注意: 認証フローのレート制限はD-U6-14が正。本ADRの方式は管理APIにのみ適用する
A58: ADR-053 | B58: 可観測性戦略 | C58: Proposed | D58: 2026-06-23
A59: ADR-054 | B59: ID統合戦略 | C59: Proposed | D59: 2026-06-24 | E59: 現状調査＋人事DBを正＋対応表＋3段階移行
A60: ADR-055 | B60: 所属判定の実装方式選定 | C60: Accepted (Phase 1) | D60: 2026-06-25 | E60: 今回採用＝独自機能方式。次段階候補＝URL＋エッジ関数の併用
A61: ADR-056 | B61: 基盤の採用判断 | C61: Accepted（条件付き） | D61: 2026-06-25 / 2026-07-23 | E61: 2026-07-23で決定が逆転。採用条件3点の充足まで条件付き。旧判断は履歴として保存
A62: ADR-057 | B62: 偽装リクエスト対策の責任分界と実装パターン | C62: Proposed | D62: 2026-07-06 | E62: 3層に分けて整理（基盤UI／認可フロー／アプリAPI）
A63: ADR-058 | B63: 認証プラットフォームの代替6パターン比較 | C63: Accepted | D63: 2026-07-02 | E63: 2系統の独立調査で現行方式の維持を再確認
A64: ADR-059 | B64: 認証実装漏れ検知の中央監視アーキテクチャ | C64: Proposed | D64: 2026-07-06 | E64: アプリ台帳＋仕様台帳で全アプリを自動追随
A65: ADR-060 | B65: 認証プロトコルの攻撃経路 残課題対応 | C65: Proposed | D65: 2026-07-08 | E65: 33経路の残課題3領域を統合（ログのマスキング／送信者拘束／状況判定の強化）
A66: ADR-061 | B66: デプロイ検知の巡回型への統一 | C66: Accepted | D66: 2026-08-06 / 2026-08-07 | E66: ★索引に未登録。改訂で検知対象をコード差分に変更。受容した穴2点（コンソール直変更・未デプロイ時の偽安心）を明記
A67: ADR-062 | B67: 管理APIの実行形態＝関数実行 | C67: Proposed | D67: 2026-08-06 / 2026-08-08 | E67: 認証製品と管理ツールを別障害ドメインに分離。トポロジはADR-063、削除伝播はADR-064
A68: ADR-063 | B68: ブランドユニット・アーキテクチャ | C68: Proposed | D68: 2026-08-06 | E68: 仲介は共有1つ、権限系はブランド側へ。不変条件4点を明示。今回は1ブランド
A69: ADR-064 | B69: 削除・停止伝播＝取りこぼし防止方式 | C69: Proposed | D69: 2026-08-08 | E69: 1トランザクションで記録し必達送信、冪等に影ユーザを無効化。数分で突合
A70: ADR-065 | B70: 継続アクセス評価 | C70: Proposed | D70: 2026-08-12 | E70: 取り消し漏れ時間の恒久解。3段階導入。確定はゲートG-SSFと顧客確認B-CAEP-1
... A72: ADR-067 | B72: 認可判定ログ＋アクセス再認証 | C72: Proposed | D72: 2026-08-12 | E72: 決定ログと定期棚卸し。確定は顧客確認B-AUTHZLOG-1／B-IGA-REC-1

Sheet 機能グループ一覧
A1: 機能グループ | B1: 系統 | C1: 概要 | D1: 行数 | E1: 人日
A2: ログインの振り分け | B2: 認証 | C2: 入力された ID から、その人をどの顧客IdPへ送るかを決める入口。顧客IdPの一覧を見せずに済ませる | D2: 4 | E2: 4
A3: 顧客IdP 連携ログイン | B3: 認証 | C3: 顧客が持つ認証システムに認証を委ね、その結果を受けてログインさせる。Keycloak-Broker の中核で、ユーザの大半がこの経路を通る | D3: 17 | E3: 28
A4: パスワードによるログイン | B4: 認証 | C4: 顧客側に認証システムが無い顧客のユーザと、基盤の運用者が、Keycloak-Broker に直接 ID とパスワードでログインする | D4: 4 | E4: 5.5
A5: 多要素認証 | B5: 認証 | C5: パスワードに加えて 2 つ目の要素（数字コード・生体・セキュリティキー）を求める。登録と利用の両方を含む | D5: 2 | E5: 1
A6: パスワードと復旧 | B6: 認証 | C6: 端末の紛失やパスワード忘れから、ユーザ自身または管理者が復旧する | D6: 0 | E6: 0
A7: ログイン口の保護 | B7: 認証 | C7: 総当たり・ユーザ名の推測・流出パスワードなど、ログイン口への攻撃を防ぐ | D7: 1 | E7: 1
A8: セッションとログアウト | B8: 認証 | C8: ログイン状態をどこまで保つか、いつ切るか。アプリ側へのログアウト連携を含む | D8: 5 | E8: 9
A9: ログイン画面 | B9: 認証 | C9: ユーザが実際に目にする画面。ログイン画面の見せ方と、失敗したときの案内 | D9: 3 | E9: 2.5
A10: ユーザ管理 | B10: ユーザ管理 | C10: 顧客の人事システムや IdP から SCIM でユーザの登録・更新・削除を受け取る。ログインを待たずに反映できる | D10: 6 | E10: 6.75
A11: ユーザ属性の統一 | B11: ユーザ管理 | C11: 顧客ごとにバラバラな項目名や登録経路を、基盤内の統一した形に揃える | D11: 3 | E11: 3.75
A12: ユーザの停止・再開・消去 | B12: ユーザ管理 | C12: 退職などでユーザを止めた事実を確実に反映し、復職時に安全に再開する。消さずに無効化し、期限後に消す | D12: 4 | E12: 4
A13: 顧客・組織管理 | B13: ユーザ管理 | C13: 顧客と組織の作成・設定・解約 | D13: 2 | E13: 2
... A30: 非機能: 提供ドキュメント | B30: 非機能 | C30: 顧客とアプリ開発者へ渡す資料のうち、特定の機能に紐づかない共通部分 | D30: 3 | E30: 4

Sheet 提供API一覧
A1: 対象 | B1: 機能ID | C1: 機能グループ | D1: 機能名 | E1: 提供する API（機能の粒度） | F1: エンドポイント | G1: 呼ぶ主体 | H1: 区分 | I1: コスト | J1: 備考 | L1: コスト | M1: 件数
A2: Broker | B2: F-AUTH-05 | C2: 顧客IdP 連携ログイン | D2: 顧客IdPへのログイン委譲（OIDC） | E2: 接続情報の公開 | F2: GET /realms/{r}/.well-known/openid-configuration | G2: アプリ（M2M） | H2: ✅ 標準 | I2: 標準内 | J2: アプリはこの 1 本から他の入口を自動取得できる。手で URL を配らない | L2: 標準内 | M2: =COUNTIF($I$2:$I$109,$L2) -> 84
A3: Broker | B3: F-AUTH-05 | C3: 顧客IdP 連携ログイン | D3: 顧客IdPへのログイン委譲（OIDC） | E3: ログイン開始（認可） | F3: GET /realms/{r}/protocol/openid-connect/auth | G3: ブラウザ（画面遷移） | H3: ✅ 標準 | I3: 標準内 | J3: 認可コード + PKCE。顧客IdP への振り分けはこの先で Keycloak が行う | L3: 🔺 標準外（追加コスト） | M3: =COUNTIF($I$2:$I$109,$L3) -> 16
A4: Broker | B4: F-AUTH-05 | C4: 顧客IdP 連携ログイン | D4: 顧客IdPへのログイン委譲（OIDC） | E4: JWT の取得・更新 | F4: POST /realms/{r}/protocol/openid-connect/token | G4: アプリ（M2M） | H4: ✅ 標準 | I4: 標準内 | J4: 認可コード交換 / リフレッシュ / システム間の 3 用途が同じ入口 | L4: 🔻 削減候補 | M4: =COUNTIF($I$2:$I$109,$L4) -> 6
A5: Broker | B5: F-AUTH-05 | C5: 顧客IdP 連携ログイン | D5: 顧客IdPへのログイン委譲（OIDC） | E5: ユーザ情報の取得 | F5: GET /realms/{r}/protocol/openid-connect/userinfo | G5: エンドユーザ本人 | H5: ✅ 標準 | I5: 標準内 | J5: JWT に載せない属性をここで補う。JWT を軽くしたいときの受け皿 | L5: — 提供しない | M5: =COUNTIF($I$2:$I$109,$L5) -> 2
A6: Broker | B6: F-AUTH-05 | C6: 顧客IdP 連携ログイン | D6: 顧客IdPへのログイン委譲（OIDC） | E6: 署名鍵の公開 | F6: GET /realms/{r}/protocol/openid-connect/certs | G6: アプリ（M2M） | H6: ✅ 標準 | I6: 標準内 | J6: アプリ側の JWT 検証に必須。鍵の入れ替えに自動追随する前提 | L6: 合計 | M6: =SUM(M2:M5) -> 108
A7: Broker | B7: F-AUTH-06 | C7: 顧客IdP 連携ログイン | D7: 顧客IdPへのログイン委譲（SAML） | E7: SAML の接続情報 | F7: GET /realms/{r}/protocol/saml/descriptor | G7: アプリ（M2M） | H7: ✅ 標準 | I7: 標準内 | J7: 顧客IdP・業務システムとの交換用
A8: Broker | B8: F-AUTH-06 | C8: 顧客IdP 連携ログイン | D8: 顧客IdPへのログイン委譲（SAML） | E8: SAML の送受信 | F8: POST/GET /realms/{r}/protocol/saml | G8: ブラウザ（画面遷移） | H8: ✅ 標準 | I8: 標準内 | J8: 受け入れ（SP）と提供（IdP）の両方が同じ入口 | L8: 🔺 標準外（追加コスト）の API
A9: Broker | B9: F-AZ-07 | C9: JWT の発行 | D9: システム間 JWT の発行 | E9: システム間 JWT の発行 | F9: POST /realms/{r}/protocol/openid-connect/token（client_credentials） | G9: アプリ（M2M） | H9: ✅ 標準 | I9: 標準内 | J9: アプリ・バッチが API を呼ぶための資格。スコープで範囲を絞る | L9: 対象 | M9: 提供する API | N9: 機能名
A10: Broker | B10: F-AZ-08 | C10: JWT の発行 | D10: 別アプリ向け JWT への交換（Token Exchange） | E10: JWT の交換 | F10: POST /realms/{r}/protocol/openid-connect/token（token-exchange） | G10: アプリ（M2M） | H10: ✅ 標準 | I10: 標準内 | J10: Phase 1 対象外（FR-AUTH-005）。必要になったら設定で有効化 | L10: {=IFERROR(_xlfn._xlws.FILTER($A$2:$A$109,$I$2:$I$109=$L$3),"")} -> Broker | M10: {=IFERROR(_xlfn._xlws.FILTER($E$2:$E$109,$I$2:$I$109=$L$3),"")} -> 接続情報の自動追随 | N10: {=IFERROR(_xlfn._xlws.FILTER($D$2:$D$109,$I$2:$I$109=$L$3),"")} -> 顧客IdP の接続情報の自動追随
A11: Broker | B11: F-AZ-10 | C11: JWT の発行 | D11: アプリへの JWT 発行 | E11: JWT に載せる項目 | F11: （API なし）Protocol Mapper / Client Scope の設定 | G11: アプリ（M2M） | H11: ⚙ 設定のみ | I11: 標準内 | J11: 載せる項目はアプリごとにスコープで出し分ける。設計は必要だがアプリが呼ぶ API は無い | L11: Broker | M11: 証明書期限の監視 | N11: 顧客IdP・本基盤の証明書の期限監視
A12: Broker | B12: F-AUTH-23 | C12: セッションとログアウト | D12: ログイン状態の保持とタイムアウト | E12: ログイン状態の保持 | F12: POST /realms/{r}/protocol/openid-connect/token（refresh_token） | G12: アプリ（M2M） | H12: ✅ 標準 | I12: 標準内 | J12: 有効期間は Realm 設定。上限 12 時間（2026-09-07 決定） | L12: Broker | M12: ログインの振り分け（HRD） | N12: 顧客IdPの自動振り分け
A13: Broker | B13: F-AUTH-24 | C13: セッションとログアウト | D13: アプリへのログアウト連携 | E13: ログアウト | F13: GET/POST /realms/{r}/protocol/openid-connect/logout | G13: ブラウザ（画面遷移） | H13: ✅ 標準 | I13: 標準内 | J13: 本人のログイン状態を破棄。顧客IdP 側への連鎖は IdP ごとの設定 | L13: Broker | M13: アプリへの変更通知（Webhook） | N13: アプリへの変更通知（Webhook）
A14: Broker | B14: F-AUTH-24 | C14: セッションとログアウト | D14: アプリへのログアウト連携 | E14: 他アプリへのログアウト通知 | F14: （Keycloak → アプリ）Back-Channel Logout | G14: アプリ（M2M） | H14: ✅ 標準 | I14: 標準内 | J14: **アプリ側が受信の入口を作る**。Keycloak が呼びに行く向きなので、提供 API ではなくアプリへの実装要求 | L14: Broker | M14: 長期未使用者の自動停止 | N14: 長期未使用者の自動停止
A15: Broker | B15: F-AZ-10 | C15: JWT の発行 | D15: アプリへの JWT 発行 | E15: JWT の失効 | F15: POST /realms/{r}/protocol/openid-connect/revoke | G15: アプリ（M2M） | H15: ⚠ 標準（制約） | I15: 標準内 | J15: リフレッシュトークンは即時に効く。アクセストークンは署名だけで検証するアプリには最大 30 分残る（FR-SSO-009） | L15: Broker | M15: 保存期限切れの消去 | N15: 保存期限切れデータの消去
A16: Broker | B16: F-AZ-10 | C16: JWT の発行 | D16: アプリへの JWT 発行 | E16: JWT の有効性照会 | F16: POST /realms/{r}/protocol/openid-connect/token/introspect | G16: アプリ（M2M） | H16: ✅ 標準 | I16: 標準内 | J16: 失効を即座に反映したい重要な操作で使う。毎回呼ぶと Keycloak の負荷になる | L16: Broker | M16: 実在推測の防止 | N16: ユーザの存在推測の防止
A17: Broker | B17: F-ADM-16 | C17: 顧客IdP 管理 | D17: 顧客IdPの接続登録 | E17: 顧客IdP の登録 | F17: POST /admin/realms/{r}/identity-provider/instances | G17: 管理画面 | H17: ⚠ 標準（制約） | I17: 標準内 | J17: 標準にある。ただし Admin API は Realm 全体に効くため、そのままアプリへは渡せない（後述の権限の絞り込みが前提） | L17: IdP | M17: パスワードの照合 | N17: Keycloak-IdP 収容ユーザのログイン
A18: Broker | B18: F-ADM-17 | C18: 顧客IdP 管理 | D18: 接続設定の変更・証明書更新 | E18: 顧客IdP の変更・証明書更新 | F18: PUT /admin/realms/{r}/identity-provider/instances/{alias} | G18: 管理画面 | H18: ⚠ 標準（制約） | I18: 標準内 | J18: 同上 | L18: IdP | M18: 流出パスワードの使用拒否 | N18: 流出パスワードの使用拒否
A19: Broker | B19: F-ADM-16 | C19: 顧客IdP 管理 | D19: 顧客IdPの接続登録 | E19: 顧客IdP の接続情報の取り込み | F19: POST /admin/realms/{r}/identity-provider/import-config | G19: 管理画面 | H19: ✅ 標準 | I19: 標準内 | J19: 相手の接続情報（メタデータ URL）から設定値を起こす | L19: IdP | M19: メールを持たない人の復旧 | N19: メールを持たない人の復旧
A20: Broker | B20: F-INT-11 | C20: 顧客IdP 管理 | D20: 顧客IdP の接続情報の自動追随 | E20: 接続情報の自動追随 | F20: （標準に無い） | G20: バッチ・システム | H20: 🔧 カスタム必要 | I20: 🔺 標準外（追加コスト） | J20: 定期的に取り込み直す仕組みは標準に無い。Admin API を叩くバッチを作る | L20: Broker | M20: 振り分け失敗時の切替 | N20: 振り分け失敗時のパスワード入力への切替
A21: Broker | B21: F-ADM-14 | C21: 顧客・組織管理 | D21: 顧客の作成 | E21: 顧客の作成 | F21: POST /admin/realms/{r}/organizations | G21: 管理画面 | H21: ⚠ 標準（制約） | I21: 標準内 | J21: Keycloak 26 の Organizations を顧客の単位に使う | L21: Broker | M21: 管理 API の内部公開 | N21: アプリ向け管理 API の公開
A22: Broker | B22: F-ADM-15 | C22: 顧客・組織管理 | D22: 顧客設定の編集 | E22: 顧客設定の編集 | F22: PUT /admin/realms/{r}/organizations/{id} | G22: 管理画面 | H22: ⚠ 標準（制約） | I22: 標準内 | J22: ドメイン・表示名など | L22: Broker | M22: 不正兆候の検知 | N22: 不正なログインの兆候の検知
... A25: Broker | B25: F-ADM-01 | C25: ユーザ管理 | D25: ユーザの参照 | E25: ユーザの検索・一覧 | F25: GET /admin/realms/{r}/users | G25: 管理画面 | H25: ⚠ 標準（制約） | I25: 標準内 | J25: 標準にある。件数の区切りと検索条件も標準 | L25: IdP | M25: パスワードの変更日・期限の取得 | N25: パスワード変更・初回強制変更
A26: Broker | B26: F-ADM-01 | C26: ユーザ管理 | D26: ユーザの参照 | E26: ユーザの詳細参照 | F26: GET /admin/realms/{r}/users/{id} | G26: 管理画面 | H26: ⚠ 標準（制約） | I26: 標準内
A27: Broker | B27: F-ADM-03 | C27: ユーザ管理 | D27: ユーザの登録と変更 | E27: ユーザの登録 | F27: POST /admin/realms/{r}/users | G27: 管理画面 | H27: ⚠ 標準（制約） | I27: 標準内
A28: Broker | B28: F-ADM-03 | C28: ユーザ管理 | D28: ユーザの登録と変更 | E28: ユーザの変更 | F28: PUT /admin/realms/{r}/users/{id} | G28: 管理画面 | H28: ⚠ 標準（制約） | I28: 標準内 | J28: 属性の追加は User Profile で宣言した項目のみ | L28: 🔻 削減候補の API
A29: Broker | B29: F-ADM-05 | C29: ユーザ管理 | D29: ユーザの利用可否の切替・削除 | E29: ユーザの利用可否の切替 | F29: PUT /admin/realms/{r}/users/{id}（enabled） | G29: 管理画面 | H29: ⚠ 標準（制約） | I29: 標準内 | J29: 停止・再開はこの 1 本 | L29: 対象 | M29: 提供する API | N29: 機能名
A30: Broker | B30: F-PROV-10 | C30: ユーザの停止・再開・消去 | D30: ユーザの停止（消さずに無効化） | E30: ユーザの停止 | F30: PUT /admin/realms/{r}/users/{id}（enabled=false） | G30: バッチ・システム | H30: ⚠ 標準（制約） | I30: 標準内 | J30: 停止日時の記録は属性で持つ（標準の項目に無いため User Profile で宣言） | L30: {=IFERROR(_xlfn._xlws.FILTER($A$2:$A$109,$I$2:$I$109=$L$4),"")} -> Broker | M30: {=IFERROR(_xlfn._xlws.FILTER($E$2:$E$109,$I$2:$I$109=$L$4),"")} -> ユーザ登録の受信（SCIM） | N30: {=IFERROR(_xlfn._xlws.FILTER($D$2:$D$109,$I$2:$I$109=$L$4),"")} -> 顧客IdP からのユーザ情報の同期
A31: Broker | B31: F-PROV-11 | C31: ユーザの停止・再開・消去 | D31: 停止済みユーザの再開 | E31: 停止済みユーザの再開 | F31: PUT /admin/realms/{r}/users/{id}（enabled=true） | G31: バッチ・システム | H31: ⚠ 標準（制約） | I31: 標準内 | J31: 誤って戻さない条件の判定は呼ぶ側の責任 | L31: Broker | M31: ユーザ更新の受信（SCIM） | N31: 顧客IdP からのユーザ情報の同期
A32: Broker | B32: F-ADM-05 | C32: ユーザ管理 | D32: ユーザの利用可否の切替・削除 | E32: ユーザの削除 | F32: DELETE /admin/realms/{r}/users/{id} | G32: 管理画面 | H32: ⚠ 標準（制約） | I32: 標準内 | J32: Phase 1 は消さずに止める方針のため通常は使わない | L32: Broker | M32: 削除通知の受信（SCIM） | N32: 顧客IdP からのユーザ情報の同期
A33: Broker | B33: F-ADM-10 | C33: セッションとログアウト | D33: 強制ログアウト（管理者） | E33: 強制ログアウト（1 人） | F33: POST /admin/realms/{r}/users/{id}/logout | G33: 管理画面 | H33: ⚠ 標準（制約） | I33: 標準内 | L33: Broker | M33: ユーザ検索の受信（SCIM） | N33: 顧客IdP からのユーザ情報の同期
A34: Broker | B34: F-ADM-10 | C34: セッションとログアウト | D34: 強制ログアウト（管理者） | E34: 強制ログアウト（全員） | F34: POST /admin/realms/{r}/logout-all | G34: 管理画面 | H34: ⚠ 標準（制約） | I34: 標準内 | J34: 事故対応用。顧客単位の一括は標準に無く、対象を絞って繰り返す | L34: IdP | M34: パスワードの自己再設定 | N34: パスワードの自己再設定
A35: Broker | B35: F-ADM-01 | C35: ユーザ管理 | D35: ユーザの参照 | E35: ログイン状態の一覧 | F35: GET /admin/realms/{r}/users/{id}/sessions | G35: 管理画面 | H35: ⚠ 標準（制約） | I35: 標準内 | L35: Broker | M35: 一括の有効化・無効化 | N35: ユーザの利用可否の切替・削除
A36: Broker | B36: F-AUTH-20 | C36: ログイン口の保護 | D36: 連続失敗時の一時締め出し | E36: 締め出しの解除 | F36: DELETE /admin/realms/{r}/attack-detection/brute-force/users/{id} | G36: 管理画面 | H36: ✅ 標準 | I36: 標準内 | J36: 連続失敗で止まったユーザを戻す。締め出しそのものは Realm 設定
A37: Broker | B37: F-INT-13 | C37: アプリ連携 | D37: アプリの接続登録（クライアント登録） | E37: アプリの接続登録 | F37: POST /admin/realms/{r}/clients | G37: 管理画面 | H37: ⚠ 標準（制約） | I37: 標準内 | J37: ひな形を用意して登録する
A38: Broker | B38: F-INT-13 | C38: アプリ連携 | D38: アプリの接続登録（クライアント登録） | E38: アプリの接続登録（申請式） | F38: POST /realms/{r}/clients-registrations/{provider} | G38: アプリ（M2M） | H38: ✅ 標準 | I38: 標準内 | J38: 管理者が発行した引換券（initial access token）でアプリ側が自分で登録できる。Admin API を渡さずに済む
A39: Broker | B39: F-INT-13 | C39: アプリ連携 | D39: アプリの接続登録（クライアント登録） | E39: 引換券の発行 | F39: POST /admin/realms/{r}/clients-initial-access | G39: 管理画面 | H39: ⚠ 標準（制約） | I39: 標準内 | J39: 上の申請式で使う券
A40: Broker | B40: F-BAT-05 | C40: 鍵・証明書管理 | D40: アプリの接続用パスワードの定期入れ替え | E40: 接続用パスワードの再発行 | F40: POST /admin/realms/{r}/clients/{id}/client-secret | G40: 管理画面 | H40: ⚠ 標準（制約） | I40: 標準内 | J40: 入れ替えの周期と通知は運用側で作る
A41: Broker | B41: F-BAT-04 | C41: 鍵・証明書管理 | D41: JWT 署名鍵の定期入れ替え | E41: 署名鍵の状態確認 | F41: GET /admin/realms/{r}/keys | G41: 管理画面 | H41: ⚠ 標準（制約） | I41: 標準内 | J41: 鍵の追加・無効化は components API。並走期間の管理は運用手順
A42: Broker | B42: F-BAT-07 | C42: 鍵・証明書管理 | D42: 顧客IdP・本基盤の証明書の期限監視 | E42: 証明書期限の監視 | F42: （標準に無い） | G42: バッチ・システム | H42: 🔧 カスタム必要 | I42: 🔺 標準外（追加コスト） | J42: 期限が近いものを知らせる仕組みは標準に無い。API を読むバッチを作る
A43: Broker | B43: F-ADM-25 | C43: 監査・記録 | D43: 監査ログの出力と保管 | E43: 監査ログの取得 | F43: GET /admin/realms/{r}/events / GET /admin/realms/{r}/admin-events | G43: 管理画面 | H43: ⚠ 標準（制約） | I43: 標準内 | J43: 保管と検索は全体の共通基盤側。Keycloak の標準出力を流す方式が主で、この API は補助
A44: Broker | B44: F-AZ-06 | C44: 認可・権限判定 | D44: 管理操作の 3 段階権限確認 | E44: 管理操作の権限の絞り込み | F44: （API ではなく設定）Admin Permissions（FGAP v2） | G44: 管理画面 | H44: ⚙ 設定のみ | I44: 標準内 | J44: Keycloak 26.2 以降の標準機能。ユーザ・グループ・顧客の単位で管理権限を絞れる。**アプリへ Admin API を渡す場合の前提**
A45: Broker | B45: F-AUTH-02 | C45: ログインの振り分け | D45: 顧客IdPの自動振り分け | E45: ログインの振り分け（HRD） | F45: （一部のみ標準）Organizations のドメイン一致 | G45: ブラウザ（画面遷移） | H45: 🔧 カスタム必要 | I45: 🔺 標準外（追加コスト） | J45: メールのドメインで振り分けるのは標準。**識別子（顧客コード）で振り分けるには拡張が要る**
A46: Broker | B46: F-PROV-03 | C46: ユーザ管理 | D46: 顧客IdP からのユーザ情報の同期 | E46: ユーザ登録の受信（SCIM） | F46: （標準に無い） | G46: バッチ・システム | H46: 🔧 カスタム必要 | I46: 🔻 削減候補 | J46: **Keycloak に SCIM の受信機能は無い**。作るか、外部の実装を持ち込むか、使わないかの判断が要る／A-5: 削減候補。ただし候補リストには残す
A47: Broker | B47: F-PROV-03 | C47: ユーザ管理 | D47: 顧客IdP からのユーザ情報の同期 | E47: ユーザ更新の受信（SCIM） | F47: （標準に無い） | G47: バッチ・システム | H47: 🔧 カスタム必要 | I47: 🔻 削減候補 | J47: 同上／A-5: 削減候補
... A109: Broker | B109: F-ADM-05 | C109: ユーザ管理 | D109: ユーザの利用可否の切替・削除 | E109: 一括の有効化・無効化 | F109: （標準に無い）1 件ずつの呼び出しをまとめる | G109: バッチ・システム | H109: 🔧 カスタム必要 | I109: 🔻 削減候補 | J109: **G-15。2026-09-09 決定: 必要だが削減候補**。標準は 1 件ずつのため件数分の呼び出しになる。**数万人規模の停止が時間内に終わるかは性能試験で確かめる**／G-15: 必要だが削減候補

Sheet 要件マッピング
A1: 要件ID | B1: 種別 | C1: 優先度 | D1: 要件実現対象 | E1: 構築場所 | F1: 担当 | G1: 担当の理由 | H1: 項目 | I1: 概要 | J1: ① 基本設計 | K1: ② 詳細設計 | L1: ③ 製造 | M1: ④ テスト | N1: 状況 | O1: Keycloak-IdP 側
A2: FR-AUTH-001-a | B2: 機能要件 | C2: Must | D2: 対象 | E2: Keycloak-Broker | F2: インフラ（本基盤） | G2: Keycloak-Broker にローカルで残るのは運用者だけ。認証は WebAuthn 必須（NFR-SEC-021） | H2: ID/PW 認証（ローカルユーザー）（本基盤運用者） | I2: ID とパスワードで直接ログインできること。顧客IdP を持たない顧客のユーザは Keycloak-IdP（アプリ責務）、本基盤の運用者は Keycloak-Broker（NFR-SEC-021）で満たす | J2: HB-F-AUTH-01 HG-09 | K2: DDB-19 | L2: MKB-31 | M2: SEC-10 | N2: 全工程あり | O2: アプリ（主体）
A3: FR-AUTH-001-b | B3: 機能要件 | C3: Must | D3: 対象 | E3: Keycloak-IdP | F3: アプリ（Keycloak-IdP） | G3: Keycloak-IdP に収容するユーザの話。本基盤は ROSA の引き渡しまで（NFR-OPS-012） | H3: ID/PW 認証（ローカルユーザー）（顧客IdP を持たない顧客のユーザ） | I3: ID とパスワードで直接ログインできること。顧客IdP を持たない顧客のユーザは Keycloak-IdP（アプリ責務）、本基盤の運用者は Keycloak-Broker（NFR-SEC-021）で満たす | N3: アプリ側で実施（Keycloak-IdP 側。本基盤は ROSA の引き渡しまで＝NFR-OPS-012） | O3: アプリ（主体）
A4: FR-AUTH-002 | B4: 機能要件 | C4: Must | D4: 対象 | E4: Keycloak-Broker | F4: インフラ（本基盤） | G4: — | H4: Authorization Code + PKCE（SPA / モバイル） | I4: 画面を持つアプリが、標準の手順（認可コード＋PKCE）でログインを開始し JWT を受け取れること | J4: GD-09 GD-10 GD-14 GD-15 HB-F-AUTH-05 HE-14 HJ-02a HJ-09 HJ-10a | K4: DDB-01 DDB-14 DDE-01 DDI-02 | L4: MKB-02 MKB-03 MKB-22 MKI-02 MKI-13 | M4: IT-07 ST-04 | N4: 全工程あり | O4: —
A5: FR-AUTH-003 | B5: 機能要件 | C5: Must | D5: 対象 | E5: Keycloak-Broker | F5: インフラ（本基盤） | G5: — | H5: Authorization Code + client_secret（SSR） | I5: サーバ側で処理するアプリが、接続用パスワードを使う標準の手順でログインできること | J5: GD-09 GD-10 GD-14 GD-15 HB-F-AUTH-05 HE-14 HJ-02a HJ-09 HJ-10a | K5: DDB-01 DDB-14 DDE-01 DDI-02 | L5: MKB-02 MKB-03 MKB-22 MKI-02 MKI-13 | M5: IT-01 IT-07 RI-01 RI-02 ST-04 | N5: 全工程あり | O5: —
A6: FR-AUTH-004 | B6: 機能要件 | C6: Must | D6: 対象 | E6: Keycloak-Broker | F6: インフラ（本基盤） | G6: — | H6: Client Credentials（M2M） | I6: 人ではなくシステムが API を呼ぶための資格を発行できること | J6: HB-F-AZ-07 | K6: DDB-13 | L6: MKB-21 MKI-12 | M6: IT-06 | N6: 全工程あり | O6: —
A7: FR-AUTH-005 | B7: 機能要件 | C7: TBD | D7: 対象外 | E7: — | F7: — | G7: Phase 1 では作らない。必要になれば Keycloak の標準機能で足せる | H7: Token Exchange（RFC 8693） | I7: あるアプリ向けの JWT を、別のアプリ向けに交換できること | N7: Phase 1 では作らない | O7: —
A8: FR-AUTH-006 | B8: 機能要件 | C8: 不要 | D8: 対象外 | E8: — | F8: — | G8: 2026-08-16 の判断で Phase 1 対象外 | H8: Device Code Flow（画面のない機器・CLI 向けログイン） | I8: 画面のない機器や CLI からログインできること | N8: Phase 1 では作らない | O8: —
A9: FR-AUTH-007 | B9: 機能要件 | C9: 不要 | D9: 対象外 | E9: — | F9: — | G9: 2026-08-16 の判断で対象外。金融水準の顧客が現れたときに再評価 | H9: mTLS Client Authentication（RFC 8705、証明書によるアプリ認証） | I9: 証明書でアプリを認証できること | N9: Phase 1 では作らない | O9: —
A10: FR-AUTH-008 | B10: 機能要件 | C10: Won't | D10: 対象外 | E10: — | F10: — | G10: 採用しない（安全でないため） | H10: ROPC（Password Grant） | I10: アプリがユーザのパスワードを直接受け取ってログインさせる方式 | N10: Phase 1 では作らない | O10: —
A11: FR-AUTH-009 | B11: 機能要件 | C11: Must | D11: 対象 | E11: Keycloak-IdP | F11: アプリ（Keycloak-IdP） | G11: ローカルに収容するユーザだけの話。フェデレーションのユーザは顧客IdP 側の規則に従う | H11: パスワードポリシー（最小長・複雑性） | I11: パスワードの最小の長さと文字種の組み合わせを決められること | N11: アプリ側で実施（Keycloak-IdP 側。本基盤は ROSA の引き渡しまで＝NFR-OPS-012） | O11: アプリ（主体）
A12: FR-AUTH-010 | B12: 機能要件 | C12: Should | D12: 対象 | E12: Keycloak-IdP | F12: アプリ（Keycloak-IdP） | G12: 同上 | H12: パスワード履歴（N 個と一致禁止） | I12: 過去に使ったパスワードを一定個数まで再利用させないこと | N12: アプリ側で実施（Keycloak-IdP 側。本基盤は ROSA の引き渡しまで＝NFR-OPS-012） | O12: アプリ（主体）
A13: FR-AUTH-011 | B13: 機能要件 | C13: Must | D13: 対象 | E13: Keycloak-IdP | F13: アプリ（Keycloak-IdP） | G13: パスワードのロックは Keycloak-IdP 側（アプリ）。Keycloak-Broker はパスワードを持たないため、本基盤側の対策は NFR-SEC-010（実在推測の防止・試行回数の制限）で扱う | H13: アカウントロック（連続失敗） | I13: パスワードを連続で間違えたら一時的にログインを受け付けないこと | N13: アプリ側で実施（Keycloak-IdP 側） | O13: アプリ（主体）
A14: FR-AUTH-012 | B14: 機能要件 | C14: Should | D14: 対象 | E14: Keycloak-IdP | F14: アプリ（Keycloak-IdP） | G14: 同上 | H14: パスワード有効期限 | I14: パスワードに有効期限を設けられること | N14: アプリ側で実施（Keycloak-IdP 側。本基盤は ROSA の引き渡しまで＝NFR-OPS-012） | O14: アプリ（主体）
A15: FR-AUTH-013 | B15: 機能要件 | C15: Must | D15: 対象 | E15: Keycloak-IdP | F15: アプリ（Keycloak-IdP） | G15: 同上 | H15: セルフサービスパスワードリセット | I15: ユーザが自分でパスワードを再設定できること | N15: アプリ側で実施 | O15: アプリ（主体）
A16: FR-AUTH-014 | B16: 機能要件 | C16: Should | D16: 対象 | E16: Keycloak-IdP | F16: アプリ（Keycloak-IdP） | G16: 同上 | H16: 初期パスワード強制変更 | I16: 初回ログイン時にパスワードの変更を強制できること | N16: アプリ側で実施 | O16: アプリ（主体）
A17: FR-AUTH-015 | B17: 機能要件 | C17: TBD | D17: 対象外 | E17: — | F17: — | G17: 提案書で新規想定として挙げた項目。Phase 1 では作らない | H17: DPoP（RFC 9449、送信者に縛った JWT） | I17: JWT を受け取った本人以外が使い回せないよう、送信者を JWT に縛りつけること（DPoP） | N17: Phase 1 では作らない | O17: —
A18: FR-AUTH-016 | B18: 機能要件 | C18: TBD | D18: 対象 | E18: Keycloak-Broker | F18: インフラ（本基盤） | G18: 要否未確定。顧客回答待ち（D-22 で判断のみ計上） | H18: 利用規約への同意取得と記録 | I18: 利用規約などへの同意を取り、いつ誰がどの版に同意したかを記録できること | J18: D-22 | N18: 要件確認（判断のみ計上） | O18: —
A19: FR-FED-001 | B19: 機能要件 | C19: 推奨値あり | D19: 対象 | E19: Keycloak-Broker | F19: インフラ（本基盤） | G19: Auth0 も Phase 1 の対象（2026-09-07 決定）。PoC で使った接続を実機突合（RI-02）に流用する | H19: Auth0 OIDC IdP 連携 | I19: Auth0 を顧客IdP として接続できること | J19: GD-09 GD-10 GD-14 GD-15 HB-F-ADM-16 HB-F-AUTH-05 HE-14 HJ-02a HJ-10a | K19: DDB-01 DDE-01 DDI-02 | L19: MKB-02 MKB-03 MKB-16 MKI-02 | M19: IT-01 RI-02 | N19: 全工程あり | O19: —
A20: FR-FED-002 | B20: 機能要件 | C20: Must | D20: 対象 | E20: Keycloak-Broker | F20: インフラ（本基盤） | G20: — | H20: Entra ID（Azure AD）OIDC 連携 | I20: Entra ID（Azure AD）を顧客IdP として接続できること | J20: GD-09 GD-10 GD-14 GD-15 HB-F-ADM-16 HB-F-AUTH-05 HE-14 HJ-02a HJ-10a | K20: DDB-01 DDE-01 DDI-02 | L20: MKB-02 MKB-03 MKB-16 MKI-02 | M20: RI-01 | N20: 全工程あり | O20: —
A21: FR-FED-003 | B21: 機能要件 | C21: Should | D21: 対象 | E21: Keycloak-Broker | F21: インフラ（本基盤） | G21: — | H21: Okta OIDC 連携 | I21: Okta を顧客IdP として接続できること | J21: GD-09 GD-10 GD-14 GD-15 HB-F-ADM-16 HB-F-AUTH-05 HE-14 HJ-02a HJ-10a | K21: DDB-01 DDE-01 DDI-02 | L21: MKB-02 MKB-03 MKB-16 MKI-02 | M21: IT-01 OP-01 RI-01 RI-02 ST-04 | N21: 全工程あり | O21: —
A22: FR-FED-004 | B22: 機能要件 | C22: Could | D22: 対象 | E22: Keycloak-Broker | F22: インフラ（本基盤） | G22: — | H22: Google Workspace OIDC 連携 | I22: Google Workspace を顧客IdP として接続できること | J22: GD-09 GD-10 GD-14 GD-15 HB-F-ADM-16 HB-F-AUTH-05 HE-14 HJ-02a HJ-10a | K22: DDB-01 DDE-01 DDI-02 | L22: MKB-02 MKB-03 MKB-16 MKI-02 | M22: IT-01 OP-01 RI-01 RI-02 ST-04 | N22: 全工程あり | O22: —
A23: FR-FED-005 | B23: 機能要件 | C23: Should | D23: 対象 | E23: Keycloak-Broker | F23: インフラ（本基盤） | G23: — | H23: SAML 2.0 IdP として受け入れ（SP モード） | I23: 旧方式（SAML）の顧客IdP からログインを受け入れられること | J23: HB-F-ADM-16 HB-F-AUTH-06 HE-15 | K23: DDB-02 DDE-02 DDI-03 | L23: MKB-04 MKB-16 MKI-03 | M23: IT-02 RI-03 ST-05 | N23: 全工程あり | O23: —
A24: FR-FED-006 | B24: 機能要件 | C24: TBD | D24: 対象 | E24: Keycloak-Broker | F24: インフラ（本基盤） | G24: ServiceNow 連携で必要 | H24: SAML 2.0 IdP として発行（IdP モード） | I24: Keycloak-Broker が旧方式（SAML）の提供元として、業務システムへログインを提供できること | J24: GD-13 HB-F-INT-01 HE-16 | K24: DDB-15 DDI-08 | L24: MKB-23 MKI-14 | M24: IT-08 RI-05 ST-25 ST-26 | N24: 全工程あり | O24: —
A25: FR-FED-007 | B25: 機能要件 | C25: TBD | D25: 対象外 | E25: — | F25: — | G25: Phase 1 では作らない | H25: LDAP / AD 直接連携 | I25: 社内ディレクトリ（LDAP / AD）に直接つなげること | N25: Phase 1 では作らない | O25: —
A26: FR-FED-008 | B26: 機能要件 | C26: Must | D26: 対象 | E26: Keycloak-Broker | F26: インフラ（本基盤） | G26: — | H26: JIT プロビジョニング | I26: 顧客IdP 経由で初めて来た人を、その場でユーザとして自動作成できること | J26: HB-F-AUTH-07 | K26: DDB-03 DDI-04 | L26: MKB-05 MKI-04 | M26: ST-04 ST-06 ST-12 | N26: 全工程あり | O26: アプリ（Keycloak-IdP 側の同じ設定は接続仕様 HE-23 に従う）
A27: FR-FED-009 | B27: 機能要件 | C27: Must | D27: 対象 | E27: Keycloak-Broker | F27: インフラ（本基盤） | G27: — | H27: 属性マッピング / クレーム変換 | I27: 顧客ごとにバラバラな属性名を、基盤の統一名に変換して取り込めること | J27: HB-F-PROV-02 HD-05 HD-18 | K27: DDB-04 DDD-01 | L27: MKB-06 MKB-10 | M27: IT-04 ST-07 ST-16 | N27: 全工程あり | O27: アプリ（Keycloak-IdP 側の同じ設定は接続仕様 HE-23 に従う）
A28: FR-FED-010 | B28: 機能要件 | C28: Must | D28: 対象 | E28: Keycloak-Broker | F28: インフラ（本基盤） | G28: — | H28: 複数 IdP 並行運用（マルチテナント） | I28: 複数の顧客IdP を同時に運用でき、顧客ごとに分離できること | J28: HB-F-AZ-05a HJ-01a | K28: DDB-12 DDB-17 | L28: MKB-20 MKB-27 MKI-11 | M28: IT-12 ST-24 | N28: 全工程あり | O28: —
A29: FR-FED-011-a | B29: 機能要件 | C29: Must | D29: 対象 | E29: Keycloak-Broker | F29: インフラ（本基盤） | G29: 登録の手順と疎通確認は本基盤 | H29: 顧客追加時のオンボーディングフロー（本基盤側の登録） | I29: 新しい顧客を迎え入れるときの、登録から利用開始までの流れが用意されていること | J29: HB-F-ADM-14 HB-F-ADM-16 | K29: DDB-09 | L29: MKB-14 MKB-16 | M29: OP-02 ST-21 UAT-02 | N29: 全工程あり | O29: —
A30: FR-FED-011-b | B30: 機能要件 | C30: Must | D30: 対象 | E30: その他 | F30: 顧客（顧客IdP） | G30: 自社 IdP 側の設定（接続先の登録・返す項目・証明書）は顧客が接続ガイドどおりに行う | H30: 顧客追加時のオンボーディングフロー（顧客側の設定） | I30: 新しい顧客を迎え入れるときの、登録から利用開始までの流れが用意されていること | M30: UAT-02 | N30: 顧客側で実施 | O30: —
A31: FR-FED-012-a | B31: 機能要件 | C31: Must | D31: 対象 | E31: Keycloak-Broker | F31: インフラ（本基盤） | G31: 追加認証済みの印（amr）を取り込み、二重に求めない設定は Keycloak-Broker 側 | H31: フェデレーション時の MFA 重複回避（取り込み側） | I31: 顧客IdP 側で追加認証を済ませた人に、Keycloak-Broker で二重に追加認証を求めないこと | J31: HB-F-AUTH-05 HB-F-AUTH-09 HE-14 HE-23 | K31: DDB-01 DDB-18 | L31: MKB-02 MKB-30 | M31: RI-01 ST-04 ST-28 | N31: 全工程あり | O31: —
A32: FR-FED-012-b | B32: 機能要件 | C32: Must | D32: 対象 | E32: その他 | F32: 顧客（顧客IdP） | G32: 追加認証そのものは顧客IdP（Keycloak-IdP 収容ユーザは Keycloak-IdP）が行い、結果を amr で返す。接続ガイドで求める | H32: フェデレーション時の MFA 重複回避（実施側） | I32: 顧客IdP 側で追加認証を済ませた人に、Keycloak-Broker で二重に追加認証を求めないこと | M32: RI-01 | N32: 顧客側で実施 | O32: —
A33: FR-FED-013 | B33: 機能要件 | C33: Should | D33: 対象 | E33: Keycloak-Broker | F33: インフラ（本基盤） | G33: — | H33: ログイン画面での顧客IdP への振り分け（HRD） | I33: ログイン画面で入力した識別子から顧客IdP を自動で判定して送ること。顧客IdP の一覧は見せない。1 顧客に複数ある場合のみ選ばせる | J33: HB-F-AUTH-02 HB-F-AUTH-04 HC-04a HJ-03 | K33: DDC-01 DDH-01 DDI-01 | L33: MKB-01 MKC-01 MKC-03 MKI-01 MKI-08 | M33: ST-01 ST-02 ST-03 | N33: 全工程あり | O33: —
A34: FR-FED-014 | B34: 機能要件 | C34: Should | D34: 対象外 | E34: — | F34: — | G34: Phase 1 では作らない | H34: Custom Domain での federation | I34: 顧客ごとの独自ドメインでフェデレーションできること | N34: Phase 1 では作らない | O34: —
A35: FR-FED-015 | B35: 機能要件 | C35: Must | D35: 対象 | E35: Keycloak-Broker | F35: インフラ（本基盤） | G35: 顧客IdP を持たない顧客のユーザは全員ここを通る。Keycloak-IdP 側の Client・Realm 設定は要求仕様（HE-23）でアプリチームへ渡す | H35: Keycloak-Broker ⇄ Keycloak-IdP 連携 | I35: 顧客IdP を持たない顧客のユーザを Keycloak-Broker から Keycloak-IdP へ委譲してログインさせられること。識別子の引き継ぎ・追加認証結果の取り込み・ログアウト連鎖・セッション上限の同値（12 時間）・閉域の単方向接続を含む | J35: HB-F-AUTH-09 HE-23 HI-11 | K35: DDB-18 DDE-11 DDI-10 | L35: MKA-20 MKB-30 MKI-19 | M35: IT-16 ST-28 | N35: 全工程あり | O35: アプリ（要求仕様どおりに broker-rp Client と Realm 設定を作る）
A36: FR-MFA-001 | B36: 機能要件 | C36: Must | D36: 対象 | E36: Keycloak-IdP | F36: アプリ（Keycloak-IdP） | G36: 追加認証は Keycloak-Broker では扱わない。ローカル収容ユーザは Keycloak-IdP 側 | H36: TOTP（Google Authenticator 等） | I36: スマートフォンアプリの数字コードで追加認証できること | N36: アプリ側で実施 | O36: アプリ（主体）
A37: FR-MFA-002 | B37: 機能要件 | C37: Should | D37: 対象 | E37: Keycloak-IdP | F37: アプリ（Keycloak-IdP） | G37: 同上 | H37: WebAuthn / FIDO2（Passkeys） | I37: 生体認証やセキュリティキーで追加認証できること | N37: アプリ側で実施 | O37: アプリ（主体）
A38: FR-MFA-003 | B38: 機能要件 | C38: Could | D38: 対象外 | E38: — | F38: — | G38: Phase 1 では作らない | H38: SMS OTP | I38: SMS の数字コードで追加認証できること | N38: Phase 1 では作らない | O38: —
A39: FR-MFA-004 | B39: 機能要件 | C39: Could | D39: 対象外 | E39: — | F39: — | G39: Phase 1 では作らない | H39: メール OTP | I39: メールの数字コードで追加認証できること | N39: Phase 1 では作らない | O39: —
A40: FR-MFA-005 | B40: 機能要件 | C40: Should | D40: 対象 | E40: Keycloak-IdP | F40: アプリ（Keycloak-IdP） | G40: 同上 | H40: バックアップコード | I40: 端末を失くしたときに使う予備のコードを発行できること | N40: アプリ側で実施 | O40: アプリ（主体）
A41: FR-MFA-006 | B41: 機能要件 | C41: Should | D41: 対象外 | E41: — | F41: — | G41: Phase 1 では作らない | H41: 条件付き MFA（IP / リスクベース） | I41: 接続元やリスクに応じて追加認証を出し分けられること | N41: Phase 1 では作らない | O41: —
A42: FR-MFA-007 | B42: 機能要件 | C42: Must | D42: 対象 | E42: Keycloak-IdP | F42: アプリ（Keycloak-IdP） | G42: 同上 | H42: MFA 強制 / 任意の切替（ロール単位） | I42: 追加認証を必須にするか任意にするかを役割ごとに切り替えられること | N42: アプリ側で実施 | O42: アプリ（主体）
A43: FR-MFA-008 | B43: 機能要件 | C43: Could | D43: 対象外 | E43: — | F43: — | G43: Phase 1 では作らない | H43: 端末記憶（Trusted Device） | I43: 一度確認した端末を覚えて、次回から追加認証を省けること | N43: Phase 1 では作らない | O43: —
A44: FR-MFA-009 | B44: 機能要件 | C44: Must | D44: 対象 | E44: Keycloak-IdP | F44: アプリ（Keycloak-IdP） | G44: 顧客の管理者分は Keycloak-IdP（アプリ）。本基盤運用者分は NFR-SEC-021 で本基盤が満たす | H44: 管理者の MFA 強制 | I44: 管理者には追加認証を必ず求めること | N44: アプリ側で実施 | O44: アプリ（主体）
A45: FR-SSO-001 | B45: 機能要件 | C45: Must | D45: 対象 | E45: Keycloak-Broker | F45: インフラ（本基盤） | G45: — | H45: 同一 IdP 内の複数 Client 間 SSO | I45: 同じ顧客の複数のアプリを、一度のログインで行き来できること | J45: GD-21 GD-24 HA-10 | K45: DDA-01 DDI-05 | L45: MKB-08 MKI-06 | M45: ST-08 | N45: 全工程あり | O45: —
A46: FR-SSO-002 | B46: 機能要件 | C46: Must | D46: 対象 | E46: Keycloak-Broker | F46: インフラ（本基盤） | G46: — | H46: Auth0/Entra 経由のクロス IdP SSO | I46: 顧客IdP を経由した場合も、複数のアプリを一度のログインで行き来できること | J46: GD-09 GD-10 GD-14 GD-15 GD-21 GD-24 HA-10 HB-F-AUTH-05 HE-14 HJ-02a HJ-10a | K46: DDA-01 DDB-01 DDE-01 DDI-02 DDI-05 | L46: MKB-02 MKB-03 MKB-08 MKI-02 MKI-06 | M46: IT-01 RI-01 RI-02 ST-04 ST-08 | N46: 全工程あり | O46: —
A47: FR-SSO-003-a | B47: 機能要件 | C47: Must | D47: 対象 | E47: その他 | F47: アプリ（業務アプリ） | G47: 業務アプリ側の実装。本基盤はガイドとサンプルで示す | H47: ローカルログアウト（アプリ Cookie 削除のみ）（アプリの実装） | I47: アプリ側だけでログアウトできること（Keycloak-Broker の状態は保つ） | N47: アプリ側で実施 | O47: —
A48: FR-SSO-003-b | B48: 機能要件 | C48: Must | D48: 対象 | E48: Keycloak-Broker | F48: インフラ（本基盤） | G48: アプリ開発者向けガイドとサンプル実装・試用環境を本基盤が提供する | H48: ローカルログアウト（アプリ Cookie 削除のみ）（ガイド・サンプル） | I48: アプリ側だけでログアウトできること（Keycloak-Broker の状態は保つ） | J48: GD-22 | K48: DDJ-05 | L48: MKJ-05 | M48: UAT-04 | N48: 全工程あり | O48: —
A49: FR-SSO-004 | B49: 機能要件 | C49: Must | D49: 対象 | E49: Keycloak-Broker | F49: インフラ（本基盤） | G49: — | H49: IdP セッション破棄（OIDC RP-Initiated Logout） | I49: Keycloak-Broker のログイン状態を破棄できること | J49: GD-22 GD-23 | K49: DDE-03 | L49: MKB-09 MKI-07 | M49: ST-09 | N49: 全工程あり | O49: —
A50: FR-SSO-005 | B50: 機能要件 | C50: Should | D50: 対象 | E50: Keycloak-Broker | F50: インフラ（本基盤） | G50: — | H50: フェデレーション IdP セッション破棄（連動ログアウト） | I50: Keycloak-Broker のログアウトを顧客IdP 側にも連動させられること | J50: GD-22 GD-23 | K50: DDE-03 | L50: MKB-09 MKI-07 | M50: ST-09 | N50: 全工程あり | O50: アプリ（Keycloak-IdP 側の同じ設定は接続仕様 HE-23 に従う）
A51: FR-SSO-006 | B51: 機能要件 | C51: Should | D51: 対象外 | E51: — | F51: — | G51: Back-Channel を採用するため作らない | H51: Front-Channel Logout | I51: 画面経由で他のアプリにログアウトを伝えられること | N51: Phase 1 では作らない | O51: —
A52: FR-SSO-007 | B52: 機能要件 | C52: Should | D52: 対象 | E52: Keycloak-Broker | F52: インフラ（本基盤） | G52: — | H52: Back-Channel Logout（RFC 8606） | I52: サーバ間の通知で他のアプリにログアウトを伝えられること | J52: GD-22 GD-23 | K52: DDE-03 | L52: MKB-09 MKI-07 | M52: ST-09 | N52: 全工程あり | O52: —
A53: FR-SSO-008 | B53: 機能要件 | C53: Must | D53: 対象 | E53: Keycloak-Broker | F53: インフラ（本基盤） | G53: — | H53: セッションタイムアウト設定 | I53: ログイン状態が切れるまでの時間を設定できること。無操作 1 時間・上限 12 時間（2026-09-07 更新、旧 24 時間） | J53: GD-21 GD-24 HA-10 | K53: DDA-01 DDI-05 | L53: MKB-08 MKI-06 | M53: ST-08 | N53: 全工程あり | O53: アプリ（Keycloak-IdP 側の同じ設定は接続仕様 HE-23 に従う）
A54: FR-SSO-009 | B54: 機能要件 | C54: Should | D54: 対象 | E54: Keycloak-Broker | F54: インフラ（本基盤） | G54: — | H54: アクセストークン強制無効化（Revocation） | I54: 発行済みの JWT を強制的に使えなくできること。セッションとリフレッシュトークンは即時失効、アクセストークンは署名のみで検証されるため最大 30 分は残る（契約説明に明記） | J54: GD-16 GD-17 HB-F-PROV-10 HJ-07 | K54: DDB-07 DDE-08 DDI-07 | L54: MKB-12 MKB-19 MKI-10 | M54: ST-18 | N54: 全工程あり | O54: —
A55: FR-SSO-010-a | B55: 機能要件 | C55: Must | D55: 対象 | E55: その他 | F55: アプリ（管理画面・idm-api） | G55: 管理画面・idm-api 側の実装。Keycloak-Broker の管理 API を内部経路で呼ぶ | H55: 強制全セッション破棄（管理者操作）（管理画面からの操作） | I55: 管理者の操作で、対象のログイン状態をまとめて破棄できること | N55: アプリ側で実施 | O55: —
A56: FR-SSO-010-b | B56: 機能要件 | C56: Must | D56: 対象 | E56: Keycloak-Broker | F56: インフラ（本基盤） | G56: 管理 API の内部公開（F-INT-14）: 経路・呼び出し元の資格・許す操作の範囲 | H56: 強制全セッション破棄（管理者操作）（本基盤側の受け口） | I56: 管理者の操作で、対象のログイン状態をまとめて破棄できること | J56: HE-24 | K56: DDE-12 | L56: MKB-32 | M56: IT-17 | N56: 全工程あり | O56: —
A57: FR-AUTHZ-001-a | B57: 機能要件 | C57: Must | D57: 対象 | E57: Keycloak-Broker | F57: インフラ（本基盤） | G57: JWT に載せる項目と要求できる範囲は本基盤が定義し発行する | H57: JWT クレームベース認可（JWT に載せる側） | I57: JWT に載せた情報でアプリが可否を判断できること | J57: GD-16 GD-17 HJ-07 | K57: DDE-08 DDI-07 | L57: MKB-19 MKI-10 | M57: IT-05 ST-23 | N57: 全工程あり | O57: —
A58: FR-AUTHZ-001-b | B58: 機能要件 | C58: Must | D58: 対象 | E58: その他 | F58: アプリ（業務アプリ） | G58: 載った情報で可否を判断するのは業務アプリ（認可・権限判定は本基盤ではやらない） | H58: JWT クレームベース認可（判定する側） | I58: JWT に載せた情報でアプリが可否を判断できること | N58: アプリ側で実施 | O58: —
A59: FR-AUTHZ-002-a | B59: 機能要件 | C59: Must | D59: 対象 | E59: Keycloak-Broker | F59: インフラ（本基盤） | G59: 他顧客の顧客IdP で入れないことと、顧客を指す値を JWT に載せることは Keycloak-Broker 側（F-AZ-05） | H59: tenant_id によるテナント分離（認証側の越境防止と tenant_id） | I59: 顧客を指す値で、他の顧客のデータに触れられないようにできること | J59: HB-F-AZ-05a | K59: DDB-12 | L59: MKB-20 MKI-11 | M59: ST-15 ST-24 | N59: 全工程あり | O59: —
A60: FR-AUTHZ-002-b | B60: 機能要件 | C60: Must | D60: 対象 | E60: その他 | F60: アプリ（管理画面・idm-api） | G60: 権限データや業務データで他顧客に触れさせないのは管理画面・idm-api と業務アプリの責務 | H60: tenant_id によるテナント分離（権限データ側の越境防止） | I60: 顧客を指す値で、他の顧客のデータに触れられないようにできること | N60: アプリ側で実施 | O60: —
A61: FR-AUTHZ-003 | B61: 機能要件 | C61: Must | D61: 対象 | E61: その他 | F61: アプリ（業務アプリ） | G61: 認可はこちらでは行わない | H61: roles クレームによるロール認可 | I61: 役割を表す情報で可否を判断できること | N61: アプリ側で実施 | O61: —
A62: FR-AUTHZ-004 | B62: 機能要件 | C62: Should | D62: 対象 | E62: その他 | F62: アプリ（管理画面・idm-api） | G62: 同上 | H62: ロール階層（継承） | I62: 役割に上下関係を持たせられること | N62: アプリ側で実施 | O62: —
A63: FR-AUTHZ-005 | B63: 機能要件 | C63: Must | D63: 対象 | E63: Keycloak-Broker | F63: インフラ（本基盤） | G63: — | H63: scope ベース認可（M2M） | I63: システム間の呼び出しで、許す範囲を限定できること | J63: HB-F-AZ-07 | K63: DDB-13 | L63: MKB-21 MKI-12 | M63: IT-06 | N63: 全工程あり | O63: —
A64: FR-AUTHZ-006 | B64: 機能要件 | C64: Must | D64: 対象 | E64: Keycloak-Broker | F64: インフラ（本基盤） | G64: — | H64: カスタムクレーム注入（任意属性） | I64: 任意の属性を JWT に載せられること | J64: GD-16 GD-17 HD-05 HD-18 HJ-07 | K64: DDD-01 DDE-08 DDI-07 | L64: MKB-10 MKB-19 MKI-10 | M64: PT-02 ST-16 ST-23 | N64: 全工程あり | O64: アプリ（Keycloak-IdP 側の同じ設定は接続仕様 HE-23 に従う）
A65: FR-AUTHZ-007-a | B65: 機能要件 | C65: Must | D65: 対象 | E65: その他 | F65: アプリ（業務アプリ） | G65: 業務アプリ側の実装。本基盤はガイドとサンプルで示す | H65: API 入口での JWT 検証（アプリ側の認可統合）（アプリの実装） | I65: API の入口でアプリが JWT を検証して可否を判断できること（ガイドで示す。Lambda Authorizer は PoC 時の実装名） | N65: アプリ側で実施 | O65: —
A66: FR-AUTHZ-007-b | B66: 機能要件 | C66: Must | D66: 対象 | E66: Keycloak-Broker | F66: インフラ（本基盤） | G66: アプリ開発者向けガイドとサンプル実装・試用環境を本基盤が提供する | H66: API 入口での JWT 検証（アプリ側の認可統合）（ガイド・サンプル） | I66: API の入口でアプリが JWT を検証して可否を判断できること（ガイドで示す。Lambda Authorizer は PoC 時の実装名） | J66: GD-16 GD-18 | K66: DDJ-05 | L66: MKJ-05 | M66: UAT-04 | N66: 全工程あり | O66: —
A67: FR-AUTHZ-008 | B67: 機能要件 | C67: Must | D67: 対象 | E67: Keycloak-Broker | F67: インフラ（本基盤） | G67: — | H67: マルチイシュア対応（複数 User Pool / Realm） | I67: 発行元が複数あっても正しく検証できること | J67: GD-16 GD-17 HJ-01a HJ-07 | K67: DDB-17 DDE-08 DDI-07 | L67: MKB-19 MKB-27 MKI-10 | M67: IT-12 | N67: 全工程あり | O67: —
A68: FR-AUTHZ-009 | B68: 機能要件 | C68: Could | D68: 対象 | E68: その他 | F68: アプリ（業務アプリ） | G68: 認可はこちらでは行わない | H68: リソースレベル認可（UMA 2.0 / Fine-grained） | I68: データ 1 件ごとに細かく可否を判断できること | N68: アプリ側で実施 | O68: —
A69: FR-AUTHZ-010 | B69: 機能要件 | C69: Could | D69: 対象 | E69: その他 | F69: アプリ（業務アプリ） | G69: 同上 | H69: 動的属性ベース認可（ABAC） | I69: 属性の組み合わせで動的に可否を判断できること | N69: アプリ側で実施 | O69: —
A70: FR-USER-001-a | B70: 機能要件 | C70: Must | D70: 対象 | E70: その他 | F70: アプリ（管理画面・idm-api） | G70: 管理画面・idm-api 側の実装。Keycloak-Broker の管理 API を内部経路で呼ぶ | H70: ユーザー作成 / 更新 / 削除（CRUD）（管理画面と API） | I70: ユーザを作る・変える・消せること | N70: アプリ側で実施 | O70: —
A71: FR-USER-001-b | B71: 機能要件 | C71: Must | D71: 対象 | E71: Keycloak-Broker | F71: インフラ（本基盤） | G71: 管理 API の内部公開（F-INT-14）: 経路・呼び出し元の資格・許す操作の範囲 | H71: ユーザー作成 / 更新 / 削除（CRUD）（本基盤側の受け口） | I71: ユーザを作る・変える・消せること | J71: HE-24 | K71: DDE-12 | L71: MKB-32 | M71: IT-17 | N71: 全工程あり | O71: —
A72: FR-USER-002 | B72: 機能要件 | C72: Must | D72: 対象 | E72: Keycloak-Broker | F72: インフラ（本基盤） | G72: 属性の宣言と変換は Keycloak-Broker | H72: カスタム属性（任意フィールド） | I72: 顧客ごとの追加の項目を持たせられること | J72: HD-05 HD-18 | K72: DDD-01 | L72: MKB-10 | M72: ST-16 ST-17 | N72: 全工程あり | O72: アプリ（Keycloak-IdP 側の同じ設定は接続仕様 HE-23 に従う）
A73: FR-USER-003-a | B73: 機能要件 | C73: TBD | D73: 対象 | E73: Keycloak-Broker | F73: インフラ（本基盤） | G73: 受信窓口は Keycloak-Broker の上に立てる | H73: SCIM 2.0 プロビジョニング（受信側） | I73: 顧客の人事システムから SCIM でユーザを受け取れること | J73: HB-F-PROV-03 HB-F-PROV-04 HB-F-PROV-05 HB-F-PROV-06 HE-09 | K73: DDE-04 DDE-05 DDE-06 DDE-07 DDI-06 | L73: MKE-01 MKE-02 MKI-09 | M73: IT-04 RI-04 ST-12 ST-13 ST-14 ST-15 | N73: 全工程あり | O73: —
A74: FR-USER-003-b | B74: 機能要件 | C74: TBD | D74: 対象 | E74: その他 | F74: 顧客（顧客IdP） | G74: 顧客の人事システム・IdP 側の SCIM 送信設定と再送の作法は顧客が行う | H74: SCIM 2.0 プロビジョニング（送信側） | I74: 顧客の人事システムから SCIM でユーザを受け取れること | M74: RI-04 | N74: 顧客側で実施 | O74: —
A75: FR-USER-004 | B75: 機能要件 | C75: Must | D75: 対象 | E75: Keycloak-IdP | F75: アプリ（Keycloak-IdP） | G75: ローカル収容ユーザの話 | H75: セルフサービスプロフィール編集 | I75: ユーザが自分で自分の情報を変えられること | N75: アプリ側で実施（Keycloak-IdP 側。本基盤は ROSA の引き渡しまで＝NFR-OPS-012） | O75: アプリ（主体）
A76: FR-USER-005 | B76: 機能要件 | C76: Must | D76: 対象 | E76: その他 | F76: アプリ（管理画面・idm-api） | G76: 管理画面はアプリ | H76: ユーザー検索・一覧 | I76: ユーザを検索・一覧表示できること | N76: アプリ側で実施 | O76: —
A77: FR-USER-006-a | B77: 機能要件 | C77: Must | D77: 対象 | E77: Keycloak-Broker | F77: インフラ（本基盤） | G77: 停止と再開は Keycloak-Broker。画面はアプリ | H77: ユーザー有効化 / 無効化（suspend）（Keycloak-Broker 側） | I77: ユーザを一時的に使えなくする／戻せること。Keycloak-IdP 側で止めたユーザの Keycloak-Broker 側の写しは伝播しない。残存は Keycloak-Broker のセッション上限（12 時間）で受容（2026-09-07 決定） | J77: HB-F-PROV-10 HB-F-PROV-11 | K77: DDB-07 DDB-08 | L77: MKB-12 MKB-13 | M77: ST-18 ST-19 | N77: 全工程あり | O77: アプリ（Keycloak-IdP 側の同じ設定は接続仕様 HE-23 に従う）
A78: FR-USER-006-b | B78: 機能要件 | C78: Must | D78: 対象 | E78: その他 | F78: アプリ（管理画面・idm-api） | G78: 管理者が止める・戻す操作は管理画面から、管理 API の内部公開（F-INT-14）経由で行う | H78: ユーザー有効化 / 無効化（suspend）（操作画面） | I78: ユーザを一時的に使えなくする／戻せること。Keycloak-IdP 側で止めたユーザの Keycloak-Broker 側の写しは伝播しない。残存は Keycloak-Broker のセッション上限（12 時間）で受容（2026-09-07 決定） | M78: IT-17 | N78: アプリ側で実施 | O78: アプリ（Keycloak-IdP 側の同じ設定は接続仕様 HE-23 に従う）
A79: FR-USER-007 | B79: 機能要件 | C79: Should | D79: 対象外 | E79: — | F79: — | G79: Phase 1 では作らない（SCIM のグループ連携も対象外） | H79: ユーザーグループ管理 | I79: ユーザをグループでまとめられること | N79: Phase 1 では作らない | O79: —
A80: FR-USER-008 | B80: 機能要件 | C80: Must | D80: 対象 | E80: その他 | F80: アプリ（管理画面・idm-api） | G80: 権限はこちらでは扱わない | H80: ロール割り当て | I80: ユーザに役割を割り当てられること | N80: アプリ側で実施 | O80: —
A81: FR-USER-009 | B81: 機能要件 | C81: Should | D81: 対象 | E81: その他 | F81: アプリ（管理画面・idm-api） | G81: 管理画面はアプリ | H81: バルクインポート（CSV / JSON） | I81: ファイルからまとめてユーザを取り込めること | N81: アプリ側で実施 | O81: —
A82: FR-USER-010 | B82: 機能要件 | C82: Must | D82: 対象 | E82: Keycloak-IdP | F82: アプリ（Keycloak-IdP） | G82: ローカル収容ユーザの話 | H82: ユーザーパスワード強制リセット | I82: 管理者がユーザのパスワードを強制的に初期化できること | N82: アプリ側で実施 | O82: アプリ（主体）
A83: FR-USER-011-a | B83: 機能要件 | C83: Should | D83: 対象 | E83: Keycloak-Broker | F83: インフラ（本基盤） | G83: 保持と消去の方針は本基盤で決める。消去の対象は Keycloak-Broker・Keycloak-IdP（アプリ）・権限データ（アプリ）・共通ログ基盤にまたがるため、HK-07 は横断の手順とする | H83: ユーザー削除時の関連データ削除（GDPR 等）（本基盤の窓口と Keycloak-Broker 側） | I83: ユーザを消すときに関連するデータも消せること | J83: HD-24 HK-07 | K83: DDB-16 DDD-02 | L83: MKB-26 MKF-01 | M83: ST-20 | N83: 全工程あり | O83: —
A84: FR-USER-011-b | B84: 機能要件 | C84: Should | D84: 対象 | E84: その他 | F84: アプリ（管理画面・idm-api） | G84: 権限データ・参照用データの消去は管理画面・idm-api 側。本基盤の手順（HK-07）から依頼する | H84: ユーザー削除時の関連データ削除（GDPR 等）（権限データ側） | I84: ユーザを消すときに関連するデータも消せること | M84: OP-04 | N84: アプリ側で実施 | O84: —
A85: FR-USER-012 | B85: 機能要件 | C85: Should | D85: 対象 | E85: その他 | F85: アプリ（管理画面・idm-api） | G85: 管理画面はアプリ | H85: ユーザー作成時の招待メール | I85: 新しいユーザに招待を送れること | N85: アプリ側で実施 | O85: —
A86: FR-USER-013 | B86: 機能要件 | C86: Should | D86: 対象 | E86: Keycloak-Broker | F86: インフラ（本基盤） | G86: 対象で計上（2026-09-07 決定）。顧客IdP 経由で自動作成したユーザだけが対象で、Keycloak-IdP 収容ユーザはアプリ側の判断 | H86: 長期未使用ユーザの自動停止 | I86: 90 日ログインの無いユーザを自動で止められること | J86: HB-F-BAT-01 | K86: DDF-05 | L86: MKF-06 | M86: ST-29 | N86: 全工程あり | O86: アプリ（Keycloak-IdP 収容ユーザ分は任意）
A87: FR-ADMIN-001 | B87: 機能要件 | C87: Must | D87: 対象 | E87: その他 | F87: アプリ（管理画面・idm-api） | G87: 管理画面はアプリが作る | H87: 管理コンソール UI | I87: 管理のための画面があること | N87: アプリ側で実施 | O87: —
A88: FR-ADMIN-002 | B88: 機能要件 | C88: Must | D88: 対象 | E88: Keycloak-Broker | F88: インフラ（本基盤） | G88: 設計は本基盤。細部は運用設計で詰める | H88: テナント追加・削除 | I88: 顧客を追加・削除できること | J88: G-1.2 HB-F-ADM-14 | K88: DDB-09 DDB-10 | L88: MKB-14 MKB-15 | M88: ST-21 ST-22 | N88: 全工程あり | O88: —
A89: FR-ADMIN-003 | B89: 機能要件 | C89: Must | D89: 対象 | E89: Keycloak-Broker | F89: インフラ（本基盤） | G89: — | H89: IdP 追加・削除・更新 | I89: 顧客IdP を追加・変更・削除できること | J89: D-12 HB-F-ADM-16 | K89: DDB-11 | L89: MKB-16 MKB-17 | M89: OP-01 UAT-02 | N89: 全工程あり | O89: —
A90: FR-ADMIN-004 | B90: 機能要件 | C90: Must | D90: 対象 | E90: Keycloak-Broker | F90: インフラ（本基盤） | G90: — | H90: クライアント（App）管理 | I90: アプリの接続登録を管理できること | J90: HJ-09 | K90: DDB-14 | L90: MKB-22 MKI-13 | M90: IT-07 | N90: 全工程あり | O90: —
A91: FR-ADMIN-005 | B91: 機能要件 | C91: Must | D91: 対象 | E91: その他 | F91: アプリ（管理画面・idm-api） | G91: 権限はこちらでは扱わない | H91: ロール定義管理 | I91: 役割の定義を管理できること | N91: アプリ側で実施 | O91: —
A92: FR-ADMIN-006 | B92: 機能要件 | C92: Could | D92: 対象 | E92: その他 | F92: アプリ（管理画面・idm-api） | G92: 同上 | H92: パーミッション管理（細粒度） | I92: 権限を細かく設定できること | N92: アプリ側で実施 | O92: —
A93: FR-ADMIN-007-a | B93: 機能要件 | C93: Must | D93: 対象 | E93: Keycloak-Broker | F93: インフラ（本基盤） | G93: 何を記録し何年保つかは本基盤が決めて出力する | H93: 監査ログ閲覧（出力・項目・保持年数の指定） | I93: 監査の記録を閲覧できること。参照は全体の共通基盤側で行い、本基盤に照会画面は作らない（本基盤は出力と集約まで） | J93: HG-04 HG-05 | K93: DDD-04 DDE-09 | L93: MKH-01 MKI-15 | M93: IT-09 OP-03 | N93: 全工程あり | O93: —
A94: FR-ADMIN-007-b | B94: 機能要件 | C94: Must | D94: 対象 | E94: その他 | F94: 他組織（境界・共通基盤） | G94: 記録の閲覧は全体の共通基盤側。本基盤は指定した保持年数と形式で出すまで（OP-03 で確認） | H94: 監査ログ閲覧（共通基盤側の閲覧） | I94: 監査の記録を閲覧できること。参照は全体の共通基盤側で行い、本基盤に照会画面は作らない（本基盤は出力と集約まで） | M94: OP-03 | N94: 他組織で実施 | O94: —
A95: FR-ADMIN-008 | B95: 機能要件 | C95: Should | D95: 対象 | E95: Keycloak-Broker | F95: インフラ（本基盤） | G95: — | H95: 設定変更履歴 | I95: 設定を変えた履歴が残ること | J95: HG-04 HG-05 | K95: DDD-04 DDE-09 | L95: MKH-01 MKI-15 | M95: IT-09 OP-03 | N95: 全工程あり | O95: —
A96: FR-ADMIN-009 | B96: 機能要件 | C96: Must | D96: 対象 | E96: Keycloak-Broker | F96: インフラ（本基盤） | G96: — | H96: テナント別設定の分離 | I96: 顧客ごとに設定を分けられること | J96: HB-F-AZ-05a | K96: DDB-12 | L96: MKB-20 MKI-11 | M96: IT-12 ST-24 | N96: 全工程あり | O96: —
A97: FR-ADMIN-010 | B97: 機能要件 | C97: Must | D97: 対象 | E97: その他 | F97: アプリ（管理画面・idm-api） | G97: 管理画面の権限はアプリ | H97: 管理者ロール（RBAC for Admin） | I97: 管理者にも役割を持たせて操作を制限できること | N97: アプリ側で実施 | O97: —
A98: FR-ADMIN-011 | B98: 機能要件 | C98: Should | D98: 対象 | E98: その他 | F98: アプリ（管理画面・idm-api） | G98: 同上 | H98: テナント管理者の委譲（顧客の自社運用） | I98: 顧客の管理者に運用の一部を任せられること | N98: アプリ側で実施 | O98: —
A99: FR-ADMIN-012 | B99: 機能要件 | C99: Should | D99: 対象 | E99: Keycloak-Broker | F99: インフラ（本基盤） | G99: 振り分けの識別子入力画面とエラー画面は Keycloak-Broker で作る | H99: カスタマイズ可能なログイン UI | I99: ログイン画面の見た目を変えられること | J99: HC-04a HC-04j | K99: DDC-01 DDC-02 | L99: MKC-03 MKC-04 MKI-08 | M99: ST-10 ST-11 | N99: 全工程あり | O99: —
A100: FR-INT-001 | B100: 機能要件 | C100: Must | D100: 対象 | E100: Keycloak-Broker | F100: インフラ（本基盤） | G100: — | H100: OIDC 1.0 / OAuth 2.0 標準準拠 | I100: OIDC / OAuth 2.0 の標準に従っていること | J100: GD-09 GD-10 GD-14 GD-15 GD-16 GD-17 HB-F-AUTH-05 HE-14 HJ-02a HJ-07 HJ-10a | K100: DDB-01 DDE-01 DDE-08 DDI-02 DDI-07 | L100: MKB-02 MKB-03 MKB-19 MKI-02 MKI-10 | M100: IT-01 | N100: 全工程あり | O100: —
...

Sheet 要件・機能対応表
A1: 要件ID | B1: 要件 | C1: 要件の概要 | D1: 機能ID | E1: 機能 | F1: 機能の概要 | G1: 担当 | H1: 状況
A2: FR-AUTH-001-a | B2: ID/PW 認証（ローカルユーザー）（本基盤運用者） | C2: ID とパスワードで直接ログインできること。顧客IdP を持たない顧客のユーザは Keycloak-IdP（アプリ責務）、本基盤の運用者は Keycloak-Broker（NFR-SEC-021）で満たす | D2: F-AUTH-01 | E2: Keycloak-IdP 収容ユーザのログイン | F2: 顧客側に認証システムが無い顧客のユーザが Keycloak-IdP に、本基盤の運用者が Keycloak-Broker に、ID とパスワードで直接ログインする。顧客のユーザ分は Keycloak-IdP 側（アプリ責務）、運用者分は本基盤 | G2: インフラ（本基盤） | H2: 全工程あり
D3: NF-OPS-11 | E3: 運用者アカウントと権限の保護 | F3: 本基盤運用者のローカル認証（WebAuthn 必須）、常時の全権付与の禁止と必要時だけの昇格、緊急時アクセスとの関係、定期棚卸し | G3: インフラ（本基盤） | H3: 全工程あり
A4: FR-AUTH-001-b | B4: ID/PW 認証（ローカルユーザー）（顧客IdP を持たない顧客のユーザ） | C4: ID とパスワードで直接ログインできること。顧客IdP を持たない顧客のユーザは Keycloak-IdP（アプリ責務）、本基盤の運用者は Keycloak-Broker（NFR-SEC-021）で満たす | D4: F-AUTH-01 | E4: Keycloak-IdP 収容ユーザのログイン | F4: 顧客側に認証システムが無い顧客のユーザが Keycloak-IdP に、本基盤の運用者が Keycloak-Broker に、ID とパスワードで直接ログインする。顧客のユーザ分は Keycloak-IdP 側（アプリ責務）、運用者分は本基盤 | G4: アプリ（Keycloak-IdP） | H4: アプリ側で実施（Keycloak-IdP 側。本基盤は ROSA の引き渡しまで＝NFR-OPS-012）
A5: FR-AUTH-002 | B5: Authorization Code + PKCE（SPA / モバイル） | C5: 画面を持つアプリが、標準の手順（認可コード＋PKCE）でログインを開始し JWT を受け取れること | D5: F-AUTH-05 | E5: 顧客IdPへのログイン委譲（OIDC） | F5: 顧客が持つ認証システムに OIDC で認証を委ね、その結果を受け取ってログインさせる | G5: インフラ（本基盤） | H5: 全工程あり
D6: F-INT-13 | E6: アプリの接続登録（クライアント登録） | F6: 新しいアプリを Keycloak-Broker に接続するときの登録内容・申請の流れ・接続情報の渡し方 | G6: インフラ（本基盤） | H6: 全工程あり
A7: FR-AUTH-003 | B7: Authorization Code + client_secret（SSR） | C7: サーバ側で処理するアプリが、接続用パスワードを使う標準の手順でログインできること | D7: F-AUTH-05 | E7: 顧客IdPへのログイン委譲（OIDC） | F7: 顧客が持つ認証システムに OIDC で認証を委ね、その結果を受け取ってログインさせる | G7: インフラ（本基盤） | H7: 全工程あり
D8: F-INT-13 | E8: アプリの接続登録（クライアント登録） | F8: 新しいアプリを Keycloak-Broker に接続するときの登録内容・申請の流れ・接続情報の渡し方 | G8: インフラ（本基盤） | H8: 全工程あり
A9: FR-AUTH-004 | B9: Client Credentials（M2M） | C9: 人ではなくシステムが API を呼ぶための資格を発行できること | D9: F-AZ-07 | E9: システム間 JWT の発行 | F9: アプリやバッチがシステムとして API を呼ぶための資格を発行する | G9: インフラ（本基盤） | H9: 全工程あり
A10: FR-AUTH-005 | B10: Token Exchange（RFC 8693） | C10: あるアプリ向けの JWT を、別のアプリ向けに交換できること | D10: F-AZ-08 | E10: 別アプリ向け JWT への交換（Token Exchange） | F10: あるアプリ向けに出した JWT を、別のアプリ向けの JWT に引き換える | G10: — | H10: Phase 1 では作らない
A11: FR-AUTH-006 | B11: Device Code Flow（画面のない機器・CLI 向けログイン） | C11: 画面のない機器や CLI からログインできること | D11: — | E11: —（本基盤に作る機能なし） | F11: 2026-08-16 の判断で Phase 1 対象外 | G11: — | H11: Phase 1 では作らない
A12: FR-AUTH-007 | B12: mTLS Client Authentication（RFC 8705、証明書によるアプリ認証） | C12: 証明書でアプリを認証できること | D12: — | E12: —（本基盤に作る機能なし） | F12: 2026-08-16 の判断で対象外。金融水準の顧客が現れたときに再評価 | G12: — | H12: Phase 1 では作らない
A13: FR-AUTH-008 | B13: ROPC（Password Grant） | C13: アプリがユーザのパスワードを直接受け取ってログインさせる方式 | D13: — | E13: —（本基盤に作る機能なし） | F13: 採用しない（安全でないため） | G13: — | H13: Phase 1 では作らない
A14: FR-AUTH-009 | B14: パスワードポリシー（最小長・複雑性） | C14: パスワードの最小の長さと文字種の組み合わせを決められること | D14: F-AUTH-01 | E14: Keycloak-IdP 収容ユーザのログイン | F14: 顧客側に認証システムが無い顧客のユーザが Keycloak-IdP に、本基盤の運用者が Keycloak-Broker に、ID とパスワードで直接ログインする。顧客のユーザ分は Keycloak-IdP 側（アプリ責務）、運用者分は本基盤 | G14: アプリ（Keycloak-IdP） | H14: アプリ側で実施（Keycloak-IdP 側。本基盤は ROSA の引き渡しまで＝NFR-OPS-012）
A15: FR-AUTH-010 | B15: パスワード履歴（N 個と一致禁止） | C15: 過去に使ったパスワードを一定個数まで再利用させないこと | D15: F-AUTH-01 | E15: Keycloak-IdP 収容ユーザのログイン | F15: 顧客側に認証システムが無い顧客のユーザが Keycloak-IdP に、本基盤の運用者が Keycloak-Broker に、ID とパスワードで直接ログインする。顧客のユーザ分は Keycloak-IdP 側（アプリ責務）、運用者分は本基盤 | G15: アプリ（Keycloak-IdP） | H15: アプリ側で実施（Keycloak-IdP 側。本基盤は ROSA の引き渡しまで＝NFR-OPS-012）
A16: FR-AUTH-011 | B16: アカウントロック（連続失敗） | C16: パスワードを連続で間違えたら一時的にログインを受け付けないこと | D16: F-AUTH-20 | E16: 連続失敗時の一時締め出し | F16: パスワードの連続失敗を検知して一時的に受け付けなくする | G16: アプリ（Keycloak-IdP） | H16: アプリ側で実施（Keycloak-IdP 側）
A17: FR-AUTH-012 | B17: パスワード有効期限 | C17: パスワードに有効期限を設けられること | D17: F-AUTH-01 | E17: Keycloak-IdP 収容ユーザのログイン | F17: 顧客側に認証システムが無い顧客のユーザが Keycloak-IdP に、本基盤の運用者が Keycloak-Broker に、ID とパスワードで直接ログインする。顧客のユーザ分は Keycloak-IdP 側（アプリ責務）、運用者分は本基盤 | G17: アプリ（Keycloak-IdP） | H17: アプリ側で実施（Keycloak-IdP 側。本基盤は ROSA の引き渡しまで＝NFR-OPS-012）
A18: FR-AUTH-013 | B18: セルフサービスパスワードリセット | C18: ユーザが自分でパスワードを再設定できること | D18: F-AUTH-18 | E18: パスワードの自己再設定 | F18: ユーザが自分でパスワードを再設定する | G18: アプリ（Keycloak-IdP） | H18: アプリ側で実施
A19: FR-AUTH-014 | B19: 初期パスワード強制変更 | C19: 初回ログイン時にパスワードの変更を強制できること | D19: F-AUTH-19 | E19: パスワード変更・初回強制変更 | F19: パスワードの変更と、初回ログイン時に変更を強制する動き | G19: アプリ（Keycloak-IdP） | H19: アプリ側で実施
A20: FR-AUTH-015 | B20: DPoP（RFC 9449、送信者に縛った JWT） | C20: JWT を受け取った本人以外が使い回せないよう、送信者を JWT に縛りつけること（DPoP） | D20: — | E20: —（本基盤に作る機能なし） | F20: 提案書で新規想定として挙げた項目。Phase 1 では作らない | G20: — | H20: Phase 1 では作らない
... A22: FR-FED-001 | B22: Auth0 OIDC IdP 連携 | C22: Auth0 を顧客IdP として接続できること | D22: F-AUTH-05 | E22: 顧客IdPへのログイン委譲（OIDC） | F22: 顧客が持つ認証システムに OIDC で認証を委ね、その結果を受け取ってログインさせる | G22: インフラ（本基盤） | H22: 全工程あり
D23: F-ADM-16 | E23: 顧客IdPの接続登録 | F23: 顧客IdPを基盤に接続する登録作業 | G23: インフラ（本基盤） | H23: 全工程あり
A24: FR-FED-002 | B24: Entra ID（Azure AD）OIDC 連携 | C24: Entra ID（Azure AD）を顧客IdP として接続できること | D24: F-AUTH-05 | E24: 顧客IdPへのログイン委譲（OIDC） | F24: 顧客が持つ認証システムに OIDC で認証を委ね、その結果を受け取ってログインさせる | G24: インフラ（本基盤） | H24: 全工程あり
D25: F-ADM-16 | E25: 顧客IdPの接続登録 | F25: 顧客IdPを基盤に接続する登録作業 | G25: インフラ（本基盤） | H25: 全工程あり
A26: FR-FED-003 | B26: Okta OIDC 連携 | C26: Okta を顧客IdP として接続できること | D26: F-AUTH-05 | E26: 顧客IdPへのログイン委譲（OIDC） | F26: 顧客が持つ認証システムに OIDC で認証を委ね、その結果を受け取ってログインさせる | G26: インフラ（本基盤） | H26: 全工程あり
D27: F-ADM-16 | E27: 顧客IdPの接続登録 | F27: 顧客IdPを基盤に接続する登録作業 | G27: インフラ（本基盤） | H27: 全工程あり
A28: FR-FED-004 | B28: Google Workspace OIDC 連携 | C28: Google Workspace を顧客IdP として接続できること | D28: F-AUTH-05 | E28: 顧客IdPへのログイン委譲（OIDC） | F28: 顧客が持つ認証システムに OIDC で認証を委ね、その結果を受け取ってログインさせる | G28: インフラ（本基盤） | H28: 全工程あり
D29: F-ADM-16 | E29: 顧客IdPの接続登録 | F29: 顧客IdPを基盤に接続する登録作業 | G29: インフラ（本基盤） | H29: 全工程あり
A30: FR-FED-005 | B30: SAML 2.0 IdP として受け入れ（SP モード） | C30: 旧方式（SAML）の顧客IdP からログインを受け入れられること | D30: F-AUTH-06 | E30: 顧客IdPへのログイン委譲（SAML） | F30: 顧客が持つ認証システムに SAML で認証を委ね、その結果を受け取ってログインさせる | G30: インフラ（本基盤） | H30: 全工程あり
D31: F-ADM-16 | E31: 顧客IdPの接続登録 | F31: 顧客IdPを基盤に接続する登録作業 | G31: インフラ（本基盤） | H31: 全工程あり
A32: FR-FED-006 | B32: SAML 2.0 IdP として発行（IdP モード） | C32: Keycloak-Broker が旧方式（SAML）の提供元として、業務システムへログインを提供できること | D32: F-INT-01 | E32: 業務システムへの認証提供 | F32: 業務システムに対して、Keycloak-Broker が認証の提供元として振る舞う | G32: インフラ（本基盤） | H32: 全工程あり
D33: F-INT-02 | E33: 業務システム側のユーザ自動作成 | F33: 業務システム側で、初回ログイン時にユーザを自動作成させる | G33: インフラ（本基盤） | H33: 全工程あり
A34: FR-FED-007 | B34: LDAP / AD 直接連携 | C34: 社内ディレクトリ（LDAP / AD）に直接つなげること | D34: — | E34: —（本基盤に作る機能なし） | F34: Phase 1 では作らない | G34: — | H34: Phase 1 では作らない
A35: FR-FED-008 | B35: JIT プロビジョニング | C35: 顧客IdP 経由で初めて来た人を、その場でユーザとして自動作成できること | D35: F-AUTH-05 | E35: 顧客IdPへのログイン委譲（OIDC） | F35: 顧客が持つ認証システムに OIDC で認証を委ね、その結果を受け取ってログインさせる | G35: インフラ（本基盤） | H35: 全工程あり
D36: F-PROV-01 | E36: 初回ログイン時のユーザ自動作成（JIT） | F36: 顧客IdP経由で初めてログインした人を、その場で Keycloak-Broker のユーザとして作成する | G36: インフラ（本基盤） | H36: 全工程あり
D37: F-PROV-03 | E37: 顧客IdP からのユーザ情報の同期 | F37: 顧客IdP から SCIM でユーザの登録・更新・削除通知・検索を受け取り、本基盤へ反映する。呼び出し口ごとの違いは提供 API 一覧で持つ。グループ連携は初期リリース対象外 | G37: インフラ（本基盤） | H37: 全工程あり
A38: FR-FED-009 | B38: 属性マッピング / クレーム変換 | C38: 顧客ごとにバラバラな属性名を、基盤の統一名に変換して取り込めること | D38: F-PROV-02 | E38: ログイン時の属性更新 | F38: 2 回目以降のログインで、顧客側の最新情報を使って属性を更新する | G38: インフラ（本基盤） | H38: 全工程あり
D39: F-PROV-03 | E39: 顧客IdP からのユーザ情報の同期 | F39: 顧客IdP から SCIM でユーザの登録・更新・削除通知・検索を受け取り、本基盤へ反映する。呼び出し口ごとの違いは提供 API 一覧で持つ。グループ連携は初期リリース対象外 | G39: インフラ（本基盤） | H39: 全工程あり
D40: F-PROV-08 | E40: 顧客IdP から受け取る属性の名前の統一 | F40: 顧客ごとにバラバラな項目名を基盤内の統一名に変換して取り込む。統一名の辞書と 顧客IdPごとの変換表を含む | G40: インフラ（本基盤） | H40: 全工程あり
A41: FR-FED-010 | B41: 複数 IdP 並行運用（マルチテナント） | C41: 複数の顧客IdP を同時に運用でき、顧客ごとに分離できること | D41: F-AZ-05 | E41: 顧客越境の防止（Keycloak-Broker 側） | F41: ユーザが自分の顧客以外の顧客IdPを使ってログインできないようにする。権限データ側の越境防止はアプリの責務 | G41: インフラ（本基盤） | H41: 全工程あり
D42: NF-ARC-04 | E42: Realm・ブランド区画構成 | F42: Keycloak-Brokerを何個の区画に分けるか。ブランドごとの分け方と発行元の規律 | G42: インフラ（本基盤） | H42: 全工程あり
A43: FR-FED-011-a | B43: 顧客追加時のオンボーディングフロー（本基盤側の登録） | C43: 新しい顧客を迎え入れるときの、登録から利用開始までの流れが用意されていること | D43: F-ADM-14 | E43: 顧客の作成 | F43: 新しい顧客を作成する | G43: インフラ（本基盤） | H43: 全工程あり
D44: F-ADM-16 | E44: 顧客IdPの接続登録 | F44: 顧客IdPを基盤に接続する登録作業 | G44: インフラ（本基盤） | H44: 全工程あり
D45: F-ADM-17 | E45: 接続設定の変更・証明書更新 | F45: 接続済みの認証システムの設定変更と、期限が来る証明書の入れ替え | G45: インフラ（本基盤） | H45: 全工程あり
D46: F-INT-11 | E46: 顧客IdP の接続情報の自動追随 | F46: 顧客IdPの接続情報を定期的に取り直し、証明書の入れ替えに自動追随する | G46: インフラ（本基盤） | H46: 全工程あり
A47: FR-FED-011-b | B47: 顧客追加時のオンボーディングフロー（顧客側の設定） | C47: 新しい顧客を迎え入れるときの、登録から利用開始までの流れが用意されていること | D47: F-ADM-17 | E47: 接続設定の変更・証明書更新 | F47: 接続済みの認証システムの設定変更と、期限が来る証明書の入れ替え | G47: 顧客（顧客IdP） | H47: 顧客側で実施
A48: FR-FED-012-a | B48: フェデレーション時の MFA 重複回避（取り込み側） | C48: 顧客IdP 側で追加認証を済ませた人に、Keycloak-Broker で二重に追加認証を求めないこと | D48: F-AUTH-05 | E48: 顧客IdPへのログイン委譲（OIDC） | F48: 顧客が持つ認証システムに OIDC で認証を委ね、その結果を受け取ってログインさせる | G48: インフラ（本基盤） | H48: 全工程あり
D49: F-AUTH-09 | E49: Keycloak-Broker と Keycloak-IdP の連携 | F49: Keycloak-Broker から見て Keycloak-IdP を顧客IdP の 1 つ（共有エントリ）として接続する。識別子の引き継ぎ・追加認証結果の取り込み・ログアウト連鎖・セッション上限の同値を含む。Keycloak-IdP 側の Client・Realm 設定は要求仕様としてアプリチームへ渡す（2026-09-07 復活: 2 台構成に戻したため） | G49: インフラ（本基盤） | H49: 全工程あり
A50: FR-FED-012-b | B50: フェデレーション時の MFA 重複回避（実施側） | C50: 顧客IdP 側で追加認証を済ませた人に、Keycloak-Broker で二重に追加認証を求めないこと | D50: F-AUTH-05 | E50: 顧客IdPへのログイン委譲（OIDC） | F50: 顧客が持つ認証システムに OIDC で認証を委ね、その結果を受け取ってログインさせる | G50: 顧客（顧客IdP） | H50: 顧客側で実施
A51: FR-FED-013 | B51: ログイン画面での顧客IdP への振り分け（HRD） | C51: ログイン画面で入力した識別子から顧客IdP を自動で判定して送ること。顧客IdP の一覧は見せない。1 顧客に複数ある場合のみ選ばせる | D51: F-AUTH-02 | E51: 顧客IdPの自動振り分け | F51: ログイン画面で入力された ID から、その人がどの顧客IdPのユーザかを判定し、自動で振り分ける | G51: インフラ（本基盤） | H51: 全工程あり
D52: F-AUTH-03 | E52: 振り分け失敗時のパスワード入力への切替 | F52: 顧客IdPを判定できなかったときに、パスワード入力欄に切り替えて処理を続ける逃げ道 | G52: インフラ（本基盤） | H52: 全工程あり
D53: F-AUTH-04 | E53: 顧客IdPの選択（1 顧客に複数） | F53: 1 つの顧客に顧客IdPが複数ある場合に、ユーザにどれを使うか選ばせる | G53: インフラ（本基盤） | H53: 全工程あり
D54: F-AUTH-25 | E54: ログイン画面の表示（ブランド・並び順） | F54: ログイン画面の見せ方。ブランドごとの表示切替と、顧客IdPの並び順 | G54: インフラ（本基盤） | H54: 全工程あり
A55: FR-FED-014 | B55: Custom Domain での federation | C55: 顧客ごとの独自ドメインでフェデレーションできること | D55: — | E55: —（本基盤に作る機能なし） | F55: Phase 1 では作らない | G55: — | H55: Phase 1 では作らない
A56: FR-FED-015 | B56: Keycloak-Broker ⇄ Keycloak-IdP 連携 | C56: 顧客IdP を持たない顧客のユーザを Keycloak-Broker から Keycloak-IdP へ委譲してログインさせられること。識別子の引き継ぎ・追加認証結果の取り込み・ログアウト連鎖・セッション上限の同値（12 時間）・閉域の単方向接続を含む | D56: F-AUTH-09 | E56: Keycloak-Broker と Keycloak-IdP の連携 | F56: Keycloak-Broker から見て Keycloak-IdP を顧客IdP の 1 つ（共有エントリ）として接続する。識別子の引き継ぎ・追加認証結果の取り込み・ログアウト連鎖・セッション上限の同値を含む。Keycloak-IdP 側の Client・Realm 設定は要求仕様としてアプリチームへ渡す（2026-09-07 復活: 2 台構成に戻したため） | G56: インフラ（本基盤） | H56: 全工程あり
A57: FR-MFA-001 | B57: TOTP（Google Authenticator 等） | C57: スマートフォンアプリの数字コードで追加認証できること | D57: F-AUTH-10 | E57: 追加認証の利用 | F57: パスワードに加えて 2 つ目の要素で本人を確かめる。数字コードと生体・セキュリティキーの両方を含む | G57: アプリ（Keycloak-IdP） | H57: アプリ側で実施
D58: F-AUTH-12 | E58: 追加認証の登録 | F58: 2 つ目の要素を初めて登録する流れ。数字コードと生体・セキュリティキーの両方を含む | G58: アプリ（Keycloak-IdP） | H58: アプリ側で実施
A59: FR-MFA-002 | B59: WebAuthn / FIDO2（Passkeys） | C59: 生体認証やセキュリティキーで追加認証できること | D59: F-AUTH-10 | E59: 追加認証の利用 | F59: パスワードに加えて 2 つ目の要素で本人を確かめる。数字コードと生体・セキュリティキーの両方を含む | G59: アプリ（Keycloak-IdP） | H59: アプリ側で実施
D60: F-AUTH-12 | E60: 追加認証の登録 | F60: 2 つ目の要素を初めて登録する流れ。数字コードと生体・セキュリティキーの両方を含む | G60: アプリ（Keycloak-IdP） | H60: アプリ側で実施
A61: FR-MFA-003 | B61: SMS OTP | C61: SMS の数字コードで追加認証できること | D61: — | E61: —（本基盤に作る機能なし） | F61: Phase 1 では作らない | G61: — | H61: Phase 1 では作らない
A62: FR-MFA-004 | B62: メール OTP | C62: メールの数字コードで追加認証できること | D62: — | E62: —（本基盤に作る機能なし） | F62: Phase 1 では作らない | G62: — | H62: Phase 1 では作らない
A63: FR-MFA-005 | B63: バックアップコード | C63: 端末を失くしたときに使う予備のコードを発行できること | D63: F-AUTH-15 | E63: 復旧用コードの発行・利用 | F63: 端末を失くしたときに使う一度きりのコードを発行し、利用させる | G63: アプリ（Keycloak-IdP） | H63: アプリ側で実施
A64: FR-MFA-006 | B64: 条件付き MFA（IP / リスクベース） | C64: 接続元やリスクに応じて追加認証を出し分けられること | D64: — | E64: —（本基盤に作る機能なし） | F64: Phase 1 では作らない | G64: — | H64: Phase 1 では作らない
A65: FR-MFA-007 | B65: MFA 強制 / 任意の切替（ロール単位） | C65: 追加認証を必須にするか任意にするかを役割ごとに切り替えられること | D65: F-AUTH-10 | E65: 追加認証の利用 | F65: パスワードに加えて 2 つ目の要素で本人を確かめる。数字コードと生体・セキュリティキーの両方を含む | G65: アプリ（Keycloak-IdP） | H65: アプリ側で実施
A66: FR-MFA-008 | B66: 端末記憶（Trusted Device） | C66: 一度確認した端末を覚えて、次回から追加認証を省けること | D66: — | E66: —（本基盤に作る機能なし） | F66: Phase 1 では作らない | G66: — | H66: Phase 1 では作らない
A67: FR-MFA-009 | B67: 管理者の MFA 強制 | C67: 管理者には追加認証を必ず求めること | D67: F-AUTH-10 | E67: 追加認証の利用 | F67: パスワードに加えて 2 つ目の要素で本人を確かめる。数字コードと生体・セキュリティキーの両方を含む | G67: アプリ（Keycloak-IdP） | H67: アプリ側で実施
A68: FR-SSO-001 | B68: 同一 IdP 内の複数 Client 間 SSO | C68: 同じ顧客の複数のアプリを、一度のログインで行き来できること | D68: F-AUTH-23 | E68: ログイン状態の保持とタイムアウト | F68: ログイン状態をどこにどれだけ保つか、いつ切れるか。アプリ側のセッションとの関係を含む | G68: インフラ（本基盤） | H68: 全工程あり
A69: FR-SSO-002 | B69: Auth0/Entra 経由のクロス IdP SSO | C69: 顧客IdP を経由した場合も、複数のアプリを一度のログインで行き来できること | D69: F-AUTH-05 | E69: 顧客IdPへのログイン委譲（OIDC） | F69: 顧客が持つ認証システムに OIDC で認証を委ね、その結果を受け取ってログインさせる | G69: インフラ（本基盤） | H69: 全工程あり
D70: F-AUTH-23 | E70: ログイン状態の保持とタイムアウト | F70: ログイン状態をどこにどれだけ保つか、いつ切れるか。アプリ側のセッションとの関係を含む | G70: インフラ（本基盤） | H70: 全工程あり
A71: FR-SSO-003-a | B71: ローカルログアウト（アプリ Cookie 削除のみ）（アプリの実装） | C71: アプリ側だけでログアウトできること（Keycloak-Broker の状態は保つ） | D71: NF-DOC-01 | E71: アプリ開発者向けガイド（共通部） | F71: アプリ開発者へ渡すガイドのうち、特定の機能に紐づかない導入・運用・参照の部分 | G71: アプリ（業務アプリ） | H71: アプリ側で実施
A72: FR-SSO-003-b | B72: ローカルログアウト（アプリ Cookie 削除のみ）（ガイド・サンプル） | C72: アプリ側だけでログアウトできること（Keycloak-Broker の状態は保つ） | D72: F-AUTH-24 | E72: アプリへのログアウト連携 | F72: 1 箇所でログアウトしたとき、他のアプリのログイン状態も切る仕組み | G72: インフラ（本基盤） | H72: 全工程あり
D73: NF-DOC-01 | E73: アプリ開発者向けガイド（共通部） | F73: アプリ開発者へ渡すガイドのうち、特定の機能に紐づかない導入・運用・参照の部分 | G73: インフラ（本基盤） | H73: 全工程あり
A74: FR-SSO-004 | B74: IdP セッション破棄（OIDC RP-Initiated Logout） | C74: Keycloak-Broker のログイン状態を破棄できること | D74: F-AUTH-24 | E74: アプリへのログアウト連携 | F74: 1 箇所でログアウトしたとき、他のアプリのログイン状態も切る仕組み | G74: インフラ（本基盤） | H74: 全工程あり
A75: FR-SSO-005 | B75: フェデレーション IdP セッション破棄（連動ログアウト） | C75: Keycloak-Broker のログアウトを顧客IdP 側にも連動させられること | D75: F-AUTH-24 | E75: アプリへのログアウト連携 | F75: 1 箇所でログアウトしたとき、他のアプリのログイン状態も切る仕組み | G75: インフラ（本基盤） | H75: 全工程あり
A76: FR-SSO-006 | B76: Front-Channel Logout | C76: 画面経由で他のアプリにログアウトを伝えられること | D76: — | E76: —（本基盤に作る機能なし） | F76: Back-Channel を採用するため作らない | G76: — | H76: Phase 1 では作らない
A77: FR-SSO-007 | B77: Back-Channel Logout（RFC 8606） | C77: サーバ間の通知で他のアプリにログアウトを伝えられること | D77: F-AUTH-24 | E77: アプリへのログアウト連携 | F77: 1 箇所でログアウトしたとき、他のアプリのログイン状態も切る仕組み | G77: インフラ（本基盤） | H77: 全工程あり
A78: FR-SSO-008 | B78: セッションタイムアウト設定 | C78: ログイン状態が切れるまでの時間を設定できること。無操作 1 時間・上限 12 時間（2026-09-07 更新、旧 24 時間） | D78: F-AUTH-23 | E78: ログイン状態の保持とタイムアウト | F78: ログイン状態をどこにどれだけ保つか、いつ切れるか。アプリ側のセッションとの関係を含む | G78: インフラ（本基盤） | H78: 全工程あり
A79: FR-SSO-009 | B79: アクセストークン強制無効化（Revocation） | C79: 発行済みの JWT を強制的に使えなくできること。セッションとリフレッシュトークンは即時失効、アクセストークンは署名のみで検証されるため最大 30 分は残る（契約説明に明記） | D79: F-PROV-10 | E79: ユーザの停止（消さずに無効化） | F79: ユーザを削除せず使えない状態にし、停止日時を記録する | G79: インフラ（本基盤） | H79: 全工程あり
D80: F-AZ-10 | E80: アプリへの JWT 発行 | F80: アプリへ渡す JWT を発行し、失効させ、有効性を確かめられるようにする。何を載せるか・要求できる範囲の定義はこの機能の設計作業（HJ-07）で行う | G80: インフラ（本基盤） | H80: 全工程あり
A81: FR-SSO-010-a | B81: 強制全セッション破棄（管理者操作）（管理画面からの操作） | C81: 管理者の操作で、対象のログイン状態をまとめて破棄できること | D81: F-ADM-10 | E81: 強制ログアウト（管理者） | F81: 管理者がユーザのログイン状態を強制的に終了させる。個別・顧客単位・全体の 3 段階 | G81: アプリ（管理画面・idm-api） | H81: アプリ側で実施
D82: F-INT-14 | E82: アプリ向け管理 API の公開 | F82: アプリのサーバから Keycloak-Broker の管理 API を呼べるようにする。到達経路・呼び出し元の資格・許してよい操作の範囲を決める | G82: アプリ（管理画面・idm-api） | H82: アプリ側で実施
A83: FR-SSO-010-b | B83: 強制全セッション破棄（管理者操作）（本基盤側の受け口） | C83: 管理者の操作で、対象のログイン状態をまとめて破棄できること | D83: F-INT-14 | E83: アプリ向け管理 API の公開 | F83: アプリのサーバから Keycloak-Broker の管理 API を呼べるようにする。到達経路・呼び出し元の資格・許してよい操作の範囲を決める | G83: インフラ（本基盤） | H83: 全工程あり
A84: FR-AUTHZ-001-a | B84: JWT クレームベース認可（JWT に載せる側） | C84: JWT に載せた情報でアプリが可否を判断できること | D84: F-AZ-10 | E84: アプリへの JWT 発行 | F84: アプリへ渡す JWT を発行し、失効させ、有効性を確かめられるようにする。何を載せるか・要求できる範囲の定義はこの機能の設計作業（HJ-07）で行う | G84: インフラ（本基盤） | H84: 全工程あり
D85: F-PROV-16 | E85: 顧客番号と基盤識別子の対応づけ | F85: 顧客側のユーザ番号と基盤側の識別子を対応づけて管理する | G85: インフラ（本基盤） | H85: 全工程あり
A86: FR-AUTHZ-001-b | B86: JWT クレームベース認可（判定する側） | C86: JWT に載せた情報でアプリが可否を判断できること | D86: F-AZ-10 | E86: アプリへの JWT 発行 | F86: アプリへ渡す JWT を発行し、失効させ、有効性を確かめられるようにする。何を載せるか・要求できる範囲の定義はこの機能の設計作業（HJ-07）で行う | G86: アプリ（業務アプリ） | H86: アプリ側で実施
D87: F-AZ-03 | E87: アプリ利用可否の判定 | F87: ユーザがそのアプリを使ってよいかを判定する | G87: アプリ（業務アプリ） | H87: アプリ側で実施
A88: FR-AUTHZ-002-a | B88: tenant_id によるテナント分離（認証側の越境防止と tenant_id） | C88: 顧客を指す値で、他の顧客のデータに触れられないようにできること | D88: F-PROV-03 | E88: 顧客IdP からのユーザ情報の同期 | F88: 顧客IdP から SCIM でユーザの登録・更新・削除通知・検索を受け取り、本基盤へ反映する。呼び出し口ごとの違いは提供 API 一覧で持つ。グループ連携は初期リリース対象外 | G88: インフラ（本基盤） | H88: 全工程あり
D89: F-AZ-05 | E89: 顧客越境の防止（Keycloak-Broker 側） | F89: ユーザが自分の顧客以外の顧客IdPを使ってログインできないようにする。権限データ側の越境防止はアプリの責務 | G89: インフラ（本基盤） | H89: 全工程あり
A90: FR-AUTHZ-002-b | B90: tenant_id によるテナント分離（権限データ側の越境防止） | C90: 顧客を指す値で、他の顧客のデータに触れられないようにできること | D90: F-AZ-05 | E90: 顧客越境の防止（Keycloak-Broker 側） | F90: ユーザが自分の顧客以外の顧客IdPを使ってログインできないようにする。権限データ側の越境防止はアプリの責務 | G90: アプリ（管理画面・idm-api） | H90: アプリ側で実施
A91: FR-AUTHZ-003 | B91: roles クレームによるロール認可 | C91: 役割を表す情報で可否を判断できること | D91: F-AZ-04 | E91: アプリ内の役割の解決 | F91: アプリごとの役割の値を解決して返す | G91: アプリ（業務アプリ） | H91: アプリ側で実施
A92: FR-AUTHZ-004 | B92: ロール階層（継承） | C92: 役割に上下関係を持たせられること | D92: F-ADM-12 | E92: アプリ内の役割の設定 | F92: アプリごとの役割（ロール）をユーザに割り当てる | G92: アプリ（管理画面・idm-api） | H92: アプリ側で実施
D93: F-AZ-04 | E93: アプリ内の役割の解決 | F93: アプリごとの役割の値を解決して返す | G93: アプリ（管理画面・idm-api） | H93: アプリ側で実施
A94: FR-AUTHZ-005 | B94: scope ベース認可（M2M） | C94: システム間の呼び出しで、許す範囲を限定できること | D94: F-AZ-07 | E94: システム間 JWT の発行 | F94: アプリやバッチがシステムとして API を呼ぶための資格を発行する | G94: インフラ（本基盤） | H94: 全工程あり
A95: FR-AUTHZ-006 | B95: カスタムクレーム注入（任意属性） | C95: 任意の属性を JWT に載せられること | D95: F-PROV-08 | E95: 顧客IdP から受け取る属性の名前の統一 | F95: 顧客ごとにバラバラな項目名を基盤内の統一名に変換して取り込む。統一名の辞書と 顧客IdPごとの変換表を含む | G95: インフラ（本基盤） | H95: 全工程あり
D96: F-AZ-10 | E96: アプリへの JWT 発行 | F96: アプリへ渡す JWT を発行し、失効させ、有効性を確かめられるようにする。何を載せるか・要求できる範囲の定義はこの機能の設計作業（HJ-07）で行う | G96: インフラ（本基盤） | H96: 全工程あり
A97: FR-AUTHZ-007-a | B97: API 入口での JWT 検証（アプリ側の認可統合）（アプリの実装） | C97: API の入口でアプリが JWT を検証して可否を判断できること（ガイドで示す。Lambda Authorizer は PoC 時の実装名） | D97: NF-DOC-01 | E97: アプリ開発者向けガイド（共通部） | F97: アプリ開発者へ渡すガイドのうち、特定の機能に紐づかない導入・運用・参照の部分 | G97: アプリ（業務アプリ） | H97: アプリ側で実施
A98: FR-AUTHZ-007-b | B98: API 入口での JWT 検証（アプリ側の認可統合）（ガイド・サンプル） | C98: API の入口でアプリが JWT を検証して可否を判断できること（ガイドで示す。Lambda Authorizer は PoC 時の実装名） | D98: F-AZ-10 | E98: アプリへの JWT 発行 | F98: アプリへ渡す JWT を発行し、失効させ、有効性を確かめられるようにする。何を載せるか・要求できる範囲の定義はこの機能の設計作業（HJ-07）で行う | G98: インフラ（本基盤） | H98: 全工程あり
D99: F-BAT-04 | E99: JWT 署名鍵の定期入れ替え | F99: JWT の署名に使う鍵を定期的に入れ替える。切り替え中も止めないための並走期間を含む | G99: インフラ（本基盤） | H99: 全工程あり
D100: NF-DOC-01 | E100: アプリ開発者向けガイド（共通部） | F100: アプリ開発者へ渡すガイドのうち、特定の機能に紐づかない導入・運用・参照の部分 | G100: インフラ（本基盤） | H100: 全工程あり
A101: FR-AUTHZ-008 | B101: マルチイシュア対応（複数 User Pool / Realm） | C101: 発行元が複数あっても正しく検証できること | D101: F-AZ-10 | E101: アプリへの JWT 発行 | F101: アプリへ渡す JWT を発行し、失効させ、有効性を確かめられるようにする。何を載せるか・要求できる範囲の定義はこの機能の設計作業（HJ-07）で行う | G101: インフラ（本基盤） | H101: 全工程あり
...

Sheet WBS(基本設計)
A1: ID | B1: 分類 | C1: 作業種別 | D1: 機能グループ | E1: 機能名 | F1: 項目 | G1: 概要 | H1: 成果物と完了条件 | I1: 人日 | J1: 担当（案②: 一部移管） | K1: 担当（案③: アプリ構築） | L1: 判断根拠 | M1: 根拠の補足 | N1: スコープ | O1: 当初想定 | P1: 依存 | Q1: 状態 | R1: 出典 | S1: 機能ID
A2: HB-F-AUTH-02 | B2: HB-F 機能仕様書 | C2: 設計書の執筆 | D2: ログインの振り分け | E2: 顧客IdPの自動振り分け | F2: 機能仕様書: 顧客IdPの自動振り分け（HRD） | G2: 入力された ID から、その人がどの顧客IdPのユーザかを判定し、自動で送り先を決める | H2: 機能仕様書。判定に使う値・判定の順序・判定できたときの送り先が定まっている | I2: 1 | J2: 基盤チーム | K2: 基盤チーム | L2: 認証の中核 | M2: 顧客IdPが複数ある前提で、ユーザが自分の顧客IdPにたどり着く唯一の手段 | N2: 対象 | O2: 新規: 機能追加 | P2: — | Q2: 未着手 | S2: F-AUTH-02
A3: HJ-03 | B3: HJ Keycloak-Brokerの作り込み | C3: 設計書の執筆 | D3: ログインの振り分け | E3: 顧客IdPの自動振り分け | F3: HRD：自社拡張の仕様書（判定ロジック・切替） | G3: 判定を行う自社拡張の入出力・動作条件・Keycloak-Brokerへの組み込み位置を決める | H3: 拡張の仕様書。入出力と、どのフローのどこに置くかが定まっている | I3: 2 | J3: 基盤チーム | K3: 基盤チーム | L3: 認証の中核 | M3: Keycloak-Brokerの標準機能では実現できず、自社拡張で作る必要がある | N3: 対象 | O3: 新規: 機能追加 | P3: — | Q3: 未着手 | S3: F-AUTH-02
A4: HB-F-AUTH-03 | B4: HB-F 機能仕様書 | C4: 設計書の執筆 | D4: ログインの振り分け | E4: 振り分け失敗時のパスワード入力への切替 | F4: 機能仕様書: 振り分けできないときのパスワード入力への切替 | G4: 顧客IdPを判定できなかったときに、パスワード入力へ切り替えて処理を続ける動き | H4: 機能仕様書。切り替える条件と、切り替えた後の扱いが定まっている | I4: 0.5 | J4: 基盤チーム | K4: 基盤チーム | L4: 事故防止 | M4: どの顧客か分からない状態でもユーザを止めないための逃げ道 | N4: 対象 | O4: 新規: 機能追加 | P4: — | Q4: 未着手 | S4: F-AUTH-03
A5: HB-F-AUTH-04 | B5: HB-F 機能仕様書 | C5: 設計書の執筆 | D5: ログインの振り分け | E5: 顧客IdPの選択（1 顧客に複数） | F5: 機能仕様書: 顧客IdPの選択画面 | G5: 1 つの顧客に顧客IdPが複数ある場合に、ユーザにどれを使うか選ばせる | H5: 機能仕様書。選ばせる条件と、並び順の決め方が定まっている | I5: 0.5 | J5: 基盤チーム | K5: 基盤チーム | L5: 認証の中核 | M5: グループ会社や部門ごとに認証システムを持つ顧客がいるため | N5: 対象 | O5: 新規: 機能追加 | P5: — | Q5: 未着手 | S5: F-AUTH-04
A6: HB-F-AUTH-05 | B6: HB 機能設計 | C6: 設計書の執筆 | D6: 顧客IdP 連携ログイン | E6: 顧客IdPへのログイン委譲（OIDC） | F6: 機能仕様書: 顧客IdP 連携ログイン（OIDC） | G6: 顧客が持っている認証システムに認証を委ね、その結果を受け取ってログインさせる機能（標準的な連携方式） | H6: 機能仕様書 1 本。委譲時に渡す情報・受け取る情報と、拒否された場合の扱いが定義されレビュー承認済み | I6: 0.5 | J6: 基盤チーム | K6: 基盤チーム | L6: 認証の中核 | M6: 顧客IdPへ委ねる中核で、これが無いと基盤の存在理由が無い | N6: 対象 | O6: 当初あり | P6: — | Q6: 未着手 | R6: ADR-033、U2 §2.2 | S6: F-AUTH-05
A7: HE-14 | B7: HE つなぎ目設計 | C7: 設計書の執筆 | D7: 顧客IdP 連携ログイン | E7: 顧客IdPへのログイン委譲（OIDC） | F7: 認証プロトコルIF（OIDCエンドポイント・クレーム） | G7: 標準方式の認証連携で、やり取りする情報の仕様。内訳: 認可エンドポイント / トークンエンドポイント / クレーム / ログアウト | H7: 仕様書。顧客IdPの情報と、渡す項目が定まっている | I7: 4 | J7: 基盤チーム | K7: 基盤チーム | L7: 認証の中核 | M7: 顧客IdPへ委ねる中核で、これが無いと基盤の存在理由が無い | N7: 対象 | O7: 当初あり | P7: — | Q7: 未着手 | S7: F-AUTH-05
A8: HJ-02a | B8: HJ Keycloak の作り込み | C8: 設計書の執筆 | D8: 顧客IdP 連携ログイン | E8: 顧客IdPへのログイン委譲（OIDC） | F8: 認証フローの組み立て順序（3 系統） | G8: ログイン処理の組み立て順序を決める（外部連携を受ける側の 3 系統） | H8: 処理順序の設計書。3 系統それぞれの分岐が図で示されている | I8: 1 | J8: 基盤チーム | K8: 基盤チーム | L8: 認証の中核 | M8: 顧客IdPへ委ねる中核で、これが無いと基盤の存在理由が無い | N8: 対象 | O8: 当初あり | P8: — | Q8: 未着手 | S8: F-AUTH-05
A9: HJ-10a | B9: HJ Keycloak の作り込み | C9: 設計書の執筆 | D9: 顧客IdP 連携ログイン | E9: 顧客IdPへのログイン委譲（OIDC） | F9: Keycloak-Brokerの設定値一覧 | G9: Keycloak-Brokerの設定値を決める（外部連携を受ける側） | H9: 設定値一覧。有効期間・回数制限などが数値で定まっている | I9: 2 | J9: 基盤チーム | K9: 基盤チーム | L9: 認証の中核 | M9: 顧客IdPへ委ねる中核で、これが無いと基盤の存在理由が無い | N9: 対象 | O9: 当初あり | P9: — | Q9: 未着手 | S9: F-AUTH-05
A10: HE-17 | B10: HE つなぎ目設計 | C10: 設計書の執筆 | D10: 顧客IdP 連携ログイン | E10: 顧客IdPへのログイン委譲（OIDC） | F10: 外部IF 顧客IdP（SAML/OIDC差分） | G10: 顧客IdPごとの接続仕様の差分整理 | H10: 差分表。製品ごとの違いが一覧化されている | I10: 2 | J10: 基盤チーム | K10: 基盤チーム | L10: 認証の中核 | M10: 【省略・吸収】HE-14 / HE-15 の認証プロトコル IF に吸収。人日は復活時のために残す | N10: 対象外：省略・吸収 | O10: 当初あり | P10: — | Q10: 未着手 | S10: F-AUTH-05
A11: GD-09 | B11: GD アプリ向けガイド | C11: ガイド・手順書の執筆 | D11: 顧客IdP 連携ログイン | E11: 顧客IdPへのログイン委譲（OIDC） | F11: 第3部 Webアプリ（BFF / SSR） | G11: サーバー側で処理を受け持つ形式のアプリ向けの実装手順。Keycloak-Broker の推奨形式 | H11: ガイド 1 章。推奨する理由と、この形式でしか使えない機能が明示されている | I11: 1 | J11: 基盤チーム | K11: 基盤チーム | L11: 認証の中核 | M11: 顧客IdPへ委ねる中核で、これが無いと基盤の存在理由が無い | N11: 対象 | O11: 当初あり | P11: — | Q11: 未着手 | S11: F-AUTH-05
A12: GD-10 | B12: GD アプリ向けガイド | C12: ガイド・手順書の執筆 | D12: 顧客IdP 連携ログイン | E12: 顧客IdPへのログイン委譲（OIDC） | F12: 第3部 SPA（ブラウザ） | G12: ブラウザだけで動く形式のアプリ向けの実装手順と、認める条件 | H12: ガイド 1 章。JWT をブラウザに保存してはいけない範囲と、使えない機能の制約が明示されている | I12: 1 | J12: 基盤チーム | K12: 基盤チーム | L12: 認証の中核 | M12: 顧客IdPへ委ねる中核で、これが無いと基盤の存在理由が無い | N12: 対象 | O12: 当初あり | P12: — | Q12: 未着手 | S12: F-AUTH-05
A13: GD-14 | B13: GD アプリ向けガイド | C13: ガイド・手順書の執筆 | D13: 顧客IdP 連携ログイン | E13: 顧客IdPへのログイン委譲（OIDC） | F13: 第4部 認可リクエスト | G13: ログインを開始するときにアプリが必ず付ける情報と、やってはいけない古い方式 | H13: ガイド 1 章。必須パラメータと禁止事項が判定可能な形で列挙されている | I13: 2 | J13: 基盤チーム | K13: 基盤チーム | L13: 認証の中核 | M13: 顧客IdPへ委ねる中核で、これが無いと基盤の存在理由が無い | N13: 対象 | O13: 当初あり | P13: — | Q13: 未着手 | S13: F-AUTH-05
A14: GD-15 | B14: GD アプリ向けガイド | C14: ガイド・手順書の執筆 | D14: 顧客IdP 連携ログイン | E14: 顧客IdPへのログイン委譲（OIDC） | F14: 第4部 JWT の取得・保存 | G14: 受け取ったJWT をどこに保存してよいか・いけないかの方針 | H14: ガイド 1 章。保存場所ごとの可否と理由が示されている | I14: 2 | J14: 基盤チーム | K14: 基盤チーム | L14: 認証の中核 | M14: 顧客IdPへ委ねる中核で、これが無いと基盤の存在理由が無い | N14: 対象 | O14: 当初あり | P14: — | Q14: 未着手 | S14: F-AUTH-05
A15: HB-F-AUTH-06 | B15: HB 機能設計 | C15: 設計書の執筆 | D15: 顧客IdP 連携ログイン | E15: 顧客IdPへのログイン委譲（SAML） | F15: 機能仕様書: 顧客IdP 連携ログイン（SAML） | G15: 顧客が持っている認証システムのうち、旧来の方式で連携する場合のログイン機能 | H15: 機能仕様書 1 本。旧方式特有の識別子の扱いと、標準方式との差分が定義されレビュー承認済み | I15: 0.5 | J15: 基盤チーム | K15: 基盤チーム | L15: 認証の中核 | M15: 顧客IdPへ委ねる中核で、これが無いと基盤の存在理由が無い | N15: 対象 | O15: 当初あり | P15: — | Q15: 未着手 | R15: ADR-031、U2 §2.7 | S15: F-AUTH-06
A16: HE-15 | B16: HE つなぎ目設計 | C16: 設計書の執筆 | D16: 顧客IdP 連携ログイン | E16: 顧客IdPへのログイン委譲（SAML） | F16: 認証プロトコルIF（SAMLメタデータ・Assertion） | G16: 旧方式の認証連携で、やり取りする情報の仕様。内訳: メタデータ / Assertion / シングルログアウト | H16: 仕様書。接続情報の受け渡し方と項目が定まっている | I16: 4 | J16: 基盤チーム | K16: 基盤チーム | L16: 認証の中核 | M16: 顧客IdPへ委ねる中核で、これが無いと基盤の存在理由が無い | N16: 対象 | O16: 当初あり | P16: — | Q16: 未着手 | S16: F-AUTH-06
A17: D-11 | B17: D 判断 | C17: 調査・計画 | D17: 顧客IdP 連携ログイン | E17: 顧客IdPへのログイン委譲（SAML） | F17: 旧方式の顧客IdPを登録するひな形 | G17: 旧方式の顧客IdPを登録するときのひな形を作る | H17: ひな形定義。項目の対応づけが定まっている | I17: 2 | J17: 基盤チーム | K17: 基盤チーム | L17: 認証の中核 | M17: 【省略・吸収】HE-15 認証プロトコル IF（SAML メタデータ・Assertion）に吸収。人日は復活時のために残す | N17: 対象外：省略・吸収 | O17: 当初あり | P17: — | Q17: 未着手 | S17: F-AUTH-06
A18: HB-F-AUTH-07 | B18: HB-F 機能仕様書 | C18: 設計書の執筆 | D18: 顧客IdP 連携ログイン | E18: 初回ログイン時のユーザ自動作成（JIT） | F18: 機能仕様書: 初回ログイン時のユーザ自動作成（JIT） | G18: 顧客IdP経由で初めてログインした人を、その場で Keycloak-Broker のユーザとして作る | H18: 機能仕様書。作る条件・持たせる項目・重複したときの扱いが定まっている | I18: 1 | J18: 基盤チーム | K18: 基盤チーム | L18: 認証の中核 | M18: これが無いとフェデレーションのログインが完了しない。Keycloak-Brokerの初回連携フローに直結する | N18: 対象 | O18: 新規: 機能追加 | P18: — | Q18: 未着手 | S18: F-PROV-01
A19: HB-F-PROV-02 | B19: HB-F 機能仕様書 | C19: 設計書の執筆 | D19: 顧客IdP 連携ログイン | E19: ログイン時の属性更新 | F19: 機能仕様書: ログイン時の属性更新 | G19: 2 回目以降のログインで、顧客側の最新の情報を使って属性を更新する | H19: 機能仕様書。更新する項目と、更新しない項目の区別が定まっている | I19: 0.5 | J19: 基盤チーム | K19: 基盤チーム | L19: 認証の中核 | M19: 属性が古いままだとアプリ側の判断が誤る | N19: 対象 | O19: 新規: 機能追加 | P19: — | Q19: 未着手 | S19: F-PROV-02
A20: HB-F-AUTH-09 | B20: HB-F 機能仕様書 | C20: 設計書の執筆 | D20: 顧客IdP 連携ログイン | E20: Keycloak-Broker と Keycloak-IdP の連携 | F20: 機能仕様書: Keycloak-IdP へのログイン委譲 | G20: Keycloak-Broker が Keycloak-IdP を顧客IdP の 1 つ（共有エントリ）として扱い、識別子の引き継ぎ・初回作成・追加認証結果（amr）の取り込みを行う | H20: 機能仕様書。渡す情報・受け取る情報・拒否時の扱い・2 回目以降は Keycloak-IdP を呼ばないことが定まっている | I20: 1 | J20: 基盤チーム | K20: 基盤チーム | L20: 認証の中核 | M20: 2 台構成に戻したため復活。顧客IdP を持たない顧客のログインはすべてここを通る | N20: 対象 | O20: 新規: 機能追加 | P20: — | Q20: 未着手 | S20: F-AUTH-09
A21: HE-23 | B21: HE つなぎ目設計 | C21: 設計書の執筆 | D21: 顧客IdP 連携ログイン | E21: Keycloak-Broker と Keycloak-IdP の連携 | F21: Keycloak-Broker ⇄ Keycloak-IdP 接続仕様（要求仕様としてアプリチームへ渡す） | G21: Keycloak-IdP 側に求める Client（broker-rp）・返す項目（tenant_id / username / amr）・login_hint の書式・ログアウト連鎖・セッション上限の同値（12 時間）・接続経路（閉域・単方向）を 1 冊にまとめる | H21: 接続仕様書。両チームが合意し、Keycloak-IdP 側の設定値がこの 1 冊で作れる | I21: 2.5 | J21: 基盤チーム | K21: 基盤チーム | L21: 認証の中核 | M21: U2 §2.2.2〜2.2.5 / 02a / U6 D-U6-06 の決定を接続仕様の形にする。アプリチームとの境界そのもの | N21: 対象 | O21: 新規: 機能追加 | P21: — | Q21: 未着手 | S21: F-AUTH-09
A22: HI-11 | B22: HI レビュー・合意 | C22: レビュー・合意 | D22: 顧客IdP 連携ログイン | E22: Keycloak-Broker と Keycloak-IdP の連携 | F22: 接続仕様のアプリチームとの合意 | G22: 接続仕様（HE-23）をアプリチームとレビューし、Keycloak-IdP 側の設定値と検証環境の提供時期を合意する | H22: 合意記録。設定値・検証環境の提供時期・連絡先が定まっている | I22: 1 | J22: 基盤チーム | K22: 基盤チーム | L22: 構成の前提 | M22: 合意が無いと結合試験（IT-16）が始められない | N22: 対象 | O22: 新規: 機能追加 | P22: — | Q22: 未着手 | S22: F-AUTH-09
A23: HB-F-AUTH-01 | B23: HB 機能設計 | C23: 設計書の執筆 | D23: パスワードによるログイン | E23: Keycloak-IdP 収容ユーザのログイン | F23: 機能仕様書: ローカルログイン（ID/PW） | G23: 本基盤の運用者が Keycloak-Broker に ID とパスワード＋WebAuthn で直接ログインする機能。顧客のユーザ分（Keycloak-IdP 収容）はアプリ側の仕様とし、本仕様書は運用者分のみ | H23: 機能仕様書 1 本。運用者の認証手段・失敗時にユーザへ返す内容が定義されレビュー承認済み（パスワード桁数等の顧客ユーザ向け規則は対象外） | I23: 0.5 | J23: 基盤チーム | K23: 基盤チーム | L23: 認証の中核 | M23: Keycloak-Broker にローカルで残るのは運用者だけ。顧客ユーザのパスワード規則は Keycloak-IdP（アプリ責務） | N23: 対象 | O23: 当初あり | P23: — | Q23: 未着手 | R23: U2 §2.3、P-07 | S23: F-AUTH-01
A24: HJ-10b | B24: HJ Keycloak の作り込み | C24: 設計書の執筆 | D24: パスワードによるログイン | E24: Keycloak-IdP 収容ユーザのログイン | F24: Keycloak-Brokerの設定値一覧（ユーザを直接収容する側） | G24: Keycloak-Brokerの設定値を決める（ユーザを直接収容する側） | H24: 設定値一覧。パスワード条件を含め数値で定まっている | I24: 2 | J24: 基盤チーム | K24: 基盤チーム | L24: 構成の前提 | M24: Keycloak-IdP 側の設定値はアプリチームが決める。本基盤が求める値は接続仕様（HE-23）に限る | N24: 対象外：Keycloak-IdP 側の責務 | O24: 当初あり | P24: — | Q24: 未着手 | S24: F-AUTH-01
A25: HJ-20 | B25: HJ Keycloak-Brokerの作り込み | C25: レビュー・合意 | D25: パスワードによるログイン | E25: Keycloak-IdP 側の引き渡しと責任分界 | F25: Keycloak-IdP 側の引き渡し範囲と責任分界の取り決め | G25: 基盤（ROSA）をどの状態まで作って渡すか、渡した後は誰が何を持つかを決める | H25: 合意記録。引き渡す状態・手順・渡した後の責任範囲が定まっている | I25: 1.5 | J25: 基盤チーム | K25: 基盤チーム | L25: 構成の前提 | M25: 基盤は基盤（ROSA）だけを作ってアプリチームへ引き渡す前提。境界が曖昧だと運用で揉める | N25: 対象 | O25: 新規: 機能追加 | P25: — | Q25: 未着手 | S25: F-AUTH-29
A26: D-21 | B26: D 判断 | C26: レビュー・合意 | D26: パスワードによるログイン | E26: Keycloak-IdP 側の引き渡しと責任分界 | F26: Keycloak-IdP 側の非機能責任表（可用性・復旧・監視・更新・鍵・ログ） | G26: 非機能要件ごとに Keycloak-IdP 側では誰が満たすかを表にする。本基盤は ROSA の引き渡しまで、以降はアプリ責務とする方針を明文化する | H26: 責任表。非機能要件の全行に Keycloak-IdP 側の担当が入っている | I26: 1.5 | J26: 基盤チーム | K26: 基盤チーム | L26: 構成の前提 | M26: 要件マッピングの「Keycloak-IdP 側」列の根拠。曖昧だと SLA と運用で揉める | N26: 対象 | O26: 新規: 非機能・運用 | P26: — | Q26: 未着手 | S26: F-AUTH-29
A27: HB-F-AUTH-10 | B27: HB 機能設計 | C27: 設計書の執筆 | D27: 多要素認証 | E27: 追加認証の利用 | F27: 機能仕様書: MFA認証（TOTP） | G27: スマートフォンアプリで生成する 6 桁の数字による追加認証 | H27: → 収載先: 多要素認証設計書。機能仕様書 1 本。桁ずれの許容範囲と、連続失敗時の扱いが定義されレビュー承認済み | I27: 0.5 | J27: 基盤チーム | K27: 基盤チーム | L27: 製品機能 | M27: 【Keycloak-IdP 側の責務】追加認証はKeycloak-Broker では行わない。フェデレーションのユーザは顧客IdP側、直接収容するユーザは Keycloak-IdP 側で行う。人日は復活時のために残す | N27: 対象外：Keycloak-IdP 側の責務 | O27: 当初あり | P27: — | Q27: 未着手 | R27: U7 D-U7-14 | S27: F-AUTH-10
A28: HB-F-AUTH-12 | B28: HB 機能設計 | C28: 設計書の執筆 | D28: 多要素認証 | E28: 追加認証の登録 | F28: 機能仕様書: MFAエンロール（TOTP） | G28: スマートフォンアプリの追加認証を初めて登録する画面の流れ | H28: → 収載先: 多要素認証設計書。機能仕様書 1 本。QR と手入力の両方を用意し、登録完了を確認してから有効化する手順が定義されレビュー承認済み | I28: 0.5 | J28: 基盤チーム | K28: 基盤チーム | L28: 製品機能 | M28: 【Keycloak-IdP 側の責務】追加認証はKeycloak-Broker では行わない。フェデレーションのユーザは顧客IdP側、直接収容するユーザは Keycloak-IdP 側で行う。人日は復活時のために残す | N28: 対象外：Keycloak-IdP 側の責務 | O28: 当初あり | P28: — | Q28: 未着手 | R28: U4 §4.4.2 | S28: F-AUTH-12
A29: HB-F-AUTH-21 | B29: HB-F 機能仕様書 | C29: 設計書の執筆 | D29: ログイン口の保護 | E29: ユーザの存在推測の防止 | F29: 機能仕様書: 振り分けの応答の同一化と試行回数の制限 | G29: 入力された識別子が実在するかどうかが応答の違いから分からないようにし、短時間の繰り返し試行を制限する | H29: 機能仕様書。同一化する応答の範囲・制限する回数と時間・制限にかかったときの表示が定まっている | I29: 1 | J29: 基盤チーム | K29: 基盤チーム | L29: 事故防止 | M29: Keycloak-Brokerはパスワードを持たないため連続失敗の締め出しは不要だが、振り分けは識別子を受け取るため実在の推測と総当たりが成立する。WAF は同じ送信元しか見ないので、分散して来ると効かない | N29: 対象 | O29: 新規: 機能追加 | P29: — | Q29: 未着手 | S29: F-AUTH-21
A30: HA-10 | B30: HA 全体・方式設計 | C30: 設計書の執筆 | D30: セッションとログアウト | E30: ログイン状態の保持とタイムアウト | F30: 認証：セッション管理方式設計（ログイン状態の保持・タイムアウト・ログアウト） | G30: ログイン状態をどう保持するかの全体方針 | H30: 方式設計。保持する場所と有効期間の考え方が定まっている | I30: 2 | J30: 共同 | K30: 共同 | L30: 横断（対象縮小） | M30: ログイン状態はKeycloak-Brokerが持つため全アプリ共通。アプリ内の保持方法はアプリが決めるが、全体の有効期間は 1 つの設定で全アプリに効くため共同で決める | N30: 対象 | O30: 当初あり | P30: — | Q30: 未着手 | S30: F-AUTH-23
A31: GD-21 | B31: GD アプリ向けガイド | C31: ガイド・手順書の執筆 | D31: セッションとログアウト | E31: ログイン状態の保持とタイムアウト | F31: 第4部 セッション管理 | G31: ログイン状態がどれくらい続くのか、いつ切れるのかの説明 | H31: ガイド 1 章。有効期間の一覧と、切れたときのアプリ側の動きが示されている | I31: 2 | J31: 基盤チーム | K31: 基盤チーム | L31: 認証の中核 | M31: 顧客IdPへ委ねる中核で、これが無いと基盤の存在理由が無い | N31: 対象 | O31: 当初あり | P31: — | Q31: 未着手 | S31: F-AUTH-23
A32: GD-24 | B32: GD アプリ向けガイド | C32: ガイド・手順書の執筆 | D32: セッションとログアウト | E32: ログイン状態の保持とタイムアウト | F32: 第4部 リフレッシュトークン | G32: JWT を延長するための仕組みと、不正利用が疑われた場合の挙動 | H32: ガイド 1 章。延長時の入れ替え要件と、失効したときのアプリ側の動きが示されている | I32: 1 | J32: 基盤チーム | K32: 基盤チーム | L32: 認証の中核 | M32: 顧客IdPへ委ねる中核で、これが無いと基盤の存在理由が無い | N32: 対象 | O32: 当初あり | P32: — | Q32: 未着手 | S32: F-AUTH-23
A33: GD-22 | B33: GD アプリ向けガイド | C33: ガイド・手順書の執筆 | D33: セッションとログアウト | E33: アプリへのログアウト連携 | F33: 第4部 ログアウト3方式の使い分け | G33: ログアウトの 3 つの方式の違いと、どれをいつ使うかの整理。1 つ実装すれば全アプリで切れる、という誤解を正す | H33: ガイド 1 章。3 方式の関係と責任分界が図で示されている | I33: 2 | J33: 基盤チーム | K33: 基盤チーム | L33: 認証の中核 | M33: 顧客IdPへ委ねる中核で、これが無いと基盤の存在理由が無い | N33: 対象 | O33: 当初あり | P33: — | Q33: 未着手 | S33: F-AUTH-24
A34: GD-23 | B34: GD アプリ向けガイド | C34: ガイド・手順書の執筆 | D34: セッションとログアウト | E34: アプリへのログアウト連携 | F34: 第4部 Back-Channel Logout受信実装 | G34: 他のアプリでのログアウトを受け取って自分のセッションも切る実装。受け取った通知の検証項目を含む | H34: ガイド 1 章。8 つの検証項目が列挙され、検証を省くと強制ログアウトの悪用が可能になる旨が警告されている | I34: 2 | J34: 基盤チーム | K34: 基盤チーム | L34: 認証の中核 | M34: 顧客IdPへ委ねる中核で、これが無いと基盤の存在理由が無い | N34: 対象 | O34: 当初あり | P34: — | Q34: 未着手 | S34: F-AUTH-24
A35: HC-04a | B35: HC 画面設計 | C35: 設計書の執筆 | D35: ログイン画面 | E35: ログイン画面の表示（ブランド・並び順） | F35: 画面仕様書: 識別子の入力画面（振り分け） | G35: 振り分けの起点となる、識別子を入力させる画面の項目・文言・遷移を決める | H35: 画面仕様書。入力項目・検証・次に進む条件・戻り方が定まっている | I35: 1 | J35: 基盤チーム | K35: 基盤チーム | L35: 認証の中核 | M35: 振り分け（HRD）は識別子の入力から始まるため、この画面が無いと成立しない | N35: 対象 | O35: 新規: 機能追加 | P35: — | Q35: 未着手 | S35: F-AUTH-25
A36: HC-04j | B36: HC 画面設計 | C36: 設計書の執筆 | D36: ログイン画面 | E36: エラー・案内画面（Keycloak-Broker） | F36: 画面仕様書: エラー・案内の表示画面（Keycloak-Broker） | G36: ログインや振り分けに失敗したときに何を表示し、どこへ誘導するかを決める | H36: 画面仕様書。表示する文言・出し分けの条件・誘導先が定まっている | I36: 1 | J36: 基盤チーム | K36: 基盤チーム | L36: 事故防止 | M36: 失敗したときの案内が無いとユーザが詰まる。文言はユーザの実在を推測させない書き方にする必要がある | N36: 対象 | O36: 新規: 機能追加 | P36: — | Q36: 未着手 | S36: F-AUTH-26
A37: D-22 | B37: D 判断 | C37: 調査・計画 | D37: ログイン画面 | E37: 利用規約への同意取得と記録 | F37: 同意取得の要否と方式の判断 | G37: 利用規約などへの同意をログイン画面で取るか、アプリ側で取るか、取らないかを顧客に確認して決める | H37: 決定記録。要否と、取る場合の場所と記録先が定まっている | I37: 0.5 | J37: 基盤チーム | K37: 基盤チーム | L37: 業務ルール依存 | M37: 要件未確定。顧客回答待ち | N37: 対象 | O37: 新規: 機能追加 | P37: — | Q37: 要件確認 | S37: F-AUTH-28
A38: HE-09 | B38: HE つなぎ目設計 | C38: 設計書の執筆 | D38: ユーザ管理 | E38: 顧客IdP からのユーザ情報の同期 | F38: SCIM 受信仕様（窓口・項目の対応づけ・絞り込み・削除の読み替え） | G38: 顧客の人事システムや認証システムからユーザ情報を受け取る窓口の仕様を決める。窓口はKeycloak-Broker（Keycloak）の上に立て、別の実行基盤は作らない | H38: 接続仕様。入口・認証方法・項目の対応・応答が定まっている | I38: 3 | J38: 基盤チーム | K38: アプリチーム | L38: 認証の中核 | M38: ログインを待たずにユーザを反映する唯一の経路。Keycloak-Brokerの標準機能は使わず自作または部品を使い、Keycloak-Brokerの上に載せる | N38: 対象 | O38: 新規: 機能追加 | P38: — | Q38: 未着手 | S38: F-PROV-03
A39: HB-F-PROV-03 | B39: HB-F 機能仕様書 | C39: 設計書の執筆 | D39: ユーザ管理 | E39: 顧客IdP からのユーザ情報の同期 | F39: 機能仕様書: SCIM 受信 ユーザの登録 | G39: 顧客システムからユーザの新規登録を受け取る | H39: 機能仕様書。受け取る項目と、重複したときの扱いが定まっている | I39: 1 | J39: 基盤チーム | K39: アプリチーム | L39: 認証の中核 | M39: 顧客システム連携の中核 | N39: 対象 | O39: 新規: 機能追加 | P39: — | Q39: 未着手 | S39: F-PROV-03
A40: HB-F-PROV-04 | B40: HB-F 機能仕様書 | C40: 設計書の執筆 | D40: ユーザ管理 | E40: 顧客IdP からのユーザ情報の同期 | F40: 機能仕様書: SCIM 受信 ユーザの更新 | G40: 顧客側からのユーザ情報の変更を受け取って反映する | H40: 機能仕様書。更新する項目と、競合したときの扱いが定まっている | I40: 0.75 | J40: 基盤チーム | K40: アプリチーム | L40: 認証の中核 | M40: 同上 | N40: 対象 | O40: 新規: 機能追加 | P40: — | Q40: 未着手 | S40: F-PROV-03
... A73: D-9.2 | B73: D 判断 | C73: 調査・計画 | D73: 監査・記録 | E73: 監査ログの出力と保管 | F73: 管理操作の記録の置き場所と保存年数 | G73: 誰が何をしたかの記録を、ブランドごとに分けて持つか中央に集めるかを決める | H73: 判断記録。保存年数との整合を含め、置き場所が定まっている | I73: 1 | J73: 基盤チーム | K73: 基盤チーム | L73: 画面のみ | M73: 【省略・吸収】HG-05 に吸収（監査ログの置き場所・保持年数）。人日は復活時のために残す | N73: 対象外：省略・吸収 | O73: 新規: 非機能・運用 | P73: — | Q73: 未着手 | S73: F-ADM-25
A74: HD-14 | B74: HD データ設計 | C74: 設計書の執筆 | D74: 監査・記録 | E74: 監査ログの出力と保管 | F74: 管理操作の記録テーブル定義（ブランド単位） | G74: 誰が何をしたかの記録を保持する表の定義。顧客のまとまりごとに分けて持つ | H74: 表定義。記録する項目と、他顧客の記録が混ざらない仕組みが定まっている | I74: 2 | J74: 基盤チーム | K74: 基盤チーム | L74: 改ざん防止 | M74: 【省略・吸収】② 詳細設計 DDD-07 で計上。人日は復活時のために残す | N74: 対象外：省略・吸収 | O74: 新規: 非機能・運用 | Q74: 未着手 | S74: F-ADM-25
A75: HK-07 | B75: HK 顧客提供成果物 | C75: ガイド・手順書の執筆 | D75: 監査・記録 | E75: 本人からの開示・削除請求への対応 | F75: 本人からの開示・削除請求への対応手順 | G75: 本人から求められたときに、保有しているデータを開示し、または消すまでの手順を決める | H75: 手順書。受付から回答までの期限・確認方法・記録の残し方が定まっている | I75: 1 | J75: 基盤チーム | K75: 基盤チーム | L75: 法令・契約 | M75: 顧客が本人対応の窓口になるため、本基盤側の手順が無いと顧客が答えられない | N75: 対象 | O75: 新規: 非機能・運用 | P75: — | Q75: 未着手 | S75: F-ADM-24
A76: HB-F-BAT-04 | B76: HB 機能設計 | C76: 設計書の執筆 | D76: 鍵・証明書管理 | E76: JWT 署名鍵の定期入れ替え | F76: 機能仕様書: JWT署名鍵ローテ | G76: JWT の署名に使う鍵を定期的に入れ替える処理。切り替え中も止めないための並走期間を含む | H76: → 収載先: 鍵・証明書管理設計書。機能仕様書 1 本。入れ替え周期・並走期間と、失敗時の手動手順が定義されレビュー承認済み | I76: 0.5 | J76: 基盤チーム | K76: 基盤チーム | L76: 事故防止 | M76: 入れ替えを止めると、漏れた鍵がいつまでも有効なままになる | N76: 対象 | O76: 新規: 非機能・運用 | P76: — | Q76: 未着手 | R76: ADR-045、DU-U7-02 | S76: F-BAT-04
A77: GD-18 | B77: GD アプリ向けガイド | C77: ガイド・手順書の執筆 | D77: 鍵・証明書管理 | E77: JWT 署名鍵の定期入れ替え | F77: 第4部 JWKS取得・鍵ローテ追随 | G77: 署名の検証に使う鍵の取得方法と、鍵が入れ替わっても止まらないための保持方法。鍵をアプリ内に直接書くことは禁止 | H77: ガイド 1 章。取得の頻度・保持期間・未知の鍵が来た場合の動き・取得できないときの継続方法が数値で示されている | I77: 2 | J77: 基盤チーム | K77: 基盤チーム | L77: 認証の中核 | M77: 顧客IdPへ委ねる中核で、これが無いと基盤の存在理由が無い | N77: 対象 | O77: 当初あり | P77: — | Q77: 未着手 | S77: F-BAT-04
A78: HB-F-BAT-05 | B78: HB 機能設計 | C78: 設計書の執筆 | D78: 鍵・証明書管理 | E78: アプリの接続用パスワードの定期入れ替え | F78: 機能仕様書: client_secretローテ | G78: アプリごとの接続用パスワードを定期的に入れ替える処理 | H78: → 収載先: 鍵・証明書管理設計書。機能仕様書 1 本。入れ替え周期と、切り替え中に接続が切れないための扱いが定義されレビュー承認済み | I78: 0.5 | J78: 基盤チーム | K78: 基盤チーム | L78: 事故防止 | M78: 入れ替えを止めると、漏れた鍵がいつまでも有効なままになる | N78: 対象 | O78: 新規: 非機能・運用 | P78: — | Q78: 未着手 | R78: D-U7-10b、DU-U7-12 | S78: F-BAT-05
A79: HB-F-BAT-07 | B79: HB 機能設計 | C79: 設計書の執筆 | D79: 鍵・証明書管理 | E79: 顧客IdP・本基盤の証明書の期限監視 | F79: 機能仕様書: 証明書期限監視・通知 | G79: 証明書の期限切れが近いものを検出して通知する処理 | H79: → 収載先: 鍵・証明書管理設計書。機能仕様書 1 本。通知するタイミングと、通知先が定義されレビュー承認済み | I79: 0.5 | J79: 基盤チーム | K79: 基盤チーム | L79: 事故防止 | M79: 切れると全顧客のログインが黙って止まるため、期限の監視は外せない | N79: 対象 | O79: 新規: 非機能・運用 | P79: — | Q79: 未着手 | R79: D-12 | S79: F-BAT-07
A80: HH-06 | B80: HH 運用設計 | C80: 設計書の執筆 | D80: 監視・検知 | E80: 不正なログインの兆候の検知 | F80: 運用設計：不正兆候の検知項目と通知 | G80: ログイン失敗の急増・同一送信元の連続試行・新しい顧客IdP からの大量の初回作成など、不正の兆候として見張る項目と通知先を決める。検知して知らせるまでとし、自動遮断はしない | H80: 項目一覧。検知の条件・閾値・通知先が定まっている | I80: 1 | J80: 基盤チーム | K80: 基盤チーム | L80: 事故防止 | M80: ADR-035 Phase 1a（検知通知のみ）。監視項目（HH-01〜03）とは別に不正の観点で持つ | N80: 対象 | O80: 新規: 非機能・運用 | P80: — | Q80: 未着手 | S80: F-INT-08
A81: HA-04 | B81: HA 全体・方式設計 | C81: 設計書の執筆 | D81: 非機能: システム構成 | E81: 全体構成（論理・物理） | F81: 構成図：全体構成図（論理・清書を含む） | G81: システム全体の構成を、機能のまとまりで表した図。清書（旧 G-4.1）を含む | H81: 論理構成図。主要な構成要素と関係が 1 枚で分かる | I81: 2 | J81: 基盤チーム | K81: 基盤チーム | L81: 横断（対象縮小） | M81: 方式は 1 機能でも 91 機能でも決める必要があり、対象が減っても消えない | N81: 対象 | O81: 当初あり | P81: — | Q81: 未着手 | S81: NF-ARC-01
A82: HA-05 | B82: HA 全体・方式設計 | C82: 設計書の執筆 | D82: 非機能: システム構成 | E82: ネットワーク構成 | F82: 構成図：全体構成図（物理・清書を含む） | G82: システム全体の構成を、実際の設備配置で表した図。清書（旧 G-4.1）を含む | H82: 物理構成図。設備の配置と接続経路が示されている | I82: 2 | J82: 基盤チーム | K82: 基盤チーム | L82: 横断（対象縮小） | M82: 分離は到達を防ぐものではなく「何が取れるか」を変えるもの。管理用の口はパスワードのハッシュを返さないが、DB を直接読めば全件取れる。ハッシュが持ち出されると元のパスワードが割り出され、ユーザが他所で使い回している分まで被害が広がる。分離すれば DB への経路そのものが存在しないため、これを構造的に防げる（2026-09-02 維持を決定） | N82: 対象 | O82: 当初あり | P82: — | Q82: 未着手 | S82: NF-ARC-02
A83: G-4.2 | B83: G 構成図 | C83: 設計書の執筆 | D83: 非機能: システム構成 | E83: ネットワーク構成 | F83: 構成図：ネットワーク詳細図 | G83: ネットワークの区画・経路・通信の許可範囲を図にする。使用する IP アドレス範囲は確定済みの値を用いる | H83: 構成図。閉域接続とイベント経路が反映されている | I83: 2 | J83: 基盤チーム | K83: 基盤チーム | L83: 被ってる気がする | M83: 分離は到達を防ぐものではなく「何が取れるか」を変えるもの。管理用の口はパスワードのハッシュを返さないが、DB を直接読めば全件取れる。ハッシュが持ち出されると元のパスワードが割り出され、ユーザが他所で使い回している分まで被害が広がる。分離すれば DB への経路そのものが存在しないため、これを構造的に防げる（2026-09-02 維持を決定） | N83: 対象 | O83: 新規: 非機能・運用 | P83: — | Q83: 未着手 | S83: NF-ARC-02
A84: HJ-17 | B84: HJ Keycloak の作り込み | C84: 設計書の執筆 | D84: 非機能: システム構成 | E84: クラスタ構成 | F84: 構成：クラスタ構成設計書（ノード群・配置制約・自動増減） | G84: 実行基盤の構成設計。サーバーの種類・台数・役割分担 | H84: 構成設計書。役割ごとの分離と増減の考え方が定まっている | I84: 1 | J84: 基盤チーム | K84: 基盤チーム | L84: 製品機能 | M84: Keycloak-Brokerをどう組むかは、ユーザ管理を誰が作るかとは無関係に決まる | N84: 対象 | O84: 新規: 自社構築 | P84: — | Q84: 未着手 | S84: NF-ARC-03
A85: HJ-19 | B85: HJ Keycloak の作り込み | C85: 設計書の執筆 | D85: 非機能: システム構成 | E85: クラスタ構成 | F85: 構成：クラスタ運用の境界と責任分界（ベンダー保守との分担） | G85: 実行基盤の運用について、委託先と自社の分担を整理する | H85: 分担表。どちらが何をするかが明確になっている | I85: 1 | J85: 基盤チーム | K85: 基盤チーム | L85: 製品機能 | M85: Keycloak-Brokerをどう組むかは、ユーザ管理を誰が作るかとは無関係に決まる | N85: 対象 | O85: 新規: 自社構築 | P85: — | Q85: 未着手 | S85: NF-ARC-03
A86: HJ-01a | B86: HJ Keycloak の作り込み | C86: 設計書の執筆 | D86: 非機能: システム構成 | E86: Realm・ブランド区画構成 | F86: Realm / Organizations 構成設計書 | G86: 顧客をまとめる単位と区画の構成を決める（外部連携を受ける側） | H86: 構成設計書。顧客の収容方法と区画の分け方が定まっている | I86: 4 | J86: 基盤チーム | K86: 基盤チーム | L86: 認証の中核 | M86: 顧客IdPへ委ねる中核で、これが無いと基盤の存在理由が無い | N86: 対象 | O86: 当初あり | P86: — | Q86: 未着手 | S86: NF-ARC-04
A87: HH-05 | B87: HH 運用設計 | C87: 設計書の執筆 | D87: 非機能: システム構成 | E87: 環境構成（本番 / stg / dev） | F87: 運用設計：環境設計書（本番 / stg / dev の構成差分） | G87: 本番・検証・開発の各環境の違いをまとめた設計書 | H87: 環境設計書。環境ごとの差分が一覧化されている | I87: 1 | J87: 基盤チーム | K87: 基盤チーム | L87: 運用に必須 | M87: 運用の手順が無いと、作っても回せない | N87: 対象 | O87: 新規: 非機能・運用 | P87: — | Q87: 未着手 | S87: NF-ARC-05
A88: HK-10 | B88: HK 顧客提供成果物 | C88: ガイド・手順書の執筆 | D88: 非機能: システム構成 | E88: 他組織との構成調整 | F88: 境界（WAF・NWFW）への要求仕様書／渡す相手: 境界を管理する組織 | G88: ログイン口の流量制限・署名鍵公開先の保護・管理画面の遮断・顧客IdP 向け外向き許可など、境界側に求める設定を要求仕様書にする | H88: 要求仕様書。要求ごとに値と根拠、確認方法が書かれている | I88: 1.5 | J88: 基盤チーム | K88: 基盤チーム | L88: 事故防止 | M88: WAF・DDoS は他組織が持つが、何を求めるかは本基盤の責務。HG-08 の「WAF 側で行う前提」の受け皿 | N88: 対象 | O88: 新規: 非機能・運用 | P88: — | Q88: 未着手 | S88: NF-ARC-06
A89: HD-01 | B89: HD データ設計 | C89: 設計書の執筆 | D89: 非機能: システム構成 | E89: データベース設計（Keycloak-Broker） | F89: データの全体構成図（Keycloak-Broker 側） | G89: どのデータがどこに保管されているかを 1 枚の図にする | H89: 構成図。保管先と保管内容が対応づいている | I89: 1 | J89: 基盤チーム | K89: 基盤チーム | L89: 構成の前提 | M89: Keycloak-Broker 側のみを対象とする。Keycloak-IdP 側は基盤だけ渡すためアプリチームの範囲 | N89: 対象 | O89: 新規: 機能追加 | P89: — | Q89: 未着手 | S89: NF-ARC-07
A90: HD-04 | B90: HD データ設計 | C90: 設計書の執筆 | D90: 非機能: システム構成 | E90: データベース設計（Keycloak-Broker） | F90: Keycloak-Brokerのスキーマの利用範囲整理（Keycloak-Broker 側） | G90: Keycloak-Brokerが持つ表のうち、触ってよい範囲と触らない範囲を明示する | H90: 整理結果。直接読み書きしてよい範囲が定まっている | I90: 1 | J90: 基盤チーム | K90: 基盤チーム | L90: 事故防止 | M90: 製品の表を直接触ると版を上げたときに壊れる。線引きが要る | N90: 対象 | O90: 新規: 機能追加 | P90: — | Q90: 未着手 | S90: NF-ARC-07
A91: HD-25 | B91: HD データ設計 | C91: 設計書の執筆 | D91: 非機能: システム構成 | E91: データベース設計（Keycloak-Broker） | F91: 索引・分割・チューニング方針（Keycloak-Broker 側） | G91: データベースの索引・大きな表の分割・接続の設定方針を決める | H91: 方針。索引の付け方と、接続数の上限の根拠が定まっている | I91: 1 | J91: 基盤チーム | K91: 基盤チーム | L91: 構成の前提 | M91: Keycloak-Brokerはデータベースが無いと動かない。設備量と性能の根拠になる | N91: 対象 | O91: 新規: 機能追加 | P91: — | Q91: 未着手 | S91: NF-ARC-07
... A148: HI-02 | B148: HI レビュー・合意 | C148: レビュー・合意 | D148: 非機能: 設計管理 | E148: 設計レビュー・説明会 | F148: 指摘対応・改訂（第1回） | G148: 1 回目の指摘に対応して設計書を直す | H148: 改訂済みの設計書。指摘がすべて処理されている | I148: 2 | J148: 基盤チーム | K148: 基盤チーム | L148: 横断（対象縮小） | M148: 対象が減るぶん縮むが、突き合わせと合意の場は必ず要る | N148: 対象 | O148: 当初あり | P148: HI-01 | Q148: 未着手 | S148: NF-MGT-06
A149: HI-03 | B149: HI レビュー・合意 | C149: レビュー・合意 | D149: 非機能: 設計管理 | E149: 設計レビュー・説明会 | F149: 単元間 整合性レビュー（第2回） | G149: 設計書間で矛盾がないかを通しで確認する（2 回目） | H149: レビュー記録。2 回目の指摘が一覧化されている | I149: 1 | J149: 基盤チーム | K149: 基盤チーム | L149: 横断（対象縮小） | M149: 設計書どうしの矛盾を潰す作業で、作る範囲を減らしても回数は減らない | N149: 対象 | O149: 新規: 自社構築 | Q149: 未着手 | S149: NF-MGT-06
A150: HI-04 | B150: HI レビュー・合意 | C150: レビュー・合意 | D150: 非機能: 設計管理 | E150: 設計レビュー・説明会 | F150: 指摘対応・改訂（第2回） | G150: 2 回目の指摘に対応して設計書を直す | H150: 改訂済みの設計書。2 回目の指摘がすべて処理されている | I150: 2 | J150: 基盤チーム | K150: 基盤チーム | L150: 横断（対象縮小） | M150: 設計書どうしの矛盾を潰す作業で、作る範囲を減らしても回数は減らない | N150: 対象 | O150: 新規: 自社構築 | Q150: 未着手 | S150: NF-MGT-06
A151: HI-05 | B151: HI レビュー・合意 | C151: レビュー・合意 | D151: 非機能: 設計管理 | E151: 設計レビュー・説明会 | F151: 単元間 整合性レビュー（第3回） | G151: 設計書間で矛盾がないかを通しで確認する（3 回目） | H151: レビュー記録。3 回目の指摘が一覧化されている | I151: 1 | J151: 基盤チーム | K151: 基盤チーム | L151: 横断（対象縮小） | M151: 設計書どうしの矛盾を潰す作業で、作る範囲を減らしても回数は減らない | N151: 対象 | O151: 新規: 自社構築 | Q151: 未着手 | S151: NF-MGT-06
A152: HI-06 | B152: HI レビュー・合意 | C152: レビュー・合意 | D152: 非機能: 設計管理 | E152: 設計レビュー・説明会 | F152: 指摘対応・改訂（第3回） | G152: 3 回目の指摘に対応して設計書を直す | H152: 改訂済みの設計書。3 回目の指摘がすべて処理されている | I152: 2 | J152: 基盤チーム | K152: 基盤チーム | L152: 横断（対象縮小） | M152: 設計書どうしの矛盾を潰す作業で、作る範囲を減らしても回数は減らない | N152: 対象 | O152: 新規: 自社構築 | Q152: 未着手 | S152: NF-MGT-06
A153: HI-07 | B153: HI レビュー・合意 | C153: レビュー・合意 | D153: 非機能: 設計管理 | E153: 設計レビュー・説明会 | F153: 単元間 整合性レビュー（第4回） | G153: 設計書間で矛盾がないかを通しで確認する（4 回目） | H153: レビュー記録。4 回目の指摘が一覧化されている | I153: 1 | J153: 基盤チーム | K153: 基盤チーム | L153: 横断（対象縮小） | M153: 設計書どうしの矛盾を潰す作業で、作る範囲を減らしても回数は減らない | N153: 対象 | O153: 新規: 自社構築 | Q153: 未着手 | S153: NF-MGT-06
A154: HI-08 | B154: HI レビュー・合意 | C154: レビュー・合意 | D154: 非機能: 設計管理 | E154: 設計レビュー・説明会 | F154: 指摘対応・改訂（第4回） | G154: 4 回目の指摘に対応して設計書を直す | H154: 改訂済みの設計書。4 回目の指摘がすべて処理されている | I154: 2 | J154: 基盤チーム | K154: 基盤チーム | L154: 横断（対象縮小） | M154: 設計書どうしの矛盾を潰す作業で、作る範囲を減らしても回数は減らない | N154: 対象 | O154: 新規: 自社構築 | Q154: 未着手 | S154: NF-MGT-06
A155: HI-09 | B155: HI レビュー・合意 | C155: レビュー・合意 | D155: 非機能: 設計管理 | E155: 設計レビュー・説明会 | F155: 単元間 整合性レビュー（第5回） | G155: 設計書間で矛盾がないかを通しで確認する（5 回目） | H155: レビュー記録。1 回目の指摘が解消されている | I155: 1 | J155: 基盤チーム | K155: 基盤チーム | L155: 横断（対象縮小） | M155: 対象が減るぶん縮むが、突き合わせと合意の場は必ず要る | N155: 対象 | O155: 当初あり | P155: HI-02 | Q155: 未着手 | S155: NF-MGT-06
A156: HI-10 | B156: HI レビュー・合意 | C156: レビュー・合意 | D156: 非機能: 設計管理 | E156: 設計レビュー・説明会 | F156: 指摘対応・改訂（第5回） | G156: 5 回目の指摘に対応して設計書を直す | H156: 改訂済みの設計書。残課題が明示されている | I156: 2 | J156: 基盤チーム | K156: 基盤チーム | L156: 横断（対象縮小） | M156: 対象が減るぶん縮むが、突き合わせと合意の場は必ず要る | N156: 対象 | O156: 当初あり | P156: HI-03 | Q156: 未着手 | S156: NF-MGT-06
A157: HK-03 | B157: HK 顧客提供成果物 | C157: ガイド・手順書の執筆 | D157: 非機能: 提供ドキュメント | E157: アプリ開発者向けガイド（共通部） | F157: アプリ側の実装ガイド（アプリ開発者向け）／渡す相手: 接続アプリ開発者 | G157: （廃止）アプリ開発者向けの実装ガイド。章ごとに分割したため、この行では作業しない | H157: 作業なし。分割先の各章で実施する | I157: 1 | J157: 基盤チーム | K157: 基盤チーム | L157: 法令・契約 | M157: 顧客への約束は機能の数では変わらない | N157: 対象 | O157: 新規: 非機能・運用 | P157: — | Q157: 未着手 | S157: NF-DOC-01
A158: HK-01 | B158: HK 顧客提供成果物 | C158: レビュー・合意 | D158: 非機能: 提供ドキュメント | E158: 顧客向け説明資料 | F158: 責任分界表／渡す相手: 全顧客（契約添付） | G158: 顧客と本基盤のどちらが何に責任を持つかを示す表 | H158: 責任分界表。契約に添付できる粒度で整理されている | I158: 2 | J158: 基盤チーム | K158: 基盤チーム | L158: 法令・契約 | M158: 顧客への約束は機能の数では変わらない | N158: 対象 | O158: 新規: 非機能・運用 | P158: — | Q158: 未着手 | S158: NF-DOC-02
A159: HK-09 | B159: HK 顧客提供成果物 | C159: ガイド・手順書の執筆 | D159: 非機能: 提供ドキュメント | E159: 顧客向け説明資料 | F159: サービス仕様書・制約事項一覧（ゾンビ窓/ログアウト限界/再認証の明示）／渡す相手: 全顧客 | G159: サービスの仕様と、利用上の制約をまとめた文書 | H159: 仕様書。止めてから完全に切れるまでの時間差など、注意すべき制約が明記されている | I159: 1 | J159: 基盤チーム | K159: 基盤チーム | L159: 顧客が行う | M159: 顧客への約束は機能の数では変わらない | N159: 対象 | O159: 新規: 非機能・運用 | P159: — | Q159: 未着手 | S159: NF-DOC-02

Sheet WBS(詳細設計_製造)
A1: ID | B1: 分類 | C1: 機能グループ | D1: 機能名 | E1: 項目 | F1: 概要・完了定義 | G1: 詳細設計 人日 | H1: 製造 人日 | I1: 内訳
A2: DDH-01 | B2: DD-H 自社拡張の詳細設計 | C2: ログインの振り分け | D2: 顧客IdPの自動振り分け | E2: 振り分けの判定ロジックの実装設計 | F2: 判定に使う値の取り出し方・照合の順序・見つからないときの分岐が実装できる粒度で書かれている | G2: 3
A3: DDI-01 | B3: DD-I 単体試験の仕様 | C3: ログインの振り分け | D3: 顧客IdPの自動振り分け | E3: 単体試験仕様: 振り分け | F3: 判定できる／できない／複数該当の観点と期待結果が定義されている | G3: 1
A4: MKC-01 | B4: MK-C 自社拡張の実装 | C4: ログインの振り分け | D4: 顧客IdPの自動振り分け | E4: 振り分けの自社拡張の実装 | F4: 入力された ID から送り先が決まり、実機で振り分く | H4: 5
A5: MKI-01 | B5: MK-I 単体試験の実施 | C5: ログインの振り分け | D5: 顧客IdPの自動振り分け | E5: 単体試験: 振り分け | F5: 試験仕様どおりに実施し、不具合が是正されている | H5: 2
A6: MKC-02 | B6: MK-C 自社拡張の実装 | C6: ログインの振り分け | D6: 振り分け失敗時のパスワード入力への切替 | E6: 切替の実装 | F6: 判定できないときにパスワード入力へ切り替わる | H6: 1.5
A7: MKB-01 | B7: MK-B Keycloak-Brokerの設定・構築 | C7: ログインの振り分け | D7: 顧客IdPの選択（1 顧客に複数） | E7: 顧客IdPの選択の設定 | F7: 複数ある場合に選択でき、並び順が設計どおりになる | H7: 1.5
A8: DDB-01 | B8: DD-B 機能の詳細設計 | C8: 顧客IdP 連携ログイン | D8: 顧客IdPへのログイン委譲（OIDC） | E8: OIDC フェデレーションの詳細設計 | F8: 顧客IdPの定義項目・属性の写し方・フローの配置場所が実装できる粒度で書かれている | G8: 4 | I8: 接続定義2+属性写像1+フロー配置1
A9: DDE-01 | B9: DD-E つなぎ目（IF）の詳細設計 | C9: 顧客IdP 連携ログイン | D9: 顧客IdPへのログイン委譲（OIDC） | E9: OIDC エンドポイントとクレームの実装レベル定義 | F9: 公開する入口・要求できる範囲・返す項目が一覧で確定している | G9: 3
A10: DDI-02 | B10: DD-I 単体試験の仕様 | C10: 顧客IdP 連携ログイン | D10: 顧客IdPへのログイン委譲（OIDC） | E10: 単体試験仕様: OIDC ログイン | F10: 初回・2 回目・属性変更・エラー応答の観点と期待結果が定義されている | G10: 2
A11: MKB-02 | B11: MK-B Keycloak-Brokerの設定・構築 | C11: 顧客IdP 連携ログイン | D11: 顧客IdPへのログイン委譲（OIDC） | E11: OIDC 顧客IdPの登録と属性の写し込み設定 | F11: ひな形と初期分の顧客IdPが登録され、属性が設計どおり写る | H11: 5 | I11: ひな形3+初期分2
A12: MKB-03 | B12: MK-B Keycloak-Brokerの設定・構築 | C12: 顧客IdP 連携ログイン | D12: 顧客IdPへのログイン委譲（OIDC） | E12: 認証フローの組み立て | F12: ログイン・初回連携・連携後の 3 系統のフローが構成され、実機で通る | H12: 4
A13: MKI-02 | B13: MK-I 単体試験の実施 | C13: 顧客IdP 連携ログイン | D13: 顧客IdPへのログイン委譲（OIDC） | E13: 単体試験: OIDC ログイン | F13: 試験仕様どおりに実施し、不具合が是正されている | H13: 3
A14: DDB-02 | B14: DD-B 機能の詳細設計 | C14: 顧客IdP 連携ログイン | D14: 顧客IdPへのログイン委譲（SAML） | E14: SAML フェデレーションの詳細設計 | F14: 顧客IdPの定義項目・署名の検証方法・属性の写し方が実装できる粒度で書かれている | G14: 3
A15: DDE-02 | B15: DD-E つなぎ目（IF）の詳細設計 | C15: 顧客IdP 連携ログイン | D15: 顧客IdPへのログイン委譲（SAML） | E15: SAML メタデータと Assertion の実装レベル定義 | F15: 交換する情報の項目と、必須・任意の区別が確定している | G15: 3
A16: DDI-03 | B16: DD-I 単体試験の仕様 | C16: 顧客IdP 連携ログイン | D16: 顧客IdPへのログイン委譲（SAML） | E16: 単体試験仕様: SAML ログイン | F16: 正常・署名不正・期限切れの観点と期待結果が定義されている | G16: 1.5
A17: MKB-04 | B17: MK-B Keycloak-Brokerの設定・構築 | C17: 顧客IdP 連携ログイン | D17: 顧客IdPへのログイン委譲（SAML） | E17: SAML 顧客IdPの登録と署名検証の設定 | F17: ひな形と初期分の顧客IdPが登録され、署名検証が動作する | H17: 4
A18: MKI-03 | B18: MK-I 単体試験の実施 | C18: 顧客IdP 連携ログイン | D18: 顧客IdPへのログイン委譲（SAML） | E18: 単体試験: SAML ログイン | F18: 試験仕様どおりに実施し、不具合が是正されている | H18: 2
A19: DDB-03 | B19: DD-B 機能の詳細設計 | C19: 顧客IdP 連携ログイン | D19: 初回ログイン時のユーザ自動作成（JIT） | E19: 初回作成の実装設計 | F19: 作る条件・持たせる項目・重複時の扱いと、フローのどこで動かすかが確定している | G19: 3
A20: DDI-04 | B20: DD-I 単体試験の仕様 | C20: 顧客IdP 連携ログイン | D20: 初回ログイン時のユーザ自動作成（JIT） | E20: 単体試験仕様: 初回作成 | F20: 初回・重複・項目不足の観点と期待結果が定義されている | G20: 1
A21: MKB-05 | B21: MK-B Keycloak-Brokerの設定・構築 | C21: 顧客IdP 連携ログイン | D21: 初回ログイン時のユーザ自動作成（JIT） | E21: 初回作成の実装 | F21: 初めてのログインでユーザが作られ、2 回目以降は作られない | H21: 3
A22: MKI-04 | B22: MK-I 単体試験の実施 | C22: 顧客IdP 連携ログイン | D22: 初回ログイン時のユーザ自動作成（JIT） | E22: 単体試験: 初回作成 | F22: 試験仕様どおりに実施し、不具合が是正されている | H22: 2
A23: DDB-04 | B23: DD-B 機能の詳細設計 | C23: 顧客IdP 連携ログイン | D23: ログイン時の属性更新 | E23: 属性更新の実装設計 | F23: 更新する項目・しない項目と、更新の起こし方が確定している | G23: 1.5
A24: MKB-06 | B24: MK-B Keycloak-Brokerの設定・構築 | C24: 顧客IdP 連携ログイン | D24: ログイン時の属性更新 | E24: 属性更新の実装 | F24: ログインのたびに設計どおりの項目が更新される | H24: 2
A25: DDB-18 | B25: DD-B 機能の詳細設計 | C25: 顧客IdP 連携ログイン | D25: Keycloak-Broker と Keycloak-IdP の連携 | E25: Keycloak-IdP 接続の詳細設計 | F25: 共有エントリの定義項目・属性の写し方（amr → 追加認証済みの印）・login_hint の渡し方・ログアウト連鎖の設定が実装できる粒度で書かれている | G25: 2
A26: DDE-11 | B26: DD-E つなぎ目（IF）の詳細設計 | C26: 顧客IdP 連携ログイン | D26: Keycloak-Broker と Keycloak-IdP の連携 | E26: 接続仕様の実装レベル定義（Keycloak-IdP 側へ渡す設定値） | F26: Keycloak-IdP 側の Client・返す項目・セッション上限（12 時間）・経路の設定値が一覧で確定し、アプリチームへ渡っている | G26: 1.5
A27: DDI-10 | B27: DD-I 単体試験の仕様 | C27: 顧客IdP 連携ログイン | D27: Keycloak-Broker と Keycloak-IdP の連携 | E27: 単体試験仕様: Keycloak-IdP 接続 | F27: 初回・2 回目（Keycloak-IdP を呼ばない）・追加認証済みの印・ログアウト連鎖・上限時間の観点と期待結果が定義されている | G27: 1
A28: MKA-20 | B28: MK-A 環境・基盤の構築 | C28: 顧客IdP 連携ログイン | D28: Keycloak-Broker と Keycloak-IdP の連携 | E28: Keycloak-IdP への閉域経路の構築（Keycloak-Broker 側） | F28: 閉域接続（PrivateLink）の受け口と名前解決が作られ、Keycloak-IdP 側と疎通する | H28: 3 | I28: 経路2+名前解決1
A29: MKB-30 | B29: MK-B Keycloak-Brokerの設定・構築 | C29: 顧客IdP 連携ログイン | D29: Keycloak-Broker と Keycloak-IdP の連携 | E29: Keycloak-IdP 接続の設定（共有エントリ・写し込み・ログアウト連鎖） | F29: 共有エントリが登録され、識別子が引き継がれ、追加認証の結果が写り、ログアウトが連鎖する | H29: 3
A30: MKI-19 | B30: MK-I 単体試験の実施 | C30: 顧客IdP 連携ログイン | D30: Keycloak-Broker と Keycloak-IdP の連携 | E30: 単体試験: Keycloak-IdP 接続 | F30: 試験仕様どおりに実施し、不具合が是正されている | H30: 2
A31: DDG-01 | B31: DD-G 基盤構成の実装設計 | C31: パスワードによるログイン | D31: Keycloak-IdP 側の引き渡しと責任分界 | E31: 引き渡す範囲と初期状態の取り決め | F31: どこまで作って渡すか・渡した後の責任の持ち方（D-21 責任表）・初期状態に何を入れるかが確定し、引き渡し仕様書として 1 冊になっている | G31: 2 | I31: ★基盤は基盤（ROSA）だけ作ってアプリへ引き渡す
A32: MKA-01 | B32: MK-A 環境・基盤の構築 | C32: パスワードによるログイン | D32: Keycloak-IdP 側の引き渡しと責任分界 | E32: Keycloak-IdP 用の基盤（ROSA）の構築 | F32: 既定の状態のクラスタが起動し、アプリチームがKeycloak-Brokerを載せられる | H32: 6 | I32: ★引き渡しまでが基盤の範囲
A33: MKJ-01 | B33: MK-J レビュー・受入・引き渡し | C33: パスワードによるログイン | D33: Keycloak-IdP 側の引き渡しと責任分界 | E33: アプリチームへの引き渡し | F33: 初期状態の確認が済み、引き渡し手順と責任分界が合意されている | H33: 2
A34: DDB-05 | B34: DD-B 機能の詳細設計 | C34: ログイン口の保護 | D34: ユーザの存在推測の防止 | E34: 応答の同一化と試行回数の制限の実装設計 | F34: 同一化する応答の範囲・数える単位・制限の回数と時間が確定している | G34: 1.5
A35: MKB-07 | B35: MK-B Keycloak-Brokerの設定・構築 | C35: ログイン口の保護 | D35: ユーザの存在推測の防止 | E35: 応答の同一化と試行回数の制限の実装 | F35: 実在の有無が応答から分からず、短時間の繰り返しが制限される | H35: 2
A36: MKI-05 | B36: MK-I 単体試験の実施 | C36: ログイン口の保護 | D36: ユーザの存在推測の防止 | E36: 単体試験: 応答の同一化と試行回数の制限 | F36: 実在・非実在の応答差が無いこと、制限が効くことを確認し、不具合が是正されている | H36: 1
A37: DDA-01 | B37: DD-A 共通・方式の実装仕様 | C37: セッションとログアウト | D37: ログイン状態の保持とタイムアウト | E37: ログイン状態の保持の実装仕様 | F37: 保持先・保持時間・無操作での切れ方・再ログインの条件が確定している | G37: 3
A38: DDI-05 | B38: DD-I 単体試験の仕様 | C38: セッションとログアウト | D38: ログイン状態の保持とタイムアウト | E38: 単体試験仕様: ログイン状態の保持 | F38: 時間経過・再開・強制切断の観点と期待結果が定義されている | G38: 1
A39: MKB-08 | B39: MK-B Keycloak-Brokerの設定・構築 | C39: セッションとログアウト | D39: ログイン状態の保持とタイムアウト | E39: ログイン状態の保持とタイムアウトの設定 | F39: 設計どおりの時間で切れ、再ログインを求められる | H39: 2
A40: MKI-06 | B40: MK-I 単体試験の実施 | C40: セッションとログアウト | D40: ログイン状態の保持とタイムアウト | E40: 単体試験: ログイン状態の保持 | F40: 試験仕様どおりに実施し、不具合が是正されている | H40: 1
A41: DDE-03 | B41: DD-E つなぎ目（IF）の詳細設計 | C41: セッションとログアウト | D41: アプリへのログアウト連携 | E41: ログアウト連携の実装仕様 | F41: 通知の宛先・内容・失敗時の再送と、アプリ側に求める受け口が確定している | G41: 3
A42: MKB-09 | B42: MK-B Keycloak-Brokerの設定・構築 | C42: セッションとログアウト | D42: アプリへのログアウト連携 | E42: ログアウト連携の設定 | F42: 1 箇所のログアウトで他のアプリにも通知が届く | H42: 2
A43: MKI-07 | B43: MK-I 単体試験の実施 | C43: セッションとログアウト | D43: アプリへのログアウト連携 | E43: 単体試験: ログアウト連携 | F43: 正常・宛先不達の観点で実施し、不具合が是正されている | H43: 1.5
A44: DDC-01 | B44: DD-C 画面の詳細設計 | C44: ログイン画面 | D44: ログイン画面の表示（ブランド・並び順） | E44: 画面の実装設計（差し替える範囲の特定） | F44: Keycloak-Brokerの既定画面のどこを差し替えるか、版を上げたときの作り直しの手間が確定している | G44: 2
A45: MKC-03 | B45: MK-C 自社拡張・画面の実装 | C45: ログイン画面 | D45: ログイン画面の表示（ブランド・並び順） | E45: 識別子の入力画面の実装 | F45: 設計どおりの画面が表示され、振り分けへ進む | H45: 3
A46: MKI-08 | B46: MK-I 単体試験の実施 | C46: ログイン画面 | D46: ログイン画面の表示（ブランド・並び順） | E46: 単体試験: 識別子の入力画面 | F46: 入力の検証・遷移・表示崩れの観点で実施し、不具合が是正されている | H46: 1
A47: DDC-02 | B47: DD-C 画面の詳細設計 | C47: ログイン画面 | D47: エラー・案内画面（Keycloak-Broker） | E47: エラー画面の文言と出し分けの実装設計 | F47: 表示する文言と出し分けの条件が、実在を推測させない形で確定している | G47: 1
A48: MKC-04 | B48: MK-C 自社拡張・画面の実装 | C48: ログイン画面 | D48: エラー・案内画面（Keycloak-Broker） | E48: エラー・案内画面の実装 | F48: 失敗の種類ごとに設計どおりの案内が出る | H48: 2
A49: DDE-04 | B49: DD-E つなぎ目（IF）の詳細設計 | C49: ユーザ管理 | D49: 顧客IdP からのユーザ情報の同期 | E49: 受信窓口の実装設計（入口・認証・応答） | F49: 入口の作り・呼び出し元の確認方法・応答と異常時の返し方が実装できる粒度で書かれている。窓口はKeycloak-Brokerの上に立てる（別の実行基盤は作らない） | G49: 4 | I49: 入口2+認証1+応答1
A50: DDI-06 | B50: DD-I 単体試験の仕様 | C50: ユーザ管理 | D50: 顧客IdP からのユーザ情報の同期 | E50: 単体試験仕様: 受信窓口 | F50: 登録・更新・削除・検索と、規格への適合の観点が定義されている | G50: 2
A51: MKE-01 | B51: MK-E つなぎ目（IF）の実装 | C51: ユーザ管理 | D51: 顧客IdP からのユーザ情報の同期 | E51: 受信窓口の実装 | F51: Keycloak-Brokerの上に立てた窓口で、顧客システムから登録・更新・削除・検索ができる | H51: 8 | I51: 部品の組み込み3+自作部分5
A52: MKI-09 | B52: MK-I 単体試験の実施 | C52: ユーザ管理 | D52: 顧客IdP からのユーザ情報の同期 | E52: 単体試験: 受信窓口 | F52: 試験仕様どおりに実施し、不具合が是正されている | H52: 3
A53: DDE-05 | B53: DD-E つなぎ目（IF）の詳細設計 | C53: ユーザ管理 | D53: 顧客IdP からのユーザ情報の同期 | E53: 更新の反映と競合の扱いの実装設計 | F53: 既にいるユーザを更新するときの項目の上書き規則と、競合したときの扱いが確定している | G53: 1
A54: DDE-06 | B54: DD-E つなぎ目（IF）の詳細設計 | C54: ユーザ管理 | D54: 顧客IdP からのユーザ情報の同期 | E54: 削除通知の読み替えの実装設計 | F54: 削除の通知を受けたときに消さずに止める読み替えの規則と、記録の残し方が確定している | G54: 1
A55: MKE-02 | B55: MK-E つなぎ目（IF）の実装 | C55: ユーザ管理 | D55: 顧客IdP からのユーザ情報の同期 | E55: 削除通知の読み替えの実装 | F55: 削除の通知でユーザが止まり、消えていないことを確認できる | H55: 1.5
A56: DDE-07 | B56: DD-E つなぎ目（IF）の詳細設計 | C56: ユーザ管理 | D56: 顧客IdP からのユーザ情報の同期 | E56: 項目の対応づけと絞り込みの実装設計 | F56: 受け取る項目の対応と、絞り込み・件数の区切りの実装方法が確定している | G56: 2
A57: DDD-01 | B57: DD-D データの詳細設計 | C57: ユーザ属性の統一 | D57: 顧客IdP から受け取る属性の名前の統一 | E57: 属性の宣言と変換規則の実装設計 | F57: 持たせる項目の宣言と、顧客ごとの変換規則の書き方が実装できる粒度で書かれている | G57: 3
A58: MKB-10 | B58: MK-B Keycloak-Brokerの設定・構築 | C58: ユーザ属性の統一 | D58: 顧客IdP から受け取る属性の名前の統一 | E58: 属性の宣言と変換の設定 | F58: 宣言した項目が保持され、顧客ごとの変換が設計どおり動く | H58: 3
A59: DDB-06 | B59: DD-B 機能の詳細設計 | C59: ユーザ属性の統一 | D59: ユーザの登録経路の区分 | E59: 登録経路の区分の実装設計 | F59: 区分の値と、どこで付けるかが確定している | G59: 1.5
A60: MKB-11 | B60: MK-B Keycloak-Brokerの設定・構築 | C60: ユーザ属性の統一 | D60: ユーザの登録経路の区分 | E60: 登録経路の区分の実装 | F60: 経路ごとに正しい区分が付く | H60: 1.5
A61: DDB-07 | B61: DD-B 機能の詳細設計 | C61: ユーザの停止・再開・消去 | D61: ユーザの停止（消さずに無効化） | E61: 停止と再開の実装設計 | F61: 止める条件・再開してよい条件・除外する条件が確定している | G61: 1.5
A62: MKB-12 | B62: MK-B Keycloak-Brokerの設定・構築 | C62: ユーザの停止・再開・消去 | D62: ユーザの停止（消さずに無効化） | E62: 停止と再開の実装 | F62: 削除通知で止まり、条件を満たす場合だけ再開できる | H62: 2
A63: DDB-08 | B63: DD-B 機能の詳細設計 | C63: ユーザの停止・再開・消去 | D63: 停止済みユーザの再開 | E63: 再開の条件判定の実装設計 | F63: 再開してよい条件と、誤って復活させないための除外条件が実装できる粒度で書かれている | G63: 0.5
A64: MKB-13 | B64: MK-B Keycloak-Brokerの設定・構築 | C64: ユーザの停止・再開・消去 | D64: 停止済みユーザの再開 | E64: 再開の実装 | F64: 条件を満たす場合だけ再開でき、除外条件に当たる場合は再開されない | H64: 1
A65: DDF-05 | B65: DD-F 定期処理の詳細設計 | C65: ユーザの停止・再開・消去 | D65: 長期未使用者の自動停止 | E65: 自動停止の実装仕様 | F65: 対象の抽出条件・除外条件・実行間隔・記録が確定している | G65: 1
A66: MKF-06 | B66: MK-F 定期処理の実装 | C66: ユーザの停止・再開・消去 | D66: 長期未使用者の自動停止 | E66: 自動停止の実装 | F66: 90 日ログインの無い対象ユーザだけが止まり、除外対象は止まらず、記録が残る | H66: 1.5
A67: DDD-02 | B67: DD-D データの詳細設計 | C67: ユーザの停止・再開・消去 | D67: 保存期限切れデータの消去 | E67: 保持期間と消去の実装設計 | F67: 対象の表ごとの保持年数・消去の起点・消去の順序と、消し残しの検出方法が確定している | G67: 1.5
A68: MKF-01 | B68: MK-F 定期処理の実装 | C68: ユーザの停止・再開・消去 | D68: 保存期限切れデータの消去 | E68: 消去処理の実装 | F68: 期限を過ぎたデータが自動で消え、消したことが記録に残る | H68: 2
A69: DDB-09 | B69: DD-B 機能の詳細設計 | C69: 顧客・組織管理 | D69: 顧客の作成 | E69: 顧客と顧客IdPの登録手順の実装設計 | F69: 登録する項目・順序・失敗時の戻し方が実装できる粒度で書かれている | G69: 2
A70: MKB-14 | B70: MK-B Keycloak-Brokerの設定・構築 | C70: 顧客・組織管理 | D70: 顧客の作成 | E70: 顧客登録の実装 | F70: ひな形から顧客を作成でき、初期状態が設計どおりになる | H70: 2
A71: DDB-10 | B71: DD-B 機能の詳細設計 | C71: 顧客・組織管理 | D71: 顧客の解約 | E71: 顧客解約時の処理の詳細設計 | F71: 停止・データの持ち出し・消去の順序と猶予期間が確定している | G71: 1.5
A72: MKB-15 | B72: MK-B Keycloak-Brokerの設定・構築 | C72: 顧客・組織管理 | D72: 顧客の解約 | E72: 顧客解約の処理の実装 | F72: 手順どおりに停止と消去ができる | H72: 1.5
A73: MKB-16 | B73: MK-B Keycloak-Brokerの設定・構築 | C73: 顧客IdP 管理 | D73: 顧客IdPの接続登録 | E73: 接続登録の実装 | F73: 受け取った情報から顧客IdPを登録でき、疎通確認まで通る | H73: 3
A74: DDB-11 | B74: DD-B 機能の詳細設計 | C74: 顧客IdP 管理 | D74: 接続設定の変更・証明書更新 | E74: 接続設定の変更と証明書更新の実装設計 | F74: 止めずに入れ替える順序と、切り戻しの手順が確定している | G74: 2
A75: MKB-17 | B75: MK-B Keycloak-Brokerの設定・構築 | C75: 顧客IdP 管理 | D75: 接続設定の変更・証明書更新 | E75: 証明書の無停止入れ替えの実装 | F75: 入れ替え中もログインが止まらないことを実機で確認できる | H75: 3
A76: DDF-01 | B76: DD-F 定期処理の詳細設計 | C76: 顧客IdP 管理 | D76: 顧客IdP の接続情報の自動追随 | E76: 接続情報の自動追随の実装仕様 | F76: 取り直す間隔・失敗時の再試行・追随できないときの通知先が確定している | G76: 1.5
A77: MKF-02 | B77: MK-F 定期処理の実装 | C77: 顧客IdP 管理 | D77: 顧客IdP の接続情報の自動追随 | E77: 接続情報の自動追随の実装 | F77: 相手側が証明書を入れ替えても自動で追随し、失敗時に通知が届く | H77: 2
A78: DDE-08 | B78: DD-E つなぎ目（IF）の詳細設計 | C78: JWT の発行 | D78: アプリへの JWT 発行 | E78: JWT に載せる項目の実装仕様 | F78: 項目ごとの生成規則・要求できる範囲との対応が実装できる粒度で書かれている | G78: 3
A79: DDI-07 | B79: DD-I 単体試験の仕様 | C79: JWT の発行 | D79: アプリへの JWT 発行 | E79: 単体試験仕様: JWT の内容 | F79: 項目の有無・値・範囲ごとの差分の観点と期待結果が定義されている | G79: 1
A80: MKB-19 | B80: MK-B Keycloak-Brokerの設定・構築 | C80: JWT の発行 | D80: アプリへの JWT 発行 | E80: JWT の項目生成の実装 | F80: 設計どおりの項目が入ったJWTが発行される | H80: 3
A81: MKI-10 | B81: MK-I 単体試験の実施 | C81: JWT の発行 | D81: アプリへの JWT 発行 | E81: 単体試験: JWT の内容 | F81: 試験仕様どおりに実施し、不具合が是正されている | H81: 1.5
A82: DDB-13 | B82: DD-B 機能の詳細設計 | C82: JWT の発行 | D82: システム間 JWT の発行 | E82: システム間 JWT の実装設計 | F82: 発行の条件・要求できる範囲・有効期限・失効のさせ方が実装できる粒度で書かれている | G82: 1.5
A83: MKB-21 | B83: MK-B Keycloak-Brokerの設定・構築 | C83: JWT の発行 | D83: システム間 JWT の発行 | E83: システム間 JWT の実装 | F83: システムとして入口を呼べる資格が発行でき、範囲外の呼び出しが拒否される | H83: 2
A84: MKI-12 | B84: MK-I 単体試験の実施 | C84: JWT の発行 | D84: システム間 JWT の発行 | E84: 単体試験: システム間 JWT | F84: 正常・範囲外・期限切れ・失効後の観点で実施し、不具合が是正されている | H84: 1
A85: DDD-03 | B85: DD-D データの詳細設計 | C85: 認可・権限判定 | D85: 顧客番号と基盤識別子の対応づけ | E85: 識別子の採番と対応づけの実装設計 | F85: 識別子の形式・重複の避け方・顧客番号との対応の持ち方が確定している | G85: 2
A86: MKB-18 | B86: MK-B Keycloak-Brokerの設定・構築 | C86: 認可・権限判定 | D86: 顧客番号と基盤識別子の対応づけ | E86: 識別子の採番と保持の実装 | F86: 設計どおりの識別子が付き、顧客番号と対応づく | H86: 2
A87: DDB-12 | B87: DD-B 機能の詳細設計 | C87: 認可・権限判定 | D87: 顧客越境の防止（Keycloak-Broker 側） | E87: 越境防止の実装設計 | F87: どこで判定し、弾いたときに何を記録するかが確定している | G87: 1.5
A88: MKB-20 | B88: MK-B Keycloak-Brokerの設定・構築 | C88: 認可・権限判定 | D88: 顧客越境の防止（Keycloak-Broker 側） | E88: 越境防止の実装 | F88: 他顧客の顧客IdPではログインできない | H88: 1.5
A89: MKI-11 | B89: MK-I 単体試験の実施 | C89: 認可・権限判定 | D89: 顧客越境の防止（Keycloak-Broker 側） | E89: 単体試験: 越境防止 | F89: 正しい組み合わせと誤った組み合わせで実施し、不具合が是正されている | H89: 1
A90: DDB-14 | B90: DD-B 機能の詳細設計 | C90: アプリ連携 | D90: アプリの接続登録（クライアント登録） | E90: アプリの接続登録の詳細設計 | F90: 登録項目のひな形・命名規則・接続情報の渡し方と入れ替えが確定している | G90: 2
A91: MKB-22 | B91: MK-B Keycloak-Brokerの設定・構築 | C91: アプリ連携 | D91: アプリの接続登録（クライアント登録） | E91: 接続登録のひな形の実装 | F91: ひな形からアプリを登録でき、接続情報が発行される | H91: 3
A92: MKI-13 | B92: MK-I 単体試験の実施 | C92: アプリ連携 | D92: アプリの接続登録（クライアント登録） | E92: 単体試験: アプリの接続登録 | F92: ひな形からの登録と接続確認を実施し、不具合が是正されている | H92: 1
A93: DDE-12 | B93: DD-E つなぎ目（IF）の詳細設計 | C93: アプリ連携 | D93: アプリ向け管理 API の公開 | E93: 管理 API の内部公開の実装仕様 | F93: 経路・呼び出し元の資格・許す操作の範囲・記録の項目が実装できる粒度で書かれている | G93: 1.5
A94: MKB-32 | B94: MK-B Keycloak-Brokerの設定・構築 | C94: アプリ連携 | D94: アプリ向け管理 API の公開 | E94: 管理 API の内部公開の構築 | F94: 内部経路からだけ呼べ、許した操作だけが通り、記録が残る | H94: 2
A95: DDB-15 | B95: DD-B 機能の詳細設計 | C95: 業務システムへの認証提供 | D95: 業務システムへの認証提供 | E95: 業務システム連携の実装設計 | F95: 交換する情報・署名の扱い・ログアウトの伝え方が実装できる粒度で書かれている | G95: 4
A96: DDI-08 | B96: DD-I 単体試験の仕様 | C96: 業務システムへの認証提供 | D96: 業務システムへの認証提供 | E96: 単体試験仕様: 業務システム連携 | F96: ログイン・ユーザの自動作成・ログアウトの観点と期待結果が定義されている | G96: 1
A97: MKB-23 | B97: MK-B Keycloak-Brokerの設定・構築 | C97: 業務システムへの認証提供 | D97: 業務システムへの認証提供 | E97: 業務システム連携の設定と実装 | F97: 業務システムへログインでき、相手側にユーザが作られる | H97: 4 | I97: 接続設定4+属性の受け渡し2
A98: MKI-14 | B98: MK-I 単体試験の実施 | C98: 業務システムへの認証提供 | D98: 業務システムへの認証提供 | E98: 単体試験: 業務システム連携 | F98: 試験仕様どおりに実施し、不具合が是正されている | H98: 2
A99: MKB-24 | B99: MK-B Keycloak-Brokerの設定・構築 | C99: 業務システムへの認証提供 | D99: 業務システム側のユーザ自動作成 | E99: 業務システム側のユーザ自動作成の設定 | F99: 初回ログインで相手側にユーザが作られ、渡した属性が反映される | H99: 2 | I99: 接続設定4+属性の受け渡し2
A100: MKB-25 | B100: MK-B Keycloak-Brokerの設定・構築 | C100: 業務システムへの認証提供 | D100: 業務システムから他アプリへの連携 | E100: 他アプリへの連携の設定 | F100: 業務システムにログインした状態から他のアプリを呼べる | H100: 1
...

Sheet WBS(テスト)
A1: 区分 | B1: ID | C1: 機能グループ | D1: 機能名 | E1: テスト項目 | F1: テスト観点 | G1: 人日 | H1: 対応要件 | I1: 前提
A2: A 結合 | B2: IT-01 | C2: 顧客IdP 連携ログイン | D2: 顧客IdPへのログイン委譲（OIDC） | E2: 顧客IdPとのつなぎ目（OIDC） | F2: 接続情報の自動取得ができる／署名鍵を取得して検証に使える／要求できる範囲と返る項目が仕様どおり／相手側がエラーを返したときにユーザへ正しく伝わる／相手側の応答が遅いときに設計した時間で打ち切る／相手側の署名鍵が入れ替わったときに追随できる | G2: 4 | H2: FR-FED-001〜004 / FR-INT-001・002・003 | I2: 検証用の顧客IdPが用意できていること
A3: A 結合 | B3: IT-02 | C3: 顧客IdP 連携ログイン | D3: 顧客IdPへのログイン委譲（SAML） | E3: 顧客IdPとのつなぎ目（SAML） | F3: 接続情報の交換ができる／正しい署名を受け入れる／署名が不正なものを拒否する／期限切れの主張を拒否する／暗号化された主張を復号できる／ユーザを指す値の形式が仕様どおり／時計のずれをどこまで許すかが設計どおり | G3: 4 | H3: FR-FED-005 / FR-INT-004 | I3: 検証用の旧方式の認証システムが用意できていること
A4: A 結合 | B4: IT-03 | C4: パスワードによるログイン | D4: Keycloak-IdP 側の引き渡しと責任分界 | E4: Keycloak-IdP 側の基盤の引き渡し状態の確認 | F4: 既定の状態で起動する／アプリチームがKeycloak-Brokerを載せられる状態にある／引き渡す範囲が取り決めどおり／渡した後の責任範囲が文書で確認できる | G4: 2 | H4: NFR-OPS-012 | I4: 引き渡し範囲の取り決めが合意されていること
A5: A 結合 | B5: IT-04 | C5: ユーザ管理 | D5: 顧客IdP からのユーザ情報の同期 | E5: 顧客システムからの受信窓口とKeycloak-Brokerのつなぎ目 | F5: 登録・更新・削除・検索がKeycloak-Brokerに反映される／呼び出し元の確認に失敗したとき受け付けない／項目の対応づけが設計どおりに効く／一度に多くの件数が来たときの区切り方が仕様どおり／途中で失敗したときに中途半端な状態が残らない／同じ要求が二度来ても結果が変わらない | G5: 5 | H5: FR-USER-003 / FR-FED-009 | I5: 受信窓口の実装が完了していること
A6: A 結合 | B6: IT-05 | C6: 認可・権限判定 | D6: 顧客番号と基盤識別子の対応づけ | E6: 識別子の採番と対応づけ | F6: 設計した形式の識別子が付く／重複しない／一度付いた値が変わらない／顧客側の番号と対応づく／アプリから一意に指せる | G6: 2 | H6: FR-AUTHZ-001 | I6: A 結合の前提が揃っていること
A7: A 結合 | B7: IT-06 | C7: JWT の発行 | D7: システム間 JWT の発行 | E7: システム間 JWT の発行と失効 | F7: システムとして入口を呼べる資格が発行される／要求した範囲だけが許可される／範囲外の呼び出しが拒否される／有効期限が切れたら使えない／失効させたら直ちに使えない／顧客システム連携の呼び出し元がこの資格で確認できる | G7: 2 | H7: FR-AUTH-004 / FR-AUTHZ-005 | I7: A 結合の前提が揃っていること
A8: A 結合 | B8: IT-07 | C8: アプリ連携 | D8: アプリの接続登録（クライアント登録） | E8: アプリとのつなぎ目（接続情報・JWT） | F8: ひな形からアプリを登録できる／接続情報の公開先が仕様どおりに読める／署名鍵の公開先が読める／アプリ側でJWT を検証できる／接続用パスワードを入れ替えてもアプリが追随できる | G8: 4 | H8: FR-INT-002・003・006 / FR-AUTH-002・003 | I8: クライアント登録のひな形ができていること
A9: A 結合 | B9: IT-08 | C9: 業務システムへの認証提供 | D9: 業務システムへの認証提供 | E9: 業務システムとのつなぎ目 | F9: 旧方式で情報を交換できる／渡した属性が相手側に反映される／相手側でユーザが自動作成される／ログアウトが相手側へ伝わる／Keycloak-Broker で止めたユーザが相手側で使えなくなる | G9: 4 | H9: FR-FED-006 / FR-INT-004 | I9: 業務システムの検証環境が用意できていること
A10: A 結合 | B10: IT-09 | C10: 監査・記録 | D10: 監査ログの出力と保管 | E10: 記録の出力と全体の共通基盤への集約 | F10: 設計した項目が設計した形式で出る／欠落せずに共通基盤へ届く／個人情報が伏せられている／遅延したときに順序と重複がどうなるかが設計どおり／保持年数の設定が効いている／共通基盤側で必要な条件で引ける | G10: 4 | H10: FR-INT-008 / NFR-OPS-003・004 / NFR-COMP-007・010 | I10: 共通基盤への出力経路が開通していること
A11: A 結合 | B11: IT-10 | C11: 非機能: システム構成 | D11: 全体構成（論理・物理） | E11: 構成図と実機の一致 | F11: 図に描いた要素がすべて実機にある／実機にあって図に無いものが無い／経路が図のとおり／差分があれば図を直す | G11: 1.5 | H11: — | I11: 構築が完了していること
A12: A 結合 | B12: IT-11 | C12: 非機能: システム構成 | D12: ネットワーク構成 | E12: ネットワーク経路の疎通と遮断 | F12: 外部の入口からKeycloak-Brokerまで通る／外向きの通信が許可した範囲だけ通る／名前解決が経路ごとに設計どおりに解決する／外部に出さない経路が塞がっている／管理用の経路が限定された元からだけ通る | G12: 4 | H12: NFR-SEC-011・016・017・018 | I12: ネットワークの構築と境界組織との接続が完了していること
A13: A 結合 | B13: IT-12 | C13: 非機能: システム構成 | D13: Realm・ブランド区画構成 | E13: 区画の分離 | F13: 区画をまたいでユーザが見えない／発行元の値が区画ごとに設計どおり／区画ごとの設定が独立している／一方の設定変更が他方に影響しない | G13: 2 | H13: FR-AUTHZ-008 / FR-ADMIN-009 | I13: 区画の構築が完了していること
... A95: I テスト共通 | B95: TE-06 | C95: 非機能: 設計管理 | D95: 設計レビュー・説明会 | E95: テスト計画・仕様の作成とレビュー | F95: 基本設計の全機能に試験が対応している／要件との対応がとれている／合否の基準が数値で書かれている／関係者の承認が取れている | G95: 8 | H95: — | I95: 基本設計が承認されていること

Sheet 運用（定常）
A1: 区分 | B1: ID | C1: 作業 | D1: 内容 | E1: 頻度 | F1: 1 回の工数（時間） | G1: 初年度 回数 | H1: 初年度 人日 | I1: 定常 回数 | J1: 定常 人日 | K1: 担当
A2: 日次 | B2: OPD-01 | C2: 監視の確認と一次対応 | D2: 通知された内容を確認し、一次対応するか担当へ引き継ぐ | E2: 毎営業日 | F2: 0.5 | G2: 250 | H2: 15.6 | I2: 250 | J2: 15.6 | K2: 基盤チーム
A3: 日次 | B3: OPD-02 | C3: 定期処理の結果確認 | D3: 前夜に動いた定期処理が正常に終わったかを確認する | E3: 毎営業日 | F3: 0.25 | G3: 250 | H3: 7.8 | I3: 250 | J3: 7.8 | K3: 基盤チーム
A4: 週次 | B4: OPW-01 | C4: 通知の見直し | D4: 誤検知や取りこぼしを見て、閾値と宛先を調整する | E4: 週 1 回 | F4: 1 | G4: 50 | H4: 6.2 | I4: 50 | J4: 6.2 | K4: 基盤チーム
A5: 週次 | B5: OPW-02 | C5: 変更の確認 | D5: 申請された設定変更を確認し、適用の可否を判断する | E5: 週 1 回 | F5: 1 | G5: 50 | H5: 6.2 | I5: 50 | J5: 6.2 | K5: 基盤チーム
A6: 週次 | B6: OPW-03 | C6: 脆弱性情報の確認 | D6: Keycloak-Brokerと使っている部品の脆弱性情報を確認し、対応要否を判断する | E6: 週 1 回 | F6: 1 | G6: 50 | H6: 6.2 | I6: 50 | J6: 6.2 | K6: 基盤チーム
A7: 月次 | B7: OPM-01 | C7: サービスレベルの集計と報告 | D7: 稼働率と応答時間を集計し、顧客向けの報告を作る | E7: 月 1 回 | F7: 4 | G7: 12 | H7: 6 | I7: 12 | J7: 6 | K7: 基盤チーム
A8: 月次 | B8: OPM-02 | C8: 使用量の確認と増強判断 | D8: ユーザ数・顧客IdP数・データ量の伸びを見て、増強の要否を判断する | E8: 月 1 回 | F8: 2 | G8: 12 | H8: 3 | I8: 12 | J8: 3 | K8: 基盤チーム
A9: 月次 | B9: OPM-03 | C9: 控えの取得確認と抜き取り復元 | D9: 控えが取れていることを確認し、抜き取りで復元できることを確かめる | E9: 月 1 回 | F9: 4 | G9: 12 | H9: 6 | I9: 12 | J9: 6 | K9: 基盤チーム
A10: 月次 | B10: OPM-04 | C10: 運用者アカウントの棚卸し | D10: 運用に使うアカウントと権限を確認し、不要なものを止める | E10: 月 1 回 | F10: 2 | G10: 12 | H10: 3 | I10: 12 | J10: 3 | K10: 基盤チーム
A11: 月次 | B11: OPM-05 | C11: 費用の確認 | D11: 想定と実績の差を確認し、増えている要因を調べる | E11: 月 1 回 | F11: 2 | G11: 12 | H11: 3 | I11: 12 | J11: 3 | K11: 基盤チーム
A12: 月次 | B12: OPM-06 | C12: 記録の保全確認 | D12: 監査ログが共通基盤に欠けずに貯まっていることを確認する | E12: 月 1 回 | F12: 2 | G12: 12 | H12: 3 | I12: 12 | J12: 3 | K12: 基盤チーム
A13: 四半期 | B13: OPQ-01 | C13: 手順書の見直し | D13: 実施した作業をもとに手順書を直す | E13: 四半期 1 回 | F13: 8 | G13: 4 | H13: 4 | I13: 4 | J13: 4 | K13: 基盤チーム
... A29: 随時 | B29: OPS-07 | C29: 設定変更の適用 | D29: 承認された設定変更を適用し、記録を残す | E29: 月 4 件想定 | F29: 2 | G29: 48 | H29: 12 | I29: 48 | J29: 12 | K29: 基盤チーム
C30: 合計 | H30: =SUM(H2:H29) -> 207.5 | J30: =SUM(J2:J29) -> 185.7

Sheet 機能名一覧
A1: 系統 | B1: 機能グループ | C1: 機能名 | D1: 機能ID | E1: 概要 | F1: 基盤 | G1: アプリ | H1: 行数 | I1: 人日 | J1: うち対象
A2: 認証 | B2: ログインの振り分け | C2: 顧客IdPの自動振り分け | D2: F-AUTH-02 | E2: ログイン画面で入力された ID から、その人がどの顧客IdPのユーザかを判定し、自動で振り分ける | F2: ○ | G2: - | H2: 2 | I2: 3 | J2: 3
A3: 認証 | B3: ログインの振り分け | C3: 振り分け失敗時のパスワード入力への切替 | D3: F-AUTH-03 | E3: 顧客IdPを判定できなかったときに、パスワード入力欄に切り替えて処理を続ける逃げ道 | F3: ○ | G3: - | H3: 1 | I3: 0.5 | J3: 0.5
A4: 認証 | B4: ログインの振り分け | C4: 顧客IdPの選択（1 顧客に複数） | D4: F-AUTH-04 | E4: 1 つの顧客に顧客IdPが複数ある場合に、ユーザにどれを使うか選ばせる | F4: ○ | G4: - | H4: 1 | I4: 0.5 | J4: 0.5
A5: 認証 | B5: 顧客IdP 連携ログイン | C5: 顧客IdPへのログイン委譲（OIDC） | D5: F-AUTH-05 | E5: 顧客が持つ認証システムに OIDC で認証を委ね、その結果を受け取ってログインさせる | F5: ○ | G5: - | H5: 9 | I5: 15.5 | J5: 13.5
A6: 認証 | B6: 顧客IdP 連携ログイン | C6: 顧客IdPへのログイン委譲（SAML） | D6: F-AUTH-06 | E6: 顧客が持つ認証システムに SAML で認証を委ね、その結果を受け取ってログインさせる | F6: ○ | G6: - | H6: 3 | I6: 6.5 | J6: 4.5
A7: 認証 | B7: 顧客IdP 連携ログイン | C7: 初回ログイン時のユーザ自動作成（JIT） | D7: F-PROV-01 | E7: 顧客IdP経由で初めてログインした人を、その場で Keycloak-Broker のユーザとして作成する | F7: ○ | G7: - | H7: 1 | I7: 1 | J7: 1
A8: 認証 | B8: 顧客IdP 連携ログイン | C8: ログイン時の属性更新 | D8: F-PROV-02 | E8: 2 回目以降のログインで、顧客側の最新情報を使って属性を更新する | F8: ○ | G8: - | H8: 1 | I8: 0.5 | J8: 0.5
A9: 認証 | B9: 顧客IdP 連携ログイン | C9: 初回ログイン時の権限側への識別子連携 | D9: F-PROV-14 | E9: 初めてログインした人の識別子を、権限を管理する側へ知らせる | F9: - | G9: ○ | H9: 0 | I9: 0 | J9: 0
A10: 認証 | B10: 顧客IdP 連携ログイン | C10: 初回ログイン時の権限側の受け皿作成 | D10: F-PROV-15 | E10: 権限を管理する側に、まだ権限が設定されていないユーザの受け皿となる行を作る | F10: - | G10: ○ | H10: 0 | I10: 0 | J10: 0
A11: 認証 | B11: 顧客IdP 連携ログイン | C11: Keycloak-Broker と Keycloak-IdP の連携 | D11: F-AUTH-09 | E11: Keycloak-Broker から見て Keycloak-IdP を顧客IdP の 1 つ（共有エントリ）として接続する。識別子の引き継ぎ・追加認証結果の取り込み・ログアウト連鎖・セッション上限の同値を含む。Keycloak-IdP 側の Client・Realm 設定は要求仕様としてアプリチームへ渡す（2026-09-07 復活: 2 台構成に戻したため） | F11: ○ | G11: △ | H11: 3 | I11: 4.5 | J11: 4.5
A12: 認証 | B12: パスワードによるログイン | C12: Keycloak-IdP 収容ユーザのログイン | D12: F-AUTH-01 | E12: 顧客側に認証システムが無い顧客のユーザが Keycloak-IdP に、本基盤の運用者が Keycloak-Broker に、ID とパスワードで直接ログインする。顧客のユーザ分は Keycloak-IdP 側（アプリ責務）、運用者分は本基盤 | F12: ○ | G12: △ | H12: 2 | I12: 2.5 | J12: 0.5
A13: 認証 | B13: パスワードによるログイン | C13: Keycloak-IdP 側の引き渡しと責任分界 | D13: F-AUTH-29 | E13: 本基盤が Keycloak-IdP 用の基盤（ROSA）をどこまで作って渡すか、渡した後の非機能を誰が持つかの取り決め。**機能ではなく合意事項**だが、作業の受け皿として機能名の位置に置く | F13: ○ | G13: △ | H13: 2 | I13: 3 | J13: 3
... A132: 非機能 | B132: 非機能: 提供ドキュメント | C132: 顧客向け説明資料 | D132: NF-DOC-02 | E132: 責任分界・サービス仕様・制約事項など、契約に添えて顧客へ渡す資料 | F132: ○ | G132: - | H132: 2 | I132: 3 | J132: 3
A134: 合計 | H134: =SUM(H2:H132) -> 158 | I134: =SUM(I2:I132) -> 233.5 | J134: =SUM(J2:J132) -> 220.5

Sheet サマリ(工程別)
A1: 機能グループ | B1: 機能名 | C1: ① 基本設計 | D1: ② 詳細設計 | E1: ③ 製造 | F1: ④ テスト | G1: 合計 | H1: ②③④ 行数
A2: ログインの振り分け | B2: 顧客IdPの自動振り分け | C2: =SUMIFS('WBS(基本設計)'!$I$2:$I$159,'WBS(基本設計)'!$E$2:$E$159,$B2,'WBS(基本設計)'!$N$2:$N$159,"対象") -> 3 | D2: =SUMIF('WBS(詳細設計_製造)'!$D$2:$D$182,$B2,'WBS(詳細設計_製造)'!$G$2:$G$182) -> 4 | E2: =SUMIF('WBS(詳細設計_製造)'!$D$2:$D$182,$B2,'WBS(詳細設計_製造)'!$H$2:$H$182) -> 7 | F2: =SUMIF('WBS(テスト)'!$D$2:$D$95,$B2,'WBS(テスト)'!$G$2:$G$95) -> 8 | G2: =SUM(C2:F2) -> 22 | H2: =COUNTIF('WBS(詳細設計_製造)'!$D$2:$D$182,$B2)+COUNTIF('WBS(テスト)'!$D$2:$D$95,$B2) -> 6
A3: ログインの振り分け | B3: 振り分け失敗時のパスワード入力への切替 | C3: =SUMIFS('WBS(基本設計)'!$I$2:$I$159,'WBS(基本設計)'!$E$2:$E$159,$B3,'WBS(基本設計)'!$N$2:$N$159,"対象") -> 0.5 | D3: =SUMIF('WBS(詳細設計_製造)'!$D$2:$D$182,$B3,'WBS(詳細設計_製造)'!$G$2:$G$182) -> 0 | E3: =SUMIF('WBS(詳細設計_製造)'!$D$2:$D$182,$B3,'WBS(詳細設計_製造)'!$H$2:$H$182) -> 1.5 | F3: =SUMIF('WBS(テスト)'!$D$2:$D$95,$B3,'WBS(テスト)'!$G$2:$G$95) -> 1 | G3: =SUM(C3:F3) -> 3 | H3: =COUNTIF('WBS(詳細設計_製造)'!$D$2:$D$182,$B3)+COUNTIF('WBS(テスト)'!$D$2:$D$95,$B3) -> 2
A4: ログインの振り分け | B4: 顧客IdPの選択（1 顧客に複数） | C4: =SUMIFS('WBS(基本設計)'!$I$2:$I$159,'WBS(基本設計)'!$E$2:$E$159,$B4,'WBS(基本設計)'!$N$2:$N$159,"対象") -> 0.5 | D4: =SUMIF('WBS(詳細設計_製造)'!$D$2:$D$182,$B4,'WBS(詳細設計_製造)'!$G$2:$G$182) -> 0 | E4: =SUMIF('WBS(詳細設計_製造)'!$D$2:$D$182,$B4,'WBS(詳細設計_製造)'!$H$2:$H$182) -> 1.5 | F4: =SUMIF('WBS(テスト)'!$D$2:$D$95,$B4,'WBS(テスト)'!$G$2:$G$95) -> 1 | G4: =SUM(C4:F4) -> 3 | H4: =COUNTIF('WBS(詳細設計_製造)'!$D$2:$D$182,$B4)+COUNTIF('WBS(テスト)'!$D$2:$D$95,$B4) -> 2
A5: 顧客IdP 連携ログイン | B5: 顧客IdPへのログイン委譲（OIDC） | C5: =SUMIFS('WBS(基本設計)'!$I$2:$I$159,'WBS(基本設計)'!$E$2:$E$159,$B5,'WBS(基本設計)'!$N$2:$N$159,"対象") -> 13.5 | D5: =SUMIF('WBS(詳細設計_製造)'!$D$2:$D$182,$B5,'WBS(詳細設計_製造)'!$G$2:$G$182) -> 9 | E5: =SUMIF('WBS(詳細設計_製造)'!$D$2:$D$182,$B5,'WBS(詳細設計_製造)'!$H$2:$H$182) -> 12 | F5: =SUMIF('WBS(テスト)'!$D$2:$D$95,$B5,'WBS(テスト)'!$G$2:$G$95) -> 19 | G5: =SUM(C5:F5) -> 53.5 | H5: =COUNTIF('WBS(詳細設計_製造)'!$D$2:$D$182,$B5)+COUNTIF('WBS(テスト)'!$D$2:$D$95,$B5) -> 10
A6: 顧客IdP 連携ログイン | B6: 顧客IdPへのログイン委譲（SAML） | C6: =SUMIFS('WBS(基本設計)'!$I$2:$I$159,'WBS(基本設計)'!$E$2:$E$159,$B6,'WBS(基本設計)'!$N$2:$N$159,"対象") -> 4.5 | D6: =SUMIF('WBS(詳細設計_製造)'!$D$2:$D$182,$B6,'WBS(詳細設計_製造)'!$G$2:$G$182) -> 7.5 | E6: =SUMIF('WBS(詳細設計_製造)'!$D$2:$D$182,$B6,'WBS(詳細設計_製造)'!$H$2:$H$182) -> 6 | F6: =SUMIF('WBS(テスト)'!$D$2:$D$95,$B6,'WBS(テスト)'!$G$2:$G$95) -> 14 | G6: =SUM(C6:F6) -> 32 | H6: =COUNTIF('WBS(詳細設計_製造)'!$D$2:$D$182,$B6)+COUNTIF('WBS(テスト)'!$D$2:$D$95,$B6) -> 8
A7: 顧客IdP 連携ログイン | B7: 初回ログイン時のユーザ自動作成（JIT） | C7: =SUMIFS('WBS(基本設計)'!$I$2:$I$159,'WBS(基本設計)'!$E$2:$E$159,$B7,'WBS(基本設計)'!$N$2:$N$159,"対象") -> 1 | D7: =SUMIF('WBS(詳細設計_製造)'!$D$2:$D$182,$B7,'WBS(詳細設計_製造)'!$G$2:$G$182) -> 4 | E7: =SUMIF('WBS(詳細設計_製造)'!$D$2:$D$182,$B7,'WBS(詳細設計_製造)'!$H$2:$H$182) -> 5 | F7: =SUMIF('WBS(テスト)'!$D$2:$D$95,$B7,'WBS(テスト)'!$G$2:$G$95) -> 2 | G7: =SUM(C7:F7) -> 12 | H7: =COUNTIF('WBS(詳細設計_製造)'!$D$2:$D$182,$B7)+COUNTIF('WBS(テスト)'!$D$2:$D$95,$B7) -> 5
A8: 顧客IdP 連携ログイン | B8: ログイン時の属性更新 | C8: =SUMIFS('WBS(基本設計)'!$I$2:$I$159,'WBS(基本設計)'!$E$2:$E$159,$B8,'WBS(基本設計)'!$N$2:$N$159,"対象") -> 0.5 | D8: =SUMIF('WBS(詳細設計_製造)'!$D$2:$D$182,$B8,'WBS(詳細設計_製造)'!$G$2:$G$182) -> 1.5 | E8: =SUMIF('WBS(詳細設計_製造)'!$D$2:$D$182,$B8,'WBS(詳細設計_製造)'!$H$2:$H$182) -> 2 | F8: =SUMIF('WBS(テスト)'!$D$2:$D$95,$B8,'WBS(テスト)'!$G$2:$G$95) -> 1 | G8: =SUM(C8:F8) -> 5 | H8: =COUNTIF('WBS(詳細設計_製造)'!$D$2:$D$182,$B8)+COUNTIF('WBS(テスト)'!$D$2:$D$95,$B8) -> 3
A9: 顧客IdP 連携ログイン | B9: Keycloak-Broker と Keycloak-IdP の連携 | C9: =SUMIFS('WBS(基本設計)'!$I$2:$I$159,'WBS(基本設計)'!$E$2:$E$159,$B9,'WBS(基本設計)'!$N$2:$N$159,"対象") -> 4.5 | D9: =SUMIF('WBS(詳細設計_製造)'!$D$2:$D$182,$B9,'WBS(詳細設計_製造)'!$G$2:$G$182) -> 4.5 | E9: =SUMIF('WBS(詳細設計_製造)'!$D$2:$D$182,$B9,'WBS(詳細設計_製造)'!$H$2:$H$182) -> 8 | F9: =SUMIF('WBS(テスト)'!$D$2:$D$95,$B9,'WBS(テスト)'!$G$2:$G$95) -> 7 | G9: =SUM(C9:F9) -> 24 | H9: =COUNTIF('WBS(詳細設計_製造)'!$D$2:$D$182,$B9)+COUNTIF('WBS(テスト)'!$D$2:$D$95,$B9) -> 8
A10: パスワードによるログイン | B10: Keycloak-IdP 収容ユーザのログイン | C10: =SUMIFS('WBS(基本設計)'!$I$2:$I$159,'WBS(基本設計)'!$E$2:$E$159,$B10,'WBS(基本設計)'!$N$2:$N$159,"対象") -> 0.5 | D10: =SUMIF('WBS(詳細設計_製造)'!$D$2:$D$182,$B10,'WBS(詳細設計_製造)'!$G$2:$G$182) -> 0 | E10: =SUMIF('WBS(詳細設計_製造)'!$D$2:$D$182,$B10,'WBS(詳細設計_製造)'!$H$2:$H$182) -> 0 | F10: =SUMIF('WBS(テスト)'!$D$2:$D$95,$B10,'WBS(テスト)'!$G$2:$G$95) -> 0 | G10: =SUM(C10:F10) -> 0.5 | H10: =COUNTIF('WBS(詳細設計_製造)'!$D$2:$D$182,$B10)+COUNTIF('WBS(テスト)'!$D$2:$D$95,$B10) -> 0
A11: パスワードによるログイン | B11: Keycloak-IdP 側の引き渡しと責任分界 | C11: =SUMIFS('WBS(基本設計)'!$I$2:$I$159,'WBS(基本設計)'!$E$2:$E$159,$B11,'WBS(基本設計)'!$N$2:$N$159,"対象") -> 3 | D11: =SUMIF('WBS(詳細設計_製造)'!$D$2:$D$182,$B11,'WBS(詳細設計_製造)'!$G$2:$G$182) -> 2 | E11: =SUMIF('WBS(詳細設計_製造)'!$D$2:$D$182,$B11,'WBS(詳細設計_製造)'!$H$2:$H$182) -> 8 | F11: =SUMIF('WBS(テスト)'!$D$2:$D$95,$B11,'WBS(テスト)'!$G$2:$G$95) -> 2 | G11: =SUM(C11:F11) -> 15 | H11: =COUNTIF('WBS(詳細設計_製造)'!$D$2:$D$182,$B11)+COUNTIF('WBS(テスト)'!$D$2:$D$95,$B11) -> 4
A12: ログイン口の保護 | B12: ユーザの存在推測の防止 | C12: =SUMIFS('WBS(基本設計)'!$I$2:$I$159,'WBS(基本設計)'!$E$2:$E$159,$B12,'WBS(基本設計)'!$N$2:$N$159,"対象") -> 1 | D12: =SUMIF('WBS(詳細設計_製造)'!$D$2:$D$182,$B12,'WBS(詳細設計_製造)'!$G$2:$G$182) -> 1.5 | E12: =SUMIF('WBS(詳細設計_製造)'!$D$2:$D$182,$B12,'WBS(詳細設計_製造)'!$H$2:$H$182) -> 3 | F12: =SUMIF('WBS(テスト)'!$D$2:$D$95,$B12,'WBS(テスト)'!$G$2:$G$95) -> 3 | G12: =SUM(C12:F12) -> 8.5 | H12: =COUNTIF('WBS(詳細設計_製造)'!$D$2:$D$182,$B12)+COUNTIF('WBS(テスト)'!$D$2:$D$95,$B12) -> 4
A13: セッションとログアウト | B13: ログイン状態の保持とタイムアウト | C13: =SUMIFS('WBS(基本設計)'!$I$2:$I$159,'WBS(基本設計)'!$E$2:$E$159,$B13,'WBS(基本設計)'!$N$2:$N$159,"対象") -> 5 | D13: =SUMIF('WBS(詳細設計_製造)'!$D$2:$D$182,$B13,'WBS(詳細設計_製造)'!$G$2:$G$182) -> 4 | E13: =SUMIF('WBS(詳細設計_製造)'!$D$2:$D$182,$B13,'WBS(詳細設計_製造)'!$H$2:$H$182) -> 3 | F13: =SUMIF('WBS(テスト)'!$D$2:$D$95,$B13,'WBS(テスト)'!$G$2:$G$95) -> 6 | G13: =SUM(C13:F13) -> 18 | H13: =COUNTIF('WBS(詳細設計_製造)'!$D$2:$D$182,$B13)+COUNTIF('WBS(テスト)'!$D$2:$D$95,$B13) -> 5
... A80: 非機能: 提供ドキュメント | B80: 顧客向け説明資料 | C80: =SUMIFS('WBS(基本設計)'!$I$2:$I$159,'WBS(基本設計)'!$E$2:$E$159,$B80,'WBS(基本設計)'!$N$2:$N$159,"対象") -> 3 | D80: =SUMIF('WBS(詳細設計_製造)'!$D$2:$D$182,$B80,'WBS(詳細設計_製造)'!$G$2:$G$182) -> 0 | E80: =SUMIF('WBS(詳細設計_製造)'!$D$2:$D$182,$B80,'WBS(詳細設計_製造)'!$H$2:$H$182) -> 0 | F80: =SUMIF('WBS(テスト)'!$D$2:$D$95,$B80,'WBS(テスト)'!$G$2:$G$95) -> 0 | G80: =SUM(C80:F80) -> 3 | H80: =COUNTIF('WBS(詳細設計_製造)'!$D$2:$D$182,$B80)+COUNTIF('WBS(テスト)'!$D$2:$D$95,$B80) -> 0
A82: 合計 | C82: =SUM(C2:C80) -> 220.5 | D82: =SUM(D2:D80) -> 184 | E82: =SUM(E2:E80) -> 276.5 | F82: =SUM(F2:F80) -> 345 | G82: =SUM(G2:G80) -> 1026 | H82: =SUM(H2:H80) -> 275
